Workbook
Name agua_consumo: #REF!
Name agua_consumo: #REF!
Name pp_anual26: #REF!
Name pp_anual26: #REF!

Sheet tabla
A1: anexo
A2: 2026-01
A3: 2026-02
A4: 2026-03
A5: 2026-04
A6: 2026-05
A7: 2026-06
A8: 2026-07
A9: 2026-08
A10: 2026-09
A11: 2026-10
A12: 2026-11
... A20: sin identificar

Sheet pres
B2: PRESUPUESTO X DISTRIBUIR | C2: 60116
B4: agua potable 2026-01 | C4: =5908.3-1200 -> 4708.3
C5: =SUM(C2:C4) -> 64824.3

Sheet consumo_agua
H1: recibo | I1: 4713.4 | L1: 4636.5 | O1: 5266.7 | R1: 2972.4 | U1: 3793.1 | X1: 3876.4 | AA1: 4708.3
H2: m3 conteo | I2: =$G$203 -> 1262.229 | J2: <promedio | L2: =J203 -> 1115.961 | M2: <promedio | O2: =M203 -> 824.779 | P2: <promedio | R2: =P203 -> 1035.538 | U2: =S203 -> 1272.95 | X2: =V203 -> 1302.895 | AA2: =Y203 -> 1519.337
H3: c.u. x m3 | I3: =ROUND(I1/I2,4) -> 3.7342 | L3: =ROUND(L1/L2,4) -> 4.1547 | O3: =ROUND(O1/O2,4) -> 6.3856 | R3: =ROUND(R1/R2,4) -> 2.8704 | U3: =ROUND(U1/U2,4) -> 2.9798 | X3: =ROUND(X1/X2,4) -> 2.9752 | AA3: =ROUND(AA1/AA2,4) -> 3.0989
A4: JUNTA DE PROPIETARIOS DEL EDIFICIO MULTIFAMILIAR " PACIFIK OCEAN TOWER"
A5: Historico - consumo de agua
A7: DEPAF | B7: MAYO | C7: consumo> | D7: JUNIO | E7: consumo> | F7: JULIO | G7: consumo> | H7: AGOSTO | I7: PEN-agua | J7: consumo> | K7: SET | L7: PEN-agua | M7: consumo> | N7: OCT | O7: PEN-agua | P7: consumo> | Q7: NOV | R7: PEN-agua | S7: consumo> | T7: DIC | U7: PEN-agua | V7: consumo> | W7: 46023 | X7: PEN-agua | Y7: consumo> | Z7: 46054 | AA7: PEN-agua
A8: DEPA-101 | B8: 800 | C8: =D8-B8 -> 21 | D8: 821 | E8: =F8-D8 -> 22 | F8: 843 | G8: =H8-F8 -> 27 | H8: 870 | I8: =ROUND(G8*$I$3,2) -> 100.82 | J8: =K8-H8 -> 23 | K8: 893 | L8: =ROUND(J8*$L$3,2) -> 95.56 | M8: =N8-K8 -> 18 | N8: 911 | O8: =ROUND(M8*$O$3,2) -> 114.94 | P8: =Q8-N8 -> 19 | Q8: 930 | R8: =ROUND(P8*$R$3,2) -> 54.54 | S8: =+T8-Q8 -> 22 | T8: 952 | U8: =ROUND(S8*$U$3,2) -> 65.56 | V8: =+W8-T8 -> 24 | W8: 976 | X8: =V8*$X$3 -> 71.4048 | Y8: =+Z8-W8 -> 23 | Z8: 999 | AA8: =ROUND(Y8*$AA$3,2) -> 71.27
A9: DEPA-102 | B9: 287 | C9: =D9-B9 -> 7 | D9: 294 | E9: =F9-D9 -> 4 | F9: 298 | G9: =H9-F9 -> 7 | H9: 305 | I9: =ROUND(G9*$I$3,2) -> 26.14 | J9: =K9-H9 -> 4 | K9: 309 | L9: =ROUND(J9*$L$3,2) -> 16.62 | M9: =N9-K9 -> 3 | N9: 312 | O9: =ROUND(M9*$O$3,2) -> 19.16 | P9: =Q9-N9 -> 3 | Q9: 315 | R9: =ROUND(P9*$R$3,2) -> 8.61 | S9: =+T9-Q9 -> 2 | T9: 317 | U9: =ROUND(S9*$U$3,2) -> 5.96 | V9: =+W9-T9 -> 2 | W9: 319 | X9: =V9*$X$3 -> 5.9504 | Y9: =+Z9-W9 -> 4 | Z9: 323 | AA9: =ROUND(Y9*$AA$3,2) -> 12.4
A10: DEPA-103 | B10: 51 | C10: =D10-B10 -> 0 | D10: 51 | E10: =F10-D10 -> 0 | F10: 51 | G10: =H10-F10 -> 0 | H10: 51 | I10: =ROUND(G10*$I$3,2) -> 0 | J10: =K10-H10 -> 0 | K10: 51 | L10: =ROUND(J10*$L$3,2) -> 0 | M10: =N10-K10 -> 0 | N10: 51 | O10: =ROUND(M10*$O$3,2) -> 0 | P10: =Q10-N10 -> 0 | Q10: 51 | R10: =ROUND(P10*$R$3,2) -> 0 | S10: =+T10-Q10 -> 0 | T10: 51 | U10: =ROUND(S10*$U$3,2) -> 0 | V10: =+W10-T10 -> 0 | W10: 51 | X10: =V10*$X$3 -> 0 | Y10: =+Z10-W10 -> 0 | Z10: 51 | AA10: =ROUND(Y10*$AA$3,2) -> 0
A11: DEPA-104 | B11: 327 | C11: =D11-B11 -> 5 | D11: 332 | E11: =F11-D11 -> 6 | F11: 338 | G11: =H11-F11 -> 7 | H11: 345 | I11: =ROUND(G11*$I$3,2) -> 26.14 | J11: =K11-H11 -> 5 | K11: 350 | L11: =ROUND(J11*$L$3,2) -> 20.77 | M11: =N11-K11 -> 5 | N11: 355 | O11: =ROUND(M11*$O$3,2) -> 31.93 | P11: =Q11-N11 -> 9 | Q11: 364 | R11: =ROUND(P11*$R$3,2) -> 25.83 | S11: =+T11-Q11 -> 8 | T11: 372 | U11: =ROUND(S11*$U$3,2) -> 23.84 | V11: =+W11-T11 -> 12 | W11: 384 | X11: =V11*$X$3 -> 35.7024 | Y11: =+Z11-W11 -> 12 | Z11: 396 | AA11: =ROUND(Y11*$AA$3,2) -> 37.19
A12: DEPA-105 | B12: 532 | C12: =D12-B12 -> 10 | D12: 542 | E12: =F12-D12 -> 12 | F12: 554 | G12: =H12-F12 -> 8 | H12: 562 | I12: =ROUND(G12*$I$3,2) -> 29.87 | J12: =K12-H12 -> 13 | K12: 575 | L12: =ROUND(J12*$L$3,2) -> 54.01 | M12: =N12-K12 -> 10 | N12: 585 | O12: =ROUND(M12*$O$3,2) -> 63.86 | P12: =Q12-N12 -> 14 | Q12: 599 | R12: =ROUND(P12*$R$3,2) -> 40.19 | S12: =+T12-Q12 -> 13 | T12: 612 | U12: =ROUND(S12*$U$3,2) -> 38.74 | V12: =+W12-T12 -> 22 | W12: 634 | X12: =V12*$X$3 -> 65.4544 | Y12: =+Z12-W12 -> 14 | Z12: 648 | AA12: =ROUND(Y12*$AA$3,2) -> 43.38
A13: DEPA-106 | B13: 396 | C13: =D13-B13 -> 0 | D13: 396 | E13: =F13-D13 -> 0 | F13: 396 | G13: =H13-F13 -> 1 | H13: 397 | I13: =ROUND(G13*$I$3,2) -> 3.73 | J13: =K13-H13 -> 2 | K13: 399 | L13: =ROUND(J13*$L$3,2) -> 8.31 | M13: =N13-K13 -> 5 | N13: 404 | O13: =ROUND(M13*$O$3,2) -> 31.93 | P13: =Q13-N13 -> 8 | Q13: 412 | R13: =ROUND(P13*$R$3,2) -> 22.96 | S13: =+T13-Q13 -> 9 | T13: 421 | U13: =ROUND(S13*$U$3,2) -> 26.82 | V13: =+W13-T13 -> 8 | W13: 429 | X13: =V13*$X$3 -> 23.8016 | Y13: =+Z13-W13 -> 9 | Z13: 438 | AA13: =ROUND(Y13*$AA$3,2) -> 27.89
A14: DEPA-107 | B14: 25 | C14: =D14-B14 -> 0 | D14: 25 | E14: =F14-D14 -> 1 | F14: 26 | G14: =H14-F14 -> 0 | H14: 26 | I14: =ROUND(G14*$I$3,2) -> 0 | J14: =K14-H14 -> 0 | K14: 26 | L14: =ROUND(J14*$L$3,2) -> 0 | M14: =N14-K14 -> 1 | N14: 27 | O14: =ROUND(M14*$O$3,2) -> 6.39 | P14: =Q14-N14 -> 1 | Q14: 28 | R14: =ROUND(P14*$R$3,2) -> 2.87 | S14: =+T14-Q14 -> 0 | T14: 28 | U14: =ROUND(S14*$U$3,2) -> 0 | V14: =+W14-T14 -> 1 | W14: 29 | X14: =V14*$X$3 -> 2.9752 | Y14: =+Z14-W14 -> 0 | Z14: 29 | AA14: =ROUND(Y14*$AA$3,2) -> 0
A15: DEPA-201 | B15: 128 | C15: =D15-B15 -> 8 | D15: 136 | E15: =F15-D15 -> 6 | F15: 142 | G15: =H15-F15 -> 11 | H15: 153 | I15: =ROUND(G15*$I$3,2) -> 41.08 | J15: =K15-H15 -> 8 | K15: 161 | L15: =ROUND(J15*$L$3,2) -> 33.24 | M15: =N15-K15 -> 4 | N15: 165 | O15: =ROUND(M15*$O$3,2) -> 25.54 | P15: =Q15-N15 -> 6 | Q15: 171 | R15: =ROUND(P15*$R$3,2) -> 17.22 | S15: =+T15-Q15 -> 9 | T15: 180 | U15: =ROUND(S15*$U$3,2) -> 26.82 | V15: =+W15-T15 -> 11 | W15: 191 | X15: =V15*$X$3 -> 32.7272 | Y15: =+Z15-W15 -> 9 | Z15: 200 | AA15: =ROUND(Y15*$AA$3,2) -> 27.89
A16: DEPA-202 | B16: 95 | C16: =D16-B16 -> 6 | D16: 101 | E16: =F16-D16 -> 4 | F16: 105 | G16: =H16-F16 -> 6 | H16: 111 | I16: =ROUND(G16*$I$3,2) -> 22.41 | J16: =K16-H16 -> 3 | K16: 114 | L16: =ROUND(J16*$L$3,2) -> 12.46 | M16: =N16-K16 -> 4 | N16: 118 | O16: =ROUND(M16*$O$3,2) -> 25.54 | P16: =Q16-N16 -> 4 | Q16: 122 | R16: =ROUND(P16*$R$3,2) -> 11.48 | S16: =+T16-Q16 -> 5 | T16: 127 | U16: =ROUND(S16*$U$3,2) -> 14.9 | V16: =+W16-T16 -> 6 | W16: 133 | X16: =V16*$X$3 -> 17.8512 | Y16: =+Z16-W16 -> 7 | Z16: 140 | AA16: =ROUND(Y16*$AA$3,2) -> 21.69
A17: DEPA-203 | B17: 234 | C17: =D17-B17 -> 4 | D17: 238 | E17: =F17-D17 -> 4 | F17: 242 | G17: =H17-F17 -> 8 | H17: 250 | I17: =ROUND(G17*$I$3,2) -> 29.87 | J17: =K17-H17 -> 3 | K17: 253 | L17: =ROUND(J17*$L$3,2) -> 12.46 | M17: =N17-K17 -> 4 | N17: 257 | O17: =ROUND(M17*$O$3,2) -> 25.54 | P17: =Q17-N17 -> 8 | Q17: 265 | R17: =ROUND(P17*$R$3,2) -> 22.96 | S17: =+T17-Q17 -> 55 | T17: 320 | U17: =ROUND(S17*$U$3,2) -> 163.89 | V17: =+W17-T17 -> 29 | W17: 349 | X17: =V17*$X$3 -> 86.2808 | Y17: =+Z17-W17 -> 34 | Z17: 383 | AA17: =ROUND(Y17*$AA$3,2) -> 105.36 | AC17: *pablo
A18: DEPA-204 | B18: 145 | C18: =D18-B18 -> 4 | D18: 149 | E18: =F18-D18 -> 5 | F18: 154 | G18: =H18-F18 -> 7 | H18: 161 | I18: =ROUND(G18*$I$3,2) -> 26.14 | J18: =K18-H18 -> 5 | K18: 166 | L18: =ROUND(J18*$L$3,2) -> 20.77 | M18: =N18-K18 -> 4 | N18: 170 | O18: =ROUND(M18*$O$3,2) -> 25.54 | P18: =Q18-N18 -> 4 | Q18: 174 | R18: =ROUND(P18*$R$3,2) -> 11.48 | S18: =+T18-Q18 -> 6 | T18: 180 | U18: =ROUND(S18*$U$3,2) -> 17.88 | V18: =+W18-T18 -> 5 | W18: 185 | X18: =V18*$X$3 -> 14.876 | Y18: =+Z18-W18 -> 7 | Z18: 192 | AA18: =ROUND(Y18*$AA$3,2) -> 21.69
A19: DEPA-205 | B19: 157 | C19: =D19-B19 -> 8 | D19: 165 | E19: =F19-D19 -> 7 | F19: 172 | G19: =H19-F19 -> 7 | H19: 179 | I19: =ROUND(G19*$I$3,2) -> 26.14 | J19: =K19-H19 -> 7 | K19: 186 | L19: =ROUND(J19*$L$3,2) -> 29.08 | M19: =N19-K19 -> 5 | N19: 191 | O19: =ROUND(M19*$O$3,2) -> 31.93 | P19: =Q19-N19 -> 3 | Q19: 194 | R19: =ROUND(P19*$R$3,2) -> 8.61 | S19: =+T19-Q19 -> 8 | T19: 202 | U19: =ROUND(S19*$U$3,2) -> 23.84 | V19: =+W19-T19 -> 9 | W19: 211 | X19: =V19*$X$3 -> 26.7768 | Y19: =+Z19-W19 -> 10 | Z19: 221 | AA19: =ROUND(Y19*$AA$3,2) -> 30.99
A20: DEPA-206 | B20: 131 | C20: =D20-B20 -> 4 | D20: 135 | E20: =F20-D20 -> 4 | F20: 139 | G20: =H20-F20 -> 7 | H20: 146 | I20: =ROUND(G20*$I$3,2) -> 26.14 | J20: =K20-H20 -> 5 | K20: 151 | L20: =ROUND(J20*$L$3,2) -> 20.77 | M20: =N20-K20 -> 3 | N20: 154 | O20: =ROUND(M20*$O$3,2) -> 19.16 | P20: =Q20-N20 -> 2 | Q20: 156 | R20: =ROUND(P20*$R$3,2) -> 5.74 | S20: =+T20-Q20 -> 0 | T20: 156 | U20: =ROUND(S20*$U$3,2) -> 0 | V20: =+W20-T20 -> 1 | W20: 157 | X20: =V20*$X$3 -> 2.9752 | Y20: =+Z20-W20 -> 1 | Z20: 158 | AA20: =ROUND(Y20*$AA$3,2) -> 3.1
A21: DEPA-207 | B21: 196 | C21: =D21-B21 -> 4 | D21: 200 | E21: =F21-D21 -> 4 | F21: 204 | G21: =H21-F21 -> 5 | H21: 209 | I21: =ROUND(G21*$I$3,2) -> 18.67 | J21: =K21-H21 -> 4 | K21: 213 | L21: =ROUND(J21*$L$3,2) -> 16.62 | M21: =N21-K21 -> 3 | N21: 216 | O21: =ROUND(M21*$O$3,2) -> 19.16 | P21: =Q21-N21 -> 5 | Q21: 221 | R21: =ROUND(P21*$R$3,2) -> 14.35 | S21: =+T21-Q21 -> 0 | T21: 221 | U21: =ROUND(S21*$U$3,2) -> 0 | V21: =+W21-T21 -> 7 | W21: 228 | X21: =V21*$X$3 -> 20.8264 | Y21: =+Z21-W21 -> 9 | Z21: 237 | AA21: =ROUND(Y21*$AA$3,2) -> 27.89
A22: DEPA-208 | B22: 258 | C22: =D22-B22 -> 9 | D22: 267 | E22: =F22-D22 -> 9 | F22: 276 | G22: =H22-F22 -> 5 | H22: 281 | I22: =ROUND(G22*$I$3,2) -> 18.67 | J22: =K22-H22 -> 12 | K22: 293 | L22: =ROUND(J22*$L$3,2) -> 49.86 | M22: =N22-K22 -> 5 | N22: 298 | O22: =ROUND(M22*$O$3,2) -> 31.93 | P22: =Q22-N22 -> 8 | Q22: 306 | R22: =ROUND(P22*$R$3,2) -> 22.96 | S22: =+T22-Q22 -> 10 | T22: 316 | U22: =ROUND(S22*$U$3,2) -> 29.8 | V22: =+W22-T22 -> 9 | W22: 325 | X22: =V22*$X$3 -> 26.7768 | Y22: =+Z22-W22 -> 13 | Z22: 338 | AA22: =ROUND(Y22*$AA$3,2) -> 40.29
A23: DEPA-209 | B23: 14 | C23: =D23-B23 -> 1 | D23: 15 | E23: =F23-D23 -> 1 | F23: 16 | G23: =H23-F23 -> 0 | H23: 16 | I23: =ROUND(G23*$I$3,2) -> 0 | J23: =K23-H23 -> 1 | K23: 17 | L23: =ROUND(J23*$L$3,2) -> 4.15 | M23: =N23-K23 -> 0 | N23: 17 | O23: =ROUND(M23*$O$3,2) -> 0 | P23: =Q23-N23 -> 1 | Q23: 18 | R23: =ROUND(P23*$R$3,2) -> 2.87 | S23: =+T23-Q23 -> 1 | T23: 19 | U23: =ROUND(S23*$U$3,2) -> 2.98 | V23: =+W23-T23 -> 0 | W23: 19 | X23: =V23*$X$3 -> 0 | Y23: =+Z23-W23 -> 1 | Z23: 20 | AA23: =ROUND(Y23*$AA$3,2) -> 3.1
A24: DEPA-210 | B24: 332.49 | C24: =D24-B24 -> 16.86 | D24: 349.35 | E24: =F24-D24 -> 18.18 | F24: 367.53 | G24: =H24-F24 -> 15.545 | H24: 383.075 | I24: =ROUND(G24*$I$3,2) -> 58.05 | J24: =K24-H24 -> 16.925 | K24: 400 | L24: =ROUND(J24*$L$3,2) -> 70.32 | M24: =N24-K24 -> 13.082 | N24: 413.082 | O24: =ROUND(M24*$O$3,2) -> 83.54 | P24: =Q24-N24 -> 14.926 | Q24: 428.008 | R24: =ROUND(P24*$R$3,2) -> 42.84 | S24: =+T24-Q24 -> 3.567 | T24: 431.575 | U24: =ROUND(S24*$U$3,2) -> 10.63 | V24: =+W24-T24 -> 8.425 | W24: 440 | X24: =V24*$X$3 -> 25.06606 | Y24: =+Z24-W24 -> 12 | Z24: 452 | AA24: =ROUND(Y24*$AA$3,2) -> 37.19
A25: DEPA-301 | B25: 72 | C25: =D25-B25 -> 1 | D25: 73 | E25: =F25-D25 -> 1 | F25: 74 | G25: =H25-F25 -> 2 | H25: 76 | I25: =ROUND(G25*$I$3,2) -> 7.47 | J25: =K25-H25 -> 1 | K25: 77 | L25: =ROUND(J25*$L$3,2) -> 4.15 | M25: =N25-K25 -> 0 | N25: 77 | O25: =ROUND(M25*$O$3,2) -> 0 | P25: =Q25-N25 -> 1 | Q25: 78 | R25: =ROUND(P25*$R$3,2) -> 2.87 | S25: =+T25-Q25 -> 0 | T25: 78 | U25: =ROUND(S25*$U$3,2) -> 0 | V25: =+W25-T25 -> 0 | W25: 78 | X25: =V25*$X$3 -> 0 | Y25: =+Z25-W25 -> 1 | Z25: 79 | AA25: =ROUND(Y25*$AA$3,2) -> 3.1
A26: DEPA-302 | B26: 12 | C26: =D26-B26 -> 6 | D26: 18 | E26: =F26-D26 -> 4 | F26: 22 | G26: =H26-F26 -> 5 | H26: 27 | I26: =ROUND(G26*$I$3,2) -> 18.67 | J26: =K26-H26 -> 5 | K26: 32 | L26: =ROUND(J26*$L$3,2) -> 20.77 | M26: =N26-K26 -> 5 | N26: 37 | O26: =ROUND(M26*$O$3,2) -> 31.93 | P26: =Q26-N26 -> 9 | Q26: 46 | R26: =ROUND(P26*$R$3,2) -> 25.83 | S26: =+T26-Q26 -> 12 | T26: 58 | U26: =ROUND(S26*$U$3,2) -> 35.76 | V26: =+W26-T26 -> 11 | W26: 69 | X26: =V26*$X$3 -> 32.7272 | Y26: =+Z26-W26 -> 11 | Z26: 80 | AA26: =ROUND(Y26*$AA$3,2) -> 34.09
A27: DEPA-303 | B27: 58 | C27: =D27-B27 -> 0 | D27: 58 | E27: =F27-D27 -> 0 | F27: 58 | G27: =H27-F27 -> 3 | H27: 61 | I27: =ROUND(G27*$I$3,2) -> 11.2 | J27: =K27-H27 -> 0 | K27: 61 | L27: =ROUND(J27*$L$3,2) -> 0 | M27: =N27-K27 -> 0 | N27: 61 | O27: =ROUND(M27*$O$3,2) -> 0 | P27: =Q27-N27 -> 1 | Q27: 62 | R27: =ROUND(P27*$R$3,2) -> 2.87 | S27: =+T27-Q27 -> 0 | T27: 62 | U27: =ROUND(S27*$U$3,2) -> 0 | V27: =+W27-T27 -> 1 | W27: 63 | X27: =V27*$X$3 -> 2.9752 | Y27: =+Z27-W27 -> 1 | Z27: 64 | AA27: =ROUND(Y27*$AA$3,2) -> 3.1
A28: DEPA-304 | B28: 434 | C28: =D28-B28 -> 13 | D28: 447 | E28: =F28-D28 -> 13 | F28: 460 | G28: =H28-F28 -> 13 | H28: 473 | I28: =ROUND(G28*$I$3,2) -> 48.54 | J28: =K28-H28 -> 12 | K28: 485 | L28: =ROUND(J28*$L$3,2) -> 49.86 | M28: =N28-K28 -> 7 | N28: 492 | O28: =ROUND(M28*$O$3,2) -> 44.7 | P28: =Q28-N28 -> 6 | Q28: 498 | R28: =ROUND(P28*$R$3,2) -> 17.22 | S28: =+T28-Q28 -> 2 | T28: 500 | U28: =ROUND(S28*$U$3,2) -> 5.96 | V28: =+W28-T28 -> 4 | W28: 504 | X28: =V28*$X$3 -> 11.9008 | Y28: =+Z28-W28 -> 9 | Z28: 513 | AA28: =ROUND(Y28*$AA$3,2) -> 27.89
A29: DEPA-305 | B29: 60.11 | C29: =D29-B29 -> 4.28 | D29: 64.39 | E29: =F29-D29 -> 4.77 | F29: 69.16 | G29: =H29-F29 -> 5.735 | H29: 74.895 | I29: =ROUND(G29*$I$3,2) -> 21.42 | J29: =K29-H29 -> 2.581 | K29: 77.476 | L29: =ROUND(J29*$L$3,2) -> 10.72 | M29: =N29-K29 -> 2.935 | N29: 80.411 | O29: =ROUND(M29*$O$3,2) -> 18.74 | P29: =Q29-N29 -> 4.589 | Q29: 85 | R29: =ROUND(P29*$R$3,2) -> 13.17 | S29: =+T29-Q29 -> 5.048 | T29: 90.048 | U29: =ROUND(S29*$U$3,2) -> 15.04 | V29: =+W29-T29 -> 5.952 | W29: 96 | X29: =V29*$X$3 -> 17.70839 | Y29: =+Z29-W29 -> 7 | Z29: 103 | AA29: =ROUND(Y29*$AA$3,2) -> 21.69
... A122: DEPA-1103 | B122: 210 | C122: =D122-B122 -> 4 | D122: 214 | E122: =F122-D122 -> 4 | F122: 218 | G122: =H122-F122 -> 9 | H122: 227 | I122: =ROUND(G122*$I$3,2) -> 33.61 | J122: =K122-H122 -> 3 | K122: 230 | L122: =ROUND(J122*$L$3,2) -> 12.46 | M122: =N122-K122 -> 2 | N122: 232 | O122: =ROUND(M122*$O$3,2) -> 12.77 | P122: =Q122-N122 -> 4 | Q122: 236 | R122: =ROUND(P122*$R$3,2) -> 11.48 | S122: =+T122-Q122 -> 5 | T122: 241 | U122: =ROUND(S122*$U$3,2) -> 14.9 | V122: =+W122-T122 -> 10 | W122: 251 | X122: =V122*$X$3 -> 29.752 | Y122: =+Z122-W122 -> 7 | Z122: 258 | AA122: =ROUND(Y122*$AA$3,2) -> 21.69
A123: DEPA-1104 | B123: 298 | C123: =D123-B123 -> 5 | D123: 303 | E123: =F123-D123 -> 4 | F123: 307 | G123: 5 | H123: 62 | I123: =ROUND(G123*$I$3,2) -> 18.67 | J123: =K123-H123 -> 13 | K123: 75 | L123: =ROUND(J123*$L$3,2) -> 54.01 | M123: =N123-K123 -> 9 | N123: 84 | O123: =ROUND(M123*$O$3,2) -> 57.47 | P123: =Q123-N123 -> 11 | Q123: 95 | R123: =ROUND(P123*$R$3,2) -> 31.57 | S123: =+T123-Q123 -> 12 | T123: 107 | U123: =ROUND(S123*$U$3,2) -> 35.76 | V123: =+W123-T123 -> 12 | W123: 119 | X123: =V123*$X$3 -> 35.7024 | Y123: =+Z123-W123 -> 3 | Z123: 122 | AA123: =ROUND(Y123*$AA$3,2) -> 9.3 | AD123: *medidor nuevo val. 25/08/2025
A124: DEPA-1105 | B124: 380.08 | C124: =D124-B124 -> 10.82 | D124: 390.9 | E124: =F124-D124 -> 9.63 | F124: 400.53 | G124: =H124-F124 -> 11.706 | H124: 412.236 | I124: =ROUND(G124*$I$3,2) -> 43.71 | J124: =K124-H124 -> 12.277 | K124: 424.513 | L124: =ROUND(J124*$L$3,2) -> 51.01 | M124: =N124-K124 -> 8.038 | N124: 432.551 | O124: =ROUND(M124*$O$3,2) -> 51.33 | P124: =Q124-N124 -> 7.449 | Q124: 440 | R124: =ROUND(P124*$R$3,2) -> 21.38 | S124: =+T124-Q124 -> 12.669 | T124: 452.669 | U124: =ROUND(S124*$U$3,2) -> 37.75 | V124: =+W124-T124 -> 9.331 | W124: 462 | X124: =V124*$X$3 -> 27.761591 | Y124: =+Z124-W124 -> 10 | Z124: 472 | AA124: =ROUND(Y124*$AA$3,2) -> 30.99
A125: DEPA-1106 | B125: 35 | C125: =D125-B125 -> 1 | D125: 36 | E125: =F125-D125 -> 0 | F125: 36 | G125: =H125-F125 -> 1 | H125: 37 | I125: =ROUND(G125*$I$3,2) -> 3.73 | J125: =K125-H125 -> 0 | K125: 37 | L125: =ROUND(J125*$L$3,2) -> 0 | M125: =N125-K125 -> 0 | N125: 37 | O125: =ROUND(M125*$O$3,2) -> 0 | P125: =Q125-N125 -> 1 | Q125: 38 | R125: =ROUND(P125*$R$3,2) -> 2.87 | S125: =+T125-Q125 -> 0 | T125: 38 | U125: =ROUND(S125*$U$3,2) -> 0 | V125: =+W125-T125 -> 0 | W125: 38 | X125: =V125*$X$3 -> 0 | Y125: =+Z125-W125 -> 1 | Z125: 39 | AA125: =ROUND(Y125*$AA$3,2) -> 3.1
A126: DEPA-1107 | B126: 288 | C126: =D126-B126 -> 5 | D126: 293 | E126: =F126-D126 -> 9 | F126: 302 | G126: =H126-F126 -> 8 | H126: 310 | I126: =ROUND(G126*$I$3,2) -> 29.87 | J126: =K126-H126 -> 8 | K126: 318 | L126: =ROUND(J126*$L$3,2) -> 33.24 | M126: =N126-K126 -> 3 | N126: 321 | O126: =ROUND(M126*$O$3,2) -> 19.16 | P126: =Q126-N126 -> 5 | Q126: 326 | R126: =ROUND(P126*$R$3,2) -> 14.35 | S126: =+T126-Q126 -> 9 | T126: 335 | U126: =ROUND(S126*$U$3,2) -> 26.82 | V126: =+W126-T126 -> 8 | W126: 343 | X126: =V126*$X$3 -> 23.8016 | Y126: =+Z126-W126 -> 11 | Z126: 354 | AA126: =ROUND(Y126*$AA$3,2) -> 34.09
A127: DEPA-1108 | B127: 137 | C127: =D127-B127 -> 2 | D127: 139 | E127: =F127-D127 -> 3 | F127: 142 | G127: =H127-F127 -> 5 | H127: 147 | I127: =ROUND(G127*$I$3,2) -> 18.67 | J127: =K127-H127 -> 2 | K127: 149 | L127: =ROUND(J127*$L$3,2) -> 8.31 | M127: =N127-K127 -> 2 | N127: 151 | O127: =ROUND(M127*$O$3,2) -> 12.77 | P127: =Q127-N127 -> 3 | Q127: 154 | R127: =ROUND(P127*$R$3,2) -> 8.61 | S127: =+T127-Q127 -> 3 | T127: 157 | U127: =ROUND(S127*$U$3,2) -> 8.94 | V127: =+W127-T127 -> 3 | W127: 160 | X127: =V127*$X$3 -> 8.9256 | Y127: =+Z127-W127 -> 6 | Z127: 166 | AA127: =ROUND(Y127*$AA$3,2) -> 18.59
A128: DEPA-1109 | B128: 199 | C128: =D128-B128 -> 4 | D128: 203 | E128: =F128-D128 -> 3 | F128: 206 | G128: =H128-F128 -> 5 | H128: 211 | I128: =ROUND(G128*$I$3,2) -> 18.67 | J128: =K128-H128 -> 4 | K128: 215 | L128: =ROUND(J128*$L$3,2) -> 16.62 | M128: =N128-K128 -> 3 | N128: 218 | O128: =ROUND(M128*$O$3,2) -> 19.16 | P128: =Q128-N128 -> 3 | Q128: 221 | R128: =ROUND(P128*$R$3,2) -> 8.61 | S128: =+T128-Q128 -> 4 | T128: 225 | U128: =ROUND(S128*$U$3,2) -> 11.92 | V128: =+W128-T128 -> 2 | W128: 227 | X128: =V128*$X$3 -> 5.9504 | Y128: =+Z128-W128 -> 3 | Z128: 230 | AA128: =ROUND(Y128*$AA$3,2) -> 9.3
A129: DEPA-1110 | B129: 278.12 | C129: =D129-B129 -> 5.13 | D129: 283.25 | E129: =F129-D129 -> 6.05 | F129: 289.3 | G129: =H129-F129 -> 7.15 | H129: 296.45 | I129: =ROUND(G129*$I$3,2) -> 26.7 | J129: =K129-H129 -> 5.854 | K129: 302.304 | L129: =ROUND(J129*$L$3,2) -> 24.32 | M129: =N129-K129 -> 4.304 | N129: 306.608 | O129: =ROUND(M129*$O$3,2) -> 27.48 | P129: =Q129-N129 -> 4.392 | Q129: 311 | R129: =ROUND(P129*$R$3,2) -> 12.61 | S129: =+T129-Q129 -> 7.308 | T129: 318.308 | U129: =ROUND(S129*$U$3,2) -> 21.78 | V129: =+W129-T129 -> 4.692 | W129: 323 | X129: =V129*$X$3 -> 13.959638 | Y129: =+Z129-W129 -> 8 | Z129: 331 | AA129: =ROUND(Y129*$AA$3,2) -> 24.79
A130: DEPA-1111 | B130: 141.87 | C130: =D130-B130 -> 7 | D130: 148.87 | E130: =F130-D130 -> 6.35 | F130: 155.22 | G130: =H130-F130 -> 6.582 | H130: 161.802 | I130: =ROUND(G130*$I$3,2) -> 24.58 | J130: =K130-H130 -> 6.058 | K130: 167.86 | L130: =ROUND(J130*$L$3,2) -> 25.17 | M130: =N130-K130 -> 4.032 | N130: 171.892 | O130: =ROUND(M130*$O$3,2) -> 25.75 | P130: =Q130-N130 -> 5.108 | Q130: 177 | R130: =ROUND(P130*$R$3,2) -> 14.66 | S130: =+T130-Q130 -> 6.588 | T130: 183.588 | U130: =ROUND(S130*$U$3,2) -> 19.63 | V130: =+W130-T130 -> 6.412 | W130: 190 | X130: =V130*$X$3 -> 19.076982 | Y130: =+Z130-W130 -> 8 | Z130: 198 | AA130: =ROUND(Y130*$AA$3,2) -> 24.79
A131: DEPA-1112 | B131: 239 | C131: =D131-B131 -> 18 | D131: 257 | E131: =F131-D131 -> 7 | F131: 264 | G131: =H131-F131 -> 13 | H131: 277 | I131: =ROUND(G131*$I$3,2) -> 48.54 | J131: =K131-H131 -> 9 | K131: 286 | L131: =ROUND(J131*$L$3,2) -> 37.39 | M131: =N131-K131 -> 7 | N131: 293 | O131: =ROUND(M131*$O$3,2) -> 44.7 | P131: =Q131-N131 -> 8 | Q131: 301 | R131: =ROUND(P131*$R$3,2) -> 22.96 | S131: =+T131-Q131 -> 10 | T131: 311 | U131: =ROUND(S131*$U$3,2) -> 29.8 | V131: =+W131-T131 -> 8 | W131: 319 | X131: =V131*$X$3 -> 23.8016 | Y131: =+Z131-W131 -> 9 | Z131: 328 | AA131: =ROUND(Y131*$AA$3,2) -> 27.89
A132: DEPA-1201 | B132: 617 | C132: =D132-B132 -> 12 | D132: 629 | E132: =F132-D132 -> 20 | F132: 649 | G132: =H132-F132 -> 22 | H132: =496+175 -> 671 | I132: =ROUND(G132*$I$3,2) -> 82.15 | J132: =K132-H132 -> 20 | K132: =511+180 -> 691 | L132: =ROUND(J132*$L$3,2) -> 83.09 | M132: =N132-K132 -> 15 | N132: =522+184 -> 706 | O132: =ROUND(M132*$O$3,2) -> 95.78 | P132: =Q132-N132 -> 17 | Q132: =535+188 -> 723 | R132: =ROUND(P132*$R$3,2) -> 48.8 | S132: =+T132-Q132 -> 22 | T132: =552+193 -> 745 | U132: =ROUND(S132*$U$3,2) -> 65.56 | V132: =+W132-T132 -> 21 | W132: =567+199 -> 766 | X132: =V132*$X$3 -> 62.4792 | Y132: =+Z132-W132 -> 22 | Z132: =583+205 -> 788 | AA132: =ROUND(Y132*$AA$3,2) -> 68.18
A133: DEPA-1204 | B133: 113 | C133: =D133-B133 -> 7 | D133: 120 | E133: =F133-D133 -> 6 | F133: 126 | G133: =H133-F133 -> 7 | H133: 133 | I133: =ROUND(G133*$I$3,2) -> 26.14 | J133: =K133-H133 -> 6 | K133: 139 | L133: =ROUND(J133*$L$3,2) -> 24.93 | M133: =N133-K133 -> 5 | N133: 144 | O133: =ROUND(M133*$O$3,2) -> 31.93 | P133: =Q133-N133 -> 6 | Q133: 150 | R133: =ROUND(P133*$R$3,2) -> 17.22 | S133: =+T133-Q133 -> 9 | T133: 159 | U133: =ROUND(S133*$U$3,2) -> 26.82 | V133: =+W133-T133 -> 8 | W133: 167 | X133: =V133*$X$3 -> 23.8016 | Y133: =+Z133-W133 -> 4 | Z133: 171 | AA133: =ROUND(Y133*$AA$3,2) -> 12.4
A134: DEPA-1205 | B134: 438 | C134: =D134-B134 -> 8 | D134: 446 | E134: =F134-D134 -> 9 | F134: 455 | G134: 9 | H134: 91 | I134: =ROUND(G134*$I$3,2) -> 33.61 | J134: =K134-H134 -> 13 | K134: 104 | L134: =ROUND(J134*$L$3,2) -> 54.01 | M134: =N134-K134 -> 9 | N134: 113 | O134: =ROUND(M134*$O$3,2) -> 57.47 | P134: =Q134-N134 -> 13 | Q134: 126 | R134: =ROUND(P134*$R$3,2) -> 37.32 | S134: =+T134-Q134 -> 15 | T134: 141 | U134: =ROUND(S134*$U$3,2) -> 44.7 | V134: =+W134-T134 -> 17 | W134: 158 | X134: =V134*$X$3 -> 50.5784 | Y134: =+Z134-W134 -> 18 | Z134: 176 | AA134: =ROUND(Y134*$AA$3,2) -> 55.78
A135: DEPA-1206 | B135: 83 | C135: =D135-B135 -> 0 | D135: 83 | E135: =F135-D135 -> 1 | F135: 84 | G135: =H135-F135 -> 0 | H135: 84 | I135: =ROUND(G135*$I$3,2) -> 0 | J135: =K135-H135 -> 0 | K135: 84 | L135: =ROUND(J135*$L$3,2) -> 0 | M135: =N135-K135 -> 1 | N135: 85 | O135: =ROUND(M135*$O$3,2) -> 6.39 | P135: =Q135-N135 -> 0 | Q135: 85 | R135: =ROUND(P135*$R$3,2) -> 0 | S135: =+T135-Q135 -> 1 | T135: 86 | U135: =ROUND(S135*$U$3,2) -> 2.98 | V135: =+W135-T135 -> 2 | W135: 88 | X135: =V135*$X$3 -> 5.9504 | Y135: =+Z135-W135 -> 0 | Z135: 88 | AA135: =ROUND(Y135*$AA$3,2) -> 0 | AD135: *medidor nuevo val. 25/08/2025
A136: DEPA-1207 | B136: 152 | C136: =D136-B136 -> 6 | D136: 158 | E136: =F136-D136 -> 7 | F136: 165 | G136: =H136-F136 -> 8 | H136: 173 | I136: =ROUND(G136*$I$3,2) -> 29.87 | J136: =K136-H136 -> 8 | K136: 181 | L136: =ROUND(J136*$L$3,2) -> 33.24 | M136: =N136-K136 -> 4 | N136: 185 | O136: =ROUND(M136*$O$3,2) -> 25.54 | P136: =Q136-N136 -> 5 | Q136: 190 | R136: =ROUND(P136*$R$3,2) -> 14.35 | S136: =+T136-Q136 -> 3 | T136: 193 | U136: =ROUND(S136*$U$3,2) -> 8.94 | V136: =+W136-T136 -> 3 | W136: 196 | X136: =V136*$X$3 -> 8.9256 | Y136: =+Z136-W136 -> 7 | Z136: 203 | AA136: =ROUND(Y136*$AA$3,2) -> 21.69
A137: DEPA-1208 | B137: 114 | C137: =D137-B137 -> 0 | D137: 114 | E137: =F137-D137 -> 2 | F137: 116 | G137: =H137-F137 -> 1 | H137: 117 | I137: =ROUND(G137*$I$3,2) -> 3.73 | J137: =K137-H137 -> 1 | K137: 118 | L137: =ROUND(J137*$L$3,2) -> 4.15 | M137: =N137-K137 -> 1 | N137: 119 | O137: =ROUND(M137*$O$3,2) -> 6.39 | P137: =Q137-N137 -> 2 | Q137: 121 | R137: =ROUND(P137*$R$3,2) -> 5.74 | S137: =+T137-Q137 -> 1 | T137: 122 | U137: =ROUND(S137*$U$3,2) -> 2.98 | V137: =+W137-T137 -> 2 | W137: 124 | X137: =V137*$X$3 -> 5.9504 | Y137: =+Z137-W137 -> 2 | Z137: 126 | AA137: =ROUND(Y137*$AA$3,2) -> 6.2
A138: DEPA-1209 | B138: 108 | C138: =D138-B138 -> 5 | D138: 113 | E138: =F138-D138 -> 10 | F138: 123 | G138: =H138-F138 -> 3 | H138: 126 | I138: =ROUND(G138*$I$3,2) -> 11.2 | J138: =K138-H138 -> 2 | K138: 128 | L138: =ROUND(J138*$L$3,2) -> 8.31 | M138: =N138-K138 -> 3 | N138: 131 | O138: =ROUND(M138*$O$3,2) -> 19.16 | P138: =Q138-N138 -> 4 | Q138: 135 | R138: =ROUND(P138*$R$3,2) -> 11.48 | S138: =+T138-Q138 -> 3 | T138: 138 | U138: =ROUND(S138*$U$3,2) -> 8.94 | V138: =+W138-T138 -> 4 | W138: 142 | X138: =V138*$X$3 -> 11.9008 | Y138: =+Z138-W138 -> 6 | Z138: 148 | AA138: =ROUND(Y138*$AA$3,2) -> 18.59
A139: DEPA-1210 | B139: 283.29 | C139: =D139-B139 -> 6.71 | D139: 290 | E139: =F139-D139 -> 5.73 | F139: 295.73 | G139: =H139-F139 -> 8.715 | H139: 304.445 | I139: =ROUND(G139*$I$3,2) -> 32.54 | J139: =K139-H139 -> 9.455 | K139: 313.9 | L139: =ROUND(J139*$L$3,2) -> 39.28 | M139: =N139-K139 -> 5.419 | N139: 319.319 | O139: =ROUND(M139*$O$3,2) -> 34.6 | P139: =Q139-N139 -> 6.681 | Q139: 326 | R139: =ROUND(P139*$R$3,2) -> 19.18 | S139: =+T139-Q139 -> 9.117 | T139: 335.117 | U139: =ROUND(S139*$U$3,2) -> 27.17 | V139: =+W139-T139 -> 8.883 | W139: 344 | X139: =V139*$X$3 -> 26.428702 | Y139: =+Z139-W139 -> 18 | Z139: 362 | AA139: =ROUND(Y139*$AA$3,2) -> 55.78
A140: DEPA-1211 | B140: 166.09 | C140: =D140-B140 -> 1.47 | D140: 167.56 | E140: =F140-D140 -> 1.87 | F140: 169.43 | G140: =H140-F140 -> 1.649 | H140: 171.079 | I140: =ROUND(G140*$I$3,2) -> 6.16 | J140: =K140-H140 -> 2.391 | K140: 173.47 | L140: =ROUND(J140*$L$3,2) -> 9.93 | M140: =N140-K140 -> 1.834 | N140: 175.304 | O140: =ROUND(M140*$O$3,2) -> 11.71 | P140: =Q140-N140 -> 1.696 | Q140: 177 | R140: =ROUND(P140*$R$3,2) -> 4.87 | S140: =+T140-Q140 -> 3.879 | T140: 180.879 | U140: =ROUND(S140*$U$3,2) -> 11.56 | V140: =+W140-T140 -> 2.121 | W140: 183 | X140: =V140*$X$3 -> 6.3103992 | Y140: =+Z140-W140 -> 3 | Z140: 186 | AA140: =ROUND(Y140*$AA$3,2) -> 9.3
A141: DEPA-1212 | B141: 152 | C141: =D141-B141 -> 0 | D141: 152 | E141: =F141-D141 -> 0 | F141: 152 | G141: =H141-F141 -> 2 | H141: 154 | I141: =ROUND(G141*$I$3,2) -> 7.47 | J141: =K141-H141 -> 7 | K141: 161 | L141: =ROUND(J141*$L$3,2) -> 29.08 | M141: =N141-K141 -> 9 | N141: 170 | O141: =ROUND(M141*$O$3,2) -> 57.47 | P141: =Q141-N141 -> 11 | Q141: 181 | R141: =ROUND(P141*$R$3,2) -> 31.57 | S141: =+T141-Q141 -> 15 | T141: 196 | U141: =ROUND(S141*$U$3,2) -> 44.7 | V141: =+W141-T141 -> 16 | W141: 212 | X141: =V141*$X$3 -> 47.6032 | Y141: =+Z141-W141 -> 16 | Z141: 228 | AA141: =ROUND(Y141*$AA$3,2) -> 49.58
A142: DEPA-1301 | B142: 96 | C142: =D142-B142 -> 1 | D142: 97 | E142: =F142-D142 -> 2 | F142: 99 | G142: =H142-F142 -> 2 | H142: 101 | I142: =ROUND(G142*$I$3,2) -> 7.47 | J142: =K142-H142 -> 2 | K142: 103 | L142: =ROUND(J142*$L$3,2) -> 8.31 | M142: =N142-K142 -> 1 | N142: 104 | O142: =ROUND(M142*$O$3,2) -> 6.39 | P142: =Q142-N142 -> 3 | Q142: 107 | R142: =ROUND(P142*$R$3,2) -> 8.61 | S142: =+T142-Q142 -> 2 | T142: 109 | U142: =ROUND(S142*$U$3,2) -> 5.96 | V142: =+W142-T142 -> 3 | W142: 112 | X142: =V142*$X$3 -> 8.9256 | Y142: =+Z142-W142 -> 1 | Z142: 113 | AA142: =ROUND(Y142*$AA$3,2) -> 3.1
A143: DEPA-1302 | B143: 145 | C143: =D143-B143 -> 7 | D143: 152 | E143: =F143-D143 -> 6 | F143: 158 | G143: =H143-F143 -> 7 | H143: 165 | I143: =ROUND(G143*$I$3,2) -> 26.14 | J143: =K143-H143 -> 10 | K143: 175 | L143: =ROUND(J143*$L$3,2) -> 41.55 | M143: =N143-K143 -> 2 | N143: 177 | O143: =ROUND(M143*$O$3,2) -> 12.77 | P143: =Q143-N143 -> 6 | Q143: 183 | R143: =ROUND(P143*$R$3,2) -> 17.22 | S143: =+T143-Q143 -> 8 | T143: 191 | U143: =ROUND(S143*$U$3,2) -> 23.84 | V143: =+W143-T143 -> 8 | W143: 199 | X143: =V143*$X$3 -> 23.8016 | Y143: =+Z143-W143 -> 9 | Z143: 208 | AA143: =ROUND(Y143*$AA$3,2) -> 27.89
A144: DEPA-1303 | B144: 178 | C144: =D144-B144 -> 4 | D144: 182 | E144: =F144-D144 -> 4 | F144: 186 | G144: =H144-F144 -> 4 | H144: 190 | I144: =ROUND(G144*$I$3,2) -> 14.94 | J144: =K144-H144 -> 2 | K144: 192 | L144: =ROUND(J144*$L$3,2) -> 8.31 | M144: =N144-K144 -> 0 | N144: 192 | O144: =ROUND(M144*$O$3,2) -> 0 | P144: =Q144-N144 -> 2 | Q144: 194 | R144: =ROUND(P144*$R$3,2) -> 5.74 | S144: =+T144-Q144 -> 1 | T144: 195 | U144: =ROUND(S144*$U$3,2) -> 2.98 | V144: =+W144-T144 -> 1 | W144: 196 | X144: =V144*$X$3 -> 2.9752 | Y144: =+Z144-W144 -> 4 | Z144: 200 | AA144: =ROUND(Y144*$AA$3,2) -> 12.4
A145: DEPA-1304 | B145: 284 | C145: =D145-B145 -> 2 | D145: 286 | E145: =F145-D145 -> 3 | F145: 289 | G145: =H145-F145 -> 0 | H145: 289 | I145: =ROUND(G145*$I$3,2) -> 0 | J145: =K145-H145 -> 1 | K145: 290 | L145: =ROUND(J145*$L$3,2) -> 4.15 | M145: =N145-K145 -> 2 | N145: 292 | O145: =ROUND(M145*$O$3,2) -> 12.77 | P145: =Q145-N145 -> 5 | Q145: 297 | R145: =ROUND(P145*$R$3,2) -> 14.35 | S145: =+T145-Q145 -> 10 | T145: 307 | U145: =ROUND(S145*$U$3,2) -> 29.8 | V145: =+W145-T145 -> 5 | W145: 312 | X145: =V145*$X$3 -> 14.876 | Y145: =+Z145-W145 -> 57 | Z145: 369 | AA145: =ROUND(Y145*$AA$3,2) -> 176.64
A146: DEPA-1305 | B146: 329.91 | C146: =D146-B146 -> 14.85 | D146: 344.76 | E146: =F146-D146 -> 12.56 | F146: 357.32 | G146: =H146-F146 -> 13.693 | H146: 371.013 | I146: =ROUND(G146*$I$3,2) -> 51.13 | J146: =K146-H146 -> 11.689 | K146: 382.702 | L146: =ROUND(J146*$L$3,2) -> 48.56 | M146: =N146-K146 -> 8.202 | N146: 390.904 | O146: =ROUND(M146*$O$3,2) -> 52.37 | P146: =Q146-N146 -> 9.096 | Q146: 400 | R146: =ROUND(P146*$R$3,2) -> 26.11 | S146: =+T146-Q146 -> 14.66 | T146: 414.66 | U146: =ROUND(S146*$U$3,2) -> 43.68 | V146: =+W146-T146 -> 14.34 | W146: 429 | X146: =V146*$X$3 -> 42.664368 | Y146: =+Z146-W146 -> 15 | Z146: 444 | AA146: =ROUND(Y146*$AA$3,2) -> 46.48
A147: DEPA-1306 | B147: 9 | C147: =D147-B147 -> 0 | D147: 9 | E147: =F147-D147 -> 0 | F147: 9 | G147: =H147-F147 -> 0 | H147: 9 | I147: =ROUND(G147*$I$3,2) -> 0 | J147: =K147-H147 -> 0 | K147: 9 | L147: =ROUND(J147*$L$3,2) -> 0 | M147: =N147-K147 -> 0 | N147: 9 | O147: =ROUND(M147*$O$3,2) -> 0 | P147: =Q147-N147 -> 0 | Q147: 9 | R147: =ROUND(P147*$R$3,2) -> 0 | S147: =+T147-Q147 -> 0 | T147: 9 | U147: =ROUND(S147*$U$3,2) -> 0 | V147: =+W147-T147 -> 1 | W147: 10 | X147: =V147*$X$3 -> 2.9752 | Y147: =+Z147-W147 -> 0 | Z147: 10 | AA147: =ROUND(Y147*$AA$3,2) -> 0
... A158: DEPA-1405 | B158: 129.72 | C158: =D158-B158 -> 4.44 | D158: 134.16 | E158: =F158-D158 -> 5.04 | F158: 139.2 | G158: =H158-F158 -> -0.2 | H158: 139 | I158: =ROUND(G158*$I$3,2) -> -0.75 | J158: =K158-H158 -> 1.419 | K158: 140.419 | L158: =ROUND(J158*$L$3,2) -> 5.9 | M158: =N158-K158 -> 1.451 | N158: 141.87 | O158: =ROUND(M158*$O$3,2) -> 9.27 | P158: =Q158-N158 -> 1.13 | Q158: 143 | R158: =ROUND(P158*$R$3,2) -> 3.24 | S158: =+T158-Q158 -> 1.553 | T158: 144.553 | U158: =ROUND(S158*$U$3,2) -> 4.63 | V158: =+W158-T158 -> 1.447 | W158: 146 | X158: =V158*$X$3 -> 4.3051144 | Y158: =+Z158-W158 -> 1 | Z158: 147 | AA158: =ROUND(Y158*$AA$3,2) -> 3.1
A159: DEPA-1406 | B159: 155 | C159: =D159-B159 -> 1 | D159: 156 | E159: =F159-D159 -> 2 | F159: 158 | G159: 2 | H159: 16 | I159: =ROUND(G159*$I$3,2) -> 7.47 | J159: =K159-H159 -> 2 | K159: 18 | L159: =ROUND(J159*$L$3,2) -> 8.31 | M159: =N159-K159 -> 0 | N159: 18 | O159: =ROUND(M159*$O$3,2) -> 0 | P159: =Q159-N159 -> 4 | Q159: 22 | R159: =ROUND(P159*$R$3,2) -> 11.48 | S159: =+T159-Q159 -> 0 | T159: 22 | U159: =ROUND(S159*$U$3,2) -> 0 | V159: =+W159-T159 -> 0 | W159: 22 | X159: =V159*$X$3 -> 0 | Y159: =+Z159-W159 -> 3 | Z159: 25 | AA159: =ROUND(Y159*$AA$3,2) -> 9.3 | AD159: *medidor nuevo val. 25/08/2025
A160: DEPA-1407 | B160: 210 | C160: =D160-B160 -> 5 | D160: 215 | E160: =F160-D160 -> 4 | F160: 219 | G160: =H160-F160 -> 5 | H160: 224 | I160: =ROUND(G160*$I$3,2) -> 18.67 | J160: =K160-H160 -> 5 | K160: 229 | L160: =ROUND(J160*$L$3,2) -> 20.77 | M160: =N160-K160 -> 3 | N160: 232 | O160: =ROUND(M160*$O$3,2) -> 19.16 | P160: =Q160-N160 -> 3 | Q160: 235 | R160: =ROUND(P160*$R$3,2) -> 8.61 | S160: =+T160-Q160 -> 3 | T160: 238 | U160: =ROUND(S160*$U$3,2) -> 8.94 | V160: =+W160-T160 -> 5 | W160: 243 | X160: =V160*$X$3 -> 14.876 | Y160: =+Z160-W160 -> 5 | Z160: 248 | AA160: =ROUND(Y160*$AA$3,2) -> 15.49
A161: DEPA-1408 | B161: 98.6 | C161: =D161-B161 -> 1.2 | D161: 99.8 | E161: =F161-D161 -> 1.2 | F161: 101 | G161: 1 | H161: 27 | I161: =ROUND(G161*$I$3,2) -> 3.73 | J161: =K161-H161 -> 3 | K161: 30 | L161: =ROUND(J161*$L$3,2) -> 12.46 | M161: =N161-K161 -> 3 | N161: 33 | O161: =ROUND(M161*$O$3,2) -> 19.16 | P161: =Q161-N161 -> 4 | Q161: 37 | R161: =ROUND(P161*$R$3,2) -> 11.48 | S161: =+T161-Q161 -> 4 | T161: 41 | U161: =ROUND(S161*$U$3,2) -> 11.92 | V161: =+W161-T161 -> 4 | W161: 45 | X161: =V161*$X$3 -> 11.9008 | Y161: =+Z161-W161 -> 5 | Z161: 50 | AA161: =ROUND(Y161*$AA$3,2) -> 15.49 | AD161: *medidor nuevo val. 25/08/2025
A162: DEPA-1409 | B162: 168 | C162: =D162-B162 -> 5 | D162: 173 | E162: =F162-D162 -> 3 | F162: 176 | G162: =H162-F162 -> 6 | H162: 182 | I162: =ROUND(G162*$I$3,2) -> 22.41 | J162: =K162-H162 -> 5 | K162: 187 | L162: =ROUND(J162*$L$3,2) -> 20.77 | M162: =N162-K162 -> 2 | N162: 189 | O162: =ROUND(M162*$O$3,2) -> 12.77 | P162: =Q162-N162 -> 1 | Q162: 190 | R162: =ROUND(P162*$R$3,2) -> 2.87 | S162: =+T162-Q162 -> 1 | T162: 191 | U162: =ROUND(S162*$U$3,2) -> 2.98 | V162: =+W162-T162 -> 3 | W162: 194 | X162: =V162*$X$3 -> 8.9256 | Y162: =+Z162-W162 -> 9 | Z162: 203 | AA162: =ROUND(Y162*$AA$3,2) -> 27.89
A163: DEPA-1410 | B163: 477.26 | C163: =D163-B163 -> 11.14 | D163: 488.4 | E163: =F163-D163 -> 11.6 | F163: 500 | G163: =H163-F163 -> 12.123 | H163: 512.123 | I163: =ROUND(G163*$I$3,2) -> 45.27 | J163: =K163-H163 -> 10.271 | K163: 522.394 | L163: =ROUND(J163*$L$3,2) -> 42.67 | M163: =N163-K163 -> 8.541 | N163: 530.935 | O163: =ROUND(M163*$O$3,2) -> 54.54 | P163: =Q163-N163 -> 8.065 | Q163: 539 | R163: =ROUND(P163*$R$3,2) -> 23.15 | S163: =+T163-Q163 -> 11.424 | T163: 550.424 | U163: =ROUND(S163*$U$3,2) -> 34.04 | V163: =+W163-T163 -> 12.576 | W163: 563 | X163: =V163*$X$3 -> 37.416115 | Y163: =+Z163-W163 -> 7 | Z163: 570 | AA163: =ROUND(Y163*$AA$3,2) -> 21.69
A164: DEPA-1411 | B164: 139.2 | C164: =D164-B164 -> 2.6 | D164: 141.8 | E164: =F164-D164 -> 1.21 | F164: 143.01 | G164: 2 | H164: 134.388 | I164: =ROUND(G164*$I$3,2) -> 7.47 | J164: =K164-H164 -> 0.465 | K164: 134.853 | L164: =ROUND(J164*$L$3,2) -> 1.93 | M164: =N164-K164 -> 1.071 | N164: 135.924 | O164: =ROUND(M164*$O$3,2) -> 6.84 | P164: =Q164-N164 -> 0.076 | Q164: 136 | R164: =ROUND(P164*$R$3,2) -> 0.22 | S164: =+T164-Q164 -> 2.232 | T164: 138.232 | U164: =ROUND(S164*$U$3,2) -> 6.65 | V164: =+W164-T164 -> 1.768 | W164: 140 | X164: =V164*$X$3 -> 5.2601536 | Y164: =+Z164-W164 -> 4 | Z164: 144 | AA164: =ROUND(Y164*$AA$3,2) -> 12.4
A165: DEPA-1412 | B165: 519 | C165: =D165-B165 -> 10 | D165: 529 | E165: =F165-D165 -> 13 | F165: 542 | G165: =H165-F165 -> 14 | H165: 556 | I165: =ROUND(G165*$I$3,2) -> 52.28 | J165: =K165-H165 -> 11 | K165: 567 | L165: =ROUND(J165*$L$3,2) -> 45.7 | M165: =N165-K165 -> 9 | N165: 576 | O165: =ROUND(M165*$O$3,2) -> 57.47 | P165: =Q165-N165 -> 11 | Q165: 587 | R165: =ROUND(P165*$R$3,2) -> 31.57 | S165: =+T165-Q165 -> 10 | T165: 597 | U165: =ROUND(S165*$U$3,2) -> 29.8 | V165: =+W165-T165 -> 2 | W165: 599 | X165: =V165*$X$3 -> 5.9504 | Y165: =+Z165-W165 -> 0 | Z165: 599 | AA165: =ROUND(Y165*$AA$3,2) -> 0
A166: DEPA-1501 | B166: 65 | C166: =D166-B166 -> 2 | D166: 67 | E166: =F166-D166 -> 1 | F166: 68 | G166: =H166-F166 -> 1 | H166: 69 | I166: =ROUND(G166*$I$3,2) -> 3.73 | J166: =K166-H166 -> 0 | K166: 69 | L166: =ROUND(J166*$L$3,2) -> 0 | M166: =N166-K166 -> 0 | N166: 69 | O166: =ROUND(M166*$O$3,2) -> 0 | P166: =Q166-N166 -> 1 | Q166: 70 | R166: =ROUND(P166*$R$3,2) -> 2.87 | S166: =+T166-Q166 -> 2 | T166: 72 | U166: =ROUND(S166*$U$3,2) -> 5.96 | V166: =+W166-T166 -> 10 | W166: 82 | X166: =V166*$X$3 -> 29.752 | Y166: =+Z166-W166 -> 12 | Z166: 94 | AA166: =ROUND(Y166*$AA$3,2) -> 37.19
A167: DEPA-1502 | B167: 225 | C167: =D167-B167 -> 14 | D167: 239 | E167: =F167-D167 -> 11 | F167: 250 | G167: =H167-F167 -> 6 | H167: 256 | I167: =ROUND(G167*$I$3,2) -> 22.41 | J167: =K167-H167 -> 4 | K167: 260 | L167: =ROUND(J167*$L$3,2) -> 16.62 | M167: =N167-K167 -> 15 | N167: 275 | O167: =ROUND(M167*$O$3,2) -> 95.78 | P167: =Q167-N167 -> 8 | Q167: 283 | R167: =ROUND(P167*$R$3,2) -> 22.96 | S167: =+T167-Q167 -> 8 | T167: 291 | U167: =ROUND(S167*$U$3,2) -> 23.84 | V167: =+W167-T167 -> 7 | W167: 298 | X167: =V167*$X$3 -> 20.8264 | Y167: =+Z167-W167 -> 9 | Z167: 307 | AA167: =ROUND(Y167*$AA$3,2) -> 27.89
A168: DEPA-1503 | B168: 338 | C168: =D168-B168 -> 9 | D168: 347 | E168: =F168-D168 -> 6 | F168: 353 | G168: =H168-F168 -> 9 | H168: 362 | I168: =ROUND(G168*$I$3,2) -> 33.61 | J168: =K168-H168 -> 7 | K168: 369 | L168: =ROUND(J168*$L$3,2) -> 29.08 | M168: =N168-K168 -> 5 | N168: 374 | O168: =ROUND(M168*$O$3,2) -> 31.93 | P168: =Q168-N168 -> 6 | Q168: 380 | R168: =ROUND(P168*$R$3,2) -> 17.22 | S168: =+T168-Q168 -> 6 | T168: 386 | U168: =ROUND(S168*$U$3,2) -> 17.88 | V168: =+W168-T168 -> 9 | W168: 395 | X168: =V168*$X$3 -> 26.7768 | Y168: =+Z168-W168 -> 9 | Z168: 404 | AA168: =ROUND(Y168*$AA$3,2) -> 27.89
A169: DEPA-1504 | B169: 231 | C169: =D169-B169 -> 3 | D169: 234 | E169: =F169-D169 -> 4 | F169: 238 | G169: =H169-F169 -> 2 | H169: 240 | I169: =ROUND(G169*$I$3,2) -> 7.47 | J169: =K169-H169 -> 2 | K169: 242 | L169: =ROUND(J169*$L$3,2) -> 8.31 | M169: =N169-K169 -> 2 | N169: 244 | O169: =ROUND(M169*$O$3,2) -> 12.77 | P169: =Q169-N169 -> 3 | Q169: 247 | R169: =ROUND(P169*$R$3,2) -> 8.61 | S169: =+T169-Q169 -> 0 | T169: 247 | U169: =ROUND(S169*$U$3,2) -> 0 | V169: =+W169-T169 -> 3 | W169: 250 | X169: =V169*$X$3 -> 8.9256 | Y169: =+Z169-W169 -> 4 | Z169: 254 | AA169: =ROUND(Y169*$AA$3,2) -> 12.4
A170: DEPA-1505 | B170: 321.39 | C170: =D170-B170 -> 12.38 | D170: 333.77 | E170: =F170-D170 -> 9.65 | F170: 343.42 | G170: =H170-F170 -> 7.543 | H170: 350.963 | I170: =ROUND(G170*$I$3,2) -> 28.17 | J170: =K170-H170 -> 6.037 | K170: 357 | L170: =ROUND(J170*$L$3,2) -> 25.08 | M170: =N170-K170 -> 1.599 | N170: 358.599 | O170: =ROUND(M170*$O$3,2) -> 10.21 | P170: =Q170-N170 -> 0.401 | Q170: 359 | R170: =ROUND(P170*$R$3,2) -> 1.15 | S170: =+T170-Q170 -> 0.821 | T170: 359.821 | U170: =ROUND(S170*$U$3,2) -> 2.45 | V170: =+W170-T170 -> 0.179 | W170: 360 | X170: =V170*$X$3 -> 0.5325608 | Y170: =+Z170-W170 -> 0 | Z170: 360 | AA170: =ROUND(Y170*$AA$3,2) -> 0
A171: DEPA-1506 | B171: 227 | C171: =D171-B171 -> 3 | D171: 230 | E171: =F171-D171 -> 4 | F171: 234 | G171: =H171-F171 -> 5 | H171: 239 | I171: =ROUND(G171*$I$3,2) -> 18.67 | J171: =K171-H171 -> 3 | K171: 242 | L171: =ROUND(J171*$L$3,2) -> 12.46 | M171: =N171-K171 -> 2 | N171: 244 | O171: =ROUND(M171*$O$3,2) -> 12.77 | P171: =Q171-N171 -> 2 | Q171: 246 | R171: =ROUND(P171*$R$3,2) -> 5.74 | S171: =+T171-Q171 -> 2 | T171: 248 | U171: =ROUND(S171*$U$3,2) -> 5.96 | V171: =+W171-T171 -> 4 | W171: 252 | X171: =V171*$X$3 -> 11.9008 | Y171: =+Z171-W171 -> 5 | Z171: 257 | AA171: =ROUND(Y171*$AA$3,2) -> 15.49
A172: DEPA-1507 | B172: 368 | C172: =D172-B172 -> 12 | D172: 380 | E172: =F172-D172 -> 13 | F172: 393 | G172: =H172-F172 -> 14 | H172: 407 | I172: =ROUND(G172*$I$3,2) -> 52.28 | J172: =K172-H172 -> 13 | K172: 420 | L172: =ROUND(J172*$L$3,2) -> 54.01 | M172: =N172-K172 -> 7 | N172: 427 | O172: =ROUND(M172*$O$3,2) -> 44.7 | P172: =Q172-N172 -> 11 | Q172: 438 | R172: =ROUND(P172*$R$3,2) -> 31.57 | S172: =+T172-Q172 -> 12 | T172: 450 | U172: =ROUND(S172*$U$3,2) -> 35.76 | V172: =+W172-T172 -> 14 | W172: 464 | X172: =V172*$X$3 -> 41.6528 | Y172: =+Z172-W172 -> 17 | Z172: 481 | AA172: =ROUND(Y172*$AA$3,2) -> 52.68
A173: DEPA-1508 | B173: 168 | C173: =D173-B173 -> 4 | D173: 172 | E173: =F173-D173 -> 3 | F173: 175 | G173: =H173-F173 -> 3 | H173: 178 | I173: =ROUND(G173*$I$3,2) -> 11.2 | J173: =K173-H173 -> 1 | K173: 179 | L173: =ROUND(J173*$L$3,2) -> 4.15 | M173: =N173-K173 -> 2 | N173: 181 | O173: =ROUND(M173*$O$3,2) -> 12.77 | P173: =Q173-N173 -> 4 | Q173: 185 | R173: =ROUND(P173*$R$3,2) -> 11.48 | S173: =+T173-Q173 -> 1 | T173: 186 | U173: =ROUND(S173*$U$3,2) -> 2.98 | V173: =+W173-T173 -> 3 | W173: 189 | X173: =V173*$X$3 -> 8.9256 | Y173: =+Z173-W173 -> 3 | Z173: 192 | AA173: =ROUND(Y173*$AA$3,2) -> 9.3
A174: DEPA-1509 | B174: 125 | C174: =D174-B174 -> 7 | D174: 132 | E174: =F174-D174 -> 5 | F174: 137 | G174: =H174-F174 -> 6 | H174: 143 | I174: =ROUND(G174*$I$3,2) -> 22.41 | J174: =K174-H174 -> 5 | K174: 148 | L174: =ROUND(J174*$L$3,2) -> 20.77 | M174: =N174-K174 -> 3 | N174: 151 | O174: =ROUND(M174*$O$3,2) -> 19.16 | P174: =Q174-N174 -> 5 | Q174: 156 | R174: =ROUND(P174*$R$3,2) -> 14.35 | S174: =+T174-Q174 -> 4 | T174: 160 | U174: =ROUND(S174*$U$3,2) -> 11.92 | V174: =+W174-T174 -> 1 | W174: 161 | X174: =V174*$X$3 -> 2.9752 | Y174: =+Z174-W174 -> 4 | Z174: 165 | AA174: =ROUND(Y174*$AA$3,2) -> 12.4
A175: DEPA-1510 | B175: 214.34 | C175: =D175-B175 -> 6.57 | D175: 220.91 | E175: =F175-D175 -> 6.91 | F175: 227.82 | G175: =H175-F175 -> 5.21 | H175: 233.03 | I175: =ROUND(G175*$I$3,2) -> 19.46 | J175: =K175-H175 -> 7.364 | K175: 240.394 | L175: =ROUND(J175*$L$3,2) -> 30.6 | M175: =N175-K175 -> 5.971 | N175: 246.365 | O175: =ROUND(M175*$O$3,2) -> 38.13 | P175: =Q175-N175 -> 5.635 | Q175: 252 | R175: =ROUND(P175*$R$3,2) -> 16.17 | S175: =+T175-Q175 -> 8.473 | T175: 260.473 | U175: =ROUND(S175*$U$3,2) -> 25.25 | V175: =+W175-T175 -> 16.527 | W175: 277 | X175: =V175*$X$3 -> 49.17113 | Y175: =+Z175-W175 -> 8 | Z175: 285 | AA175: =ROUND(Y175*$AA$3,2) -> 24.79
A176: DEPA-1511 | B176: 95.56 | C176: =D176-B176 -> 2.18 | D176: 97.74 | E176: =F176-D176 -> 2.58 | F176: 100.32 | G176: =H176-F176 -> 2.879 | H176: 103.199 | I176: =ROUND(G176*$I$3,2) -> 10.75 | J176: =K176-H176 -> 2.076 | K176: 105.275 | L176: =ROUND(J176*$L$3,2) -> 8.63 | M176: =N176-K176 -> 1.185 | N176: 106.46 | O176: =ROUND(M176*$O$3,2) -> 7.57 | P176: =Q176-N176 -> 1.54 | Q176: 108 | R176: =ROUND(P176*$R$3,2) -> 4.42 | S176: =+T176-Q176 -> 1.922 | T176: 109.922 | U176: =ROUND(S176*$U$3,2) -> 5.73 | V176: =+W176-T176 -> 1.078 | W176: 111 | X176: =V176*$X$3 -> 3.2072656 | Y176: =+Z176-W176 -> 3 | Z176: 114 | AA176: =ROUND(Y176*$AA$3,2) -> 9.3
... A185: DEPA-1608 | B185: 122 | C185: =D185-B185 -> 1 | D185: 123 | E185: =F185-D185 -> 1 | F185: 124 | G185: =H185-F185 -> 1 | H185: 125 | I185: =ROUND(G185*$I$3,2) -> 3.73 | J185: =K185-H185 -> 2 | K185: 127 | L185: =ROUND(J185*$L$3,2) -> 8.31 | M185: =N185-K185 -> 0 | N185: 127 | O185: =ROUND(M185*$O$3,2) -> 0 | P185: =Q185-N185 -> 2 | Q185: 129 | R185: =ROUND(P185*$R$3,2) -> 5.74 | S185: =+T185-Q185 -> 1 | T185: 130 | U185: =ROUND(S185*$U$3,2) -> 2.98 | V185: =+W185-T185 -> 1 | W185: 131 | X185: =V185*$X$3 -> 2.9752 | Y185: =+Z185-W185 -> 3 | Z185: 134 | AA185: =ROUND(Y185*$AA$3,2) -> 9.3
A186: DEPA-1609 | B186: 320 | C186: =D186-B186 -> 10 | D186: 330 | E186: =F186-D186 -> 11 | F186: 341 | G186: 11 | H186: 138 | I186: =ROUND(G186*$I$3,2) -> 41.08 | J186: =K186-H186 -> 11 | K186: 149 | L186: =ROUND(J186*$L$3,2) -> 45.7 | M186: =N186-K186 -> 9 | N186: 158 | O186: =ROUND(M186*$O$3,2) -> 57.47 | P186: =Q186-N186 -> 11 | Q186: 169 | R186: =ROUND(P186*$R$3,2) -> 31.57 | S186: =+T186-Q186 -> 13 | T186: 182 | U186: =ROUND(S186*$U$3,2) -> 38.74 | V186: =+W186-T186 -> 13 | W186: 195 | X186: =V186*$X$3 -> 38.6776 | Y186: =+Z186-W186 -> 16 | Z186: 211 | AA186: =ROUND(Y186*$AA$3,2) -> 49.58 | AD186: *medidor nuevo val. 25/08/2025
A187: DEPA-1610 | B187: 247.37 | C187: =D187-B187 -> 5.29 | D187: 252.66 | E187: =F187-D187 -> 8.74 | F187: 261.4 | G187: =H187-F187 -> 5.683 | H187: 267.083 | I187: =ROUND(G187*$I$3,2) -> 21.22 | J187: =K187-H187 -> 8.815 | K187: 275.898 | L187: =ROUND(J187*$L$3,2) -> 36.62 | M187: =N187-K187 -> 5.525 | N187: 281.423 | O187: =ROUND(M187*$O$3,2) -> 35.28 | P187: =Q187-N187 -> 4.577 | Q187: 286 | R187: =ROUND(P187*$R$3,2) -> 13.14 | S187: =+T187-Q187 -> 8.217 | T187: 294.217 | U187: =ROUND(S187*$U$3,2) -> 24.49 | V187: =+W187-T187 -> 6.783 | W187: 301 | X187: =V187*$X$3 -> 20.180782 | Y187: =+Z187-W187 -> 8 | Z187: 309 | AA187: =ROUND(Y187*$AA$3,2) -> 24.79
A188: DEPA-1611 | B188: 125.9 | C188: =D188-B188 -> 0.63 | D188: 126.53 | E188: =F188-D188 -> 0.34 | F188: 126.87 | G188: =H188-F188 -> 0.089 | H188: 126.959 | I188: =ROUND(G188*$I$3,2) -> 0.33 | J188: =K188-H188 -> 2.716 | K188: 129.675 | L188: =ROUND(J188*$L$3,2) -> 11.28 | M188: =N188-K188 -> 1.653 | N188: 131.328 | O188: =ROUND(M188*$O$3,2) -> 10.56 | P188: =Q188-N188 -> 1.672 | Q188: 133 | R188: =ROUND(P188*$R$3,2) -> 4.8 | S188: =+T188-Q188 -> 2.741 | T188: 135.741 | U188: =ROUND(S188*$U$3,2) -> 8.17 | V188: =+W188-T188 -> 4.259 | W188: 140 | X188: =V188*$X$3 -> 12.671377 | Y188: =+Z188-W188 -> 2 | Z188: 142 | AA188: =ROUND(Y188*$AA$3,2) -> 6.2
A189: DEPA-1612 | B189: 440 | C189: =D189-B189 -> 12 | D189: 452 | E189: =F189-D189 -> 10 | F189: 462 | G189: =H189-F189 -> 12 | H189: 474 | I189: =ROUND(G189*$I$3,2) -> 44.81 | J189: =K189-H189 -> 8 | K189: 482 | L189: =ROUND(J189*$L$3,2) -> 33.24 | M189: =N189-K189 -> 7 | N189: 489 | O189: =ROUND(M189*$O$3,2) -> 44.7 | P189: =Q189-N189 -> 9 | Q189: 498 | R189: =ROUND(P189*$R$3,2) -> 25.83 | S189: =+T189-Q189 -> 7 | T189: 505 | U189: =ROUND(S189*$U$3,2) -> 20.86 | V189: =+W189-T189 -> 9 | W189: 514 | X189: =V189*$X$3 -> 26.7768 | Y189: =+Z189-W189 -> 7 | Z189: 521 | AA189: =ROUND(Y189*$AA$3,2) -> 21.69
A190: DEPA-1701 | B190: 295 | C190: =D190-B190 -> 5 | D190: 300 | E190: =F190-D190 -> 3 | F190: 303 | G190: =H190-F190 -> 5 | H190: 308 | I190: =ROUND(G190*$I$3,2) -> 18.67 | J190: =K190-H190 -> 1 | K190: 309 | L190: =ROUND(J190*$L$3,2) -> 4.15 | M190: =N190-K190 -> 0 | N190: 309 | O190: =ROUND(M190*$O$3,2) -> 0 | P190: =Q190-N190 -> 4 | Q190: 313 | R190: =ROUND(P190*$R$3,2) -> 11.48 | S190: =+T190-Q190 -> 1 | T190: 314 | U190: =ROUND(S190*$U$3,2) -> 2.98 | V190: =+W190-T190 -> 4 | W190: 318 | X190: =V190*$X$3 -> 11.9008 | Y190: =+Z190-W190 -> 4 | Z190: 322 | AA190: =ROUND(Y190*$AA$3,2) -> 12.4
A191: DEPA-1702 | B191: 182 | C191: =D191-B191 -> 0 | D191: 182 | E191: =F191-D191 -> 0 | F191: 182 | G191: =H191-F191 -> 0 | H191: 182 | I191: =ROUND(G191*$I$3,2) -> 0 | J191: =K191-H191 -> 0 | K191: 182 | L191: =ROUND(J191*$L$3,2) -> 0 | M191: =N191-K191 -> 0 | N191: 182 | O191: =ROUND(M191*$O$3,2) -> 0 | P191: =Q191-N191 -> 0 | Q191: 182 | R191: =ROUND(P191*$R$3,2) -> 0 | S191: =+T191-Q191 -> 0 | T191: 182 | U191: =ROUND(S191*$U$3,2) -> 0 | V191: =+W191-T191 -> 0 | W191: 182 | X191: =V191*$X$3 -> 0 | Y191: =+Z191-W191 -> 8 | Z191: 190 | AA191: =ROUND(Y191*$AA$3,2) -> 24.79
A192: DEPA-1703 | B192: 188 | C192: =D192-B192 -> 8 | D192: 196 | E192: =F192-D192 -> 9 | F192: 205 | G192: =H192-F192 -> 11 | H192: 216 | I192: =ROUND(G192*$I$3,2) -> 41.08 | J192: =K192-H192 -> 4 | K192: 220 | L192: =ROUND(J192*$L$3,2) -> 16.62 | M192: =N192-K192 -> 2 | N192: 222 | O192: =ROUND(M192*$O$3,2) -> 12.77 | P192: =Q192-N192 -> 3 | Q192: 225 | R192: =ROUND(P192*$R$3,2) -> 8.61 | S192: =+T192-Q192 -> 2 | T192: 227 | U192: =ROUND(S192*$U$3,2) -> 5.96 | V192: =+W192-T192 -> 5 | W192: 232 | X192: =V192*$X$3 -> 14.876 | Y192: =+Z192-W192 -> 4 | Z192: 236 | AA192: =ROUND(Y192*$AA$3,2) -> 12.4
A193: DEPA-1704 | B193: 268 | C193: =D193-B193 -> 11 | D193: 279 | E193: =F193-D193 -> 9 | F193: 288 | G193: =H193-F193 -> 5 | H193: 293 | I193: =ROUND(G193*$I$3,2) -> 18.67 | J193: =K193-H193 -> 3 | K193: 296 | L193: =ROUND(J193*$L$3,2) -> 12.46 | M193: =N193-K193 -> 3 | N193: 299 | O193: =ROUND(M193*$O$3,2) -> 19.16 | P193: =Q193-N193 -> 5 | Q193: 304 | R193: =ROUND(P193*$R$3,2) -> 14.35 | S193: =+T193-Q193 -> 7 | T193: 311 | U193: =ROUND(S193*$U$3,2) -> 20.86 | V193: =+W193-T193 -> 9 | W193: 320 | X193: =V193*$X$3 -> 26.7768 | Y193: =+Z193-W193 -> 9 | Z193: 329 | AA193: =ROUND(Y193*$AA$3,2) -> 27.89
A194: DEPA-1705 | B194: 192.26 | C194: =D194-B194 -> 5.07 | D194: 197.33 | E194: =F194-D194 -> 5.22 | F194: 202.55 | G194: =H194-F194 -> 6.519 | H194: 209.069 | I194: =ROUND(G194*$I$3,2) -> 24.34 | J194: =K194-H194 -> 10.792 | K194: 219.861 | L194: =ROUND(J194*$L$3,2) -> 44.84 | M194: =N194-K194 -> 7.701 | N194: 227.562 | O194: =ROUND(M194*$O$3,2) -> 49.18 | P194: =Q194-N194 -> 9.438 | Q194: 237 | R194: =ROUND(P194*$R$3,2) -> 27.09 | S194: =+T194-Q194 -> 12.126 | T194: 249.126 | U194: =ROUND(S194*$U$3,2) -> 36.13 | V194: =+W194-T194 -> 10.874 | W194: 260 | X194: =V194*$X$3 -> 32.352325 | Y194: =+Z194-W194 -> 10 | Z194: 270 | AA194: =ROUND(Y194*$AA$3,2) -> 30.99
A195: DEPA-1706 | B195: 141 | C195: =D195-B195 -> 1 | D195: 142 | E195: =F195-D195 -> 2 | F195: 144 | G195: =H195-F195 -> 2 | H195: 146 | I195: =ROUND(G195*$I$3,2) -> 7.47 | J195: =K195-H195 -> 0 | K195: 146 | L195: =ROUND(J195*$L$3,2) -> 0 | M195: =N195-K195 -> 6 | N195: 152 | O195: =ROUND(M195*$O$3,2) -> 38.31 | P195: =Q195-N195 -> 6 | Q195: 158 | R195: =ROUND(P195*$R$3,2) -> 17.22 | S195: =+T195-Q195 -> 4 | T195: 162 | U195: =ROUND(S195*$U$3,2) -> 11.92 | V195: =+W195-T195 -> 4 | W195: 166 | X195: =V195*$X$3 -> 11.9008 | Y195: =+Z195-W195 -> 3 | Z195: 169 | AA195: =ROUND(Y195*$AA$3,2) -> 9.3
A196: DEPA-1707 | B196: 179 | C196: =D196-B196 -> 8 | D196: 187 | E196: =F196-D196 -> 4 | F196: 191 | G196: =H196-F196 -> 7 | H196: 198 | I196: =ROUND(G196*$I$3,2) -> 26.14 | J196: =K196-H196 -> 5 | K196: 203 | L196: =ROUND(J196*$L$3,2) -> 20.77 | M196: =N196-K196 -> 4 | N196: 207 | O196: =ROUND(M196*$O$3,2) -> 25.54 | P196: =Q196-N196 -> 4 | Q196: 211 | R196: =ROUND(P196*$R$3,2) -> 11.48 | S196: =+T196-Q196 -> 5 | T196: 216 | U196: =ROUND(S196*$U$3,2) -> 14.9 | V196: =+W196-T196 -> 2 | W196: 218 | X196: =V196*$X$3 -> 5.9504 | Y196: =+Z196-W196 -> 5 | Z196: 223 | AA196: =ROUND(Y196*$AA$3,2) -> 15.49
A197: DEPA-1708 | B197: 59 | C197: =D197-B197 -> 2 | D197: 61 | E197: =F197-D197 -> 0 | F197: 61 | G197: =H197-F197 -> 21 | H197: 82 | I197: =ROUND(G197*$I$3,2) -> 78.42 | J197: =K197-H197 -> 0 | K197: 82 | L197: =ROUND(J197*$L$3,2) -> 0 | M197: =N197-K197 -> 0 | N197: 82 | O197: =ROUND(M197*$O$3,2) -> 0 | P197: =Q197-N197 -> 0 | Q197: 82 | R197: =ROUND(P197*$R$3,2) -> 0 | S197: =+T197-Q197 -> 0 | T197: 82 | U197: =ROUND(S197*$U$3,2) -> 0 | V197: =+W197-T197 -> 0 | W197: 82 | X197: =V197*$X$3 -> 0 | Y197: =+Z197-W197 -> 0 | Z197: 82 | AA197: =ROUND(Y197*$AA$3,2) -> 0
A198: DEPA-1709 | B198: 277 | C198: =D198-B198 -> 3 | D198: 280 | E198: =F198-D198 -> 3 | F198: 283 | G198: =H198-F198 -> 5 | H198: 288 | I198: =ROUND(G198*$I$3,2) -> 18.67 | J198: =K198-H198 -> 3 | K198: 291 | L198: =ROUND(J198*$L$3,2) -> 12.46 | M198: =N198-K198 -> 2 | N198: 293 | O198: =ROUND(M198*$O$3,2) -> 12.77 | P198: =Q198-N198 -> 4 | Q198: 297 | R198: =ROUND(P198*$R$3,2) -> 11.48 | S198: =+T198-Q198 -> 3 | T198: 300 | U198: =ROUND(S198*$U$3,2) -> 8.94 | V198: =+W198-T198 -> 4 | W198: 304 | X198: =V198*$X$3 -> 11.9008 | Y198: =+Z198-W198 -> 4 | Z198: 308 | AA198: =ROUND(Y198*$AA$3,2) -> 12.4
... A201: DEPA-1712 | B201: 244 | C201: =D201-B201 -> 5 | D201: 249 | E201: =F201-D201 -> 5 | F201: 254 | G201: =H201-F201 -> 6 | H201: 260 | I201: =ROUND(G201*$I$3,2) -> 22.41 | J201: =K201-H201 -> 5 | K201: 265 | L201: =ROUND(J201*$L$3,2) -> 20.77 | M201: =N201-K201 -> 3 | N201: 268 | O201: =ROUND(M201*$O$3,2) -> 19.16 | P201: =Q201-N201 -> 6 | Q201: 274 | R201: =ROUND(P201*$R$3,2) -> 17.22 | S201: =+T201-Q201 -> 5 | T201: 279 | U201: =ROUND(S201*$U$3,2) -> 14.9 | V201: =+W201-T201 -> 7 | W201: 286 | X201: =V201*$X$3 -> 20.8264 | Y201: =+Z201-W201 -> 6 | Z201: 292 | AA201: =ROUND(Y201*$AA$3,2) -> 18.59
A202: PP-LAV | K202: 1571 | M202: =N202-K202 -> 36 | N202: 1607 | O202: =ROUND(M202*$O$3,2) -> 229.88 | P202: =Q202-N202 -> 44 | Q202: 1651 | R202: =ROUND(P202*$R$3,2) -> 126.3 | S202: =+T202-Q202 -> 37 | T202: 1688 | U202: =ROUND(S202*$U$3,2) -> 110.25 | V202: =+W202-T202 -> 48 | W202: 1736 | X202: =V202*$X$3 -> 142.8096 | Y202: =+Z202-W202 -> 69 | Z202: 1805 | AA202: =ROUND(Y202*$AA$3,2) -> 213.82
B203: =SUM(B7:B201) -> 43735.03 | C203: =SUM(C7:C201) -> 1151.35 | D203: =SUM(D7:D201) -> 44886.38 | E203: =SUM(E7:E201) -> 1109.89 | F203: =SUM(F7:F201) -> 45996.27 | G203: =SUM(G7:G201) -> 1262.229 | H203: =SUM(H7:H201) -> 46191.877 | I203: =SUM(I7:I201) -> 4713.38 | J203: =SUM(J7:J201) -> 1115.961 | L203: =SUM(L7:L201) -> 4636.29 | M203: =SUM(M7:M202) -> 824.779 | O203: =SUM(O7:O202) -> 5266.8 | P203: =SUM(P7:P202) -> 1035.538 | R203: =SUM(R7:R202) -> 2972.21 | S203: =SUM(S7:S202) -> 1272.95 | U203: =SUM(U7:U202) -> 3793.31 | V203: =SUM(V7:V202) -> 1302.895 | X203: =SUM(X7:X202) -> 3876.3732 | Y203: =SUM(Y7:Y202) -> 1519.337 | AA203: =SUM(AA7:AA202) -> 4708.33

Sheet calculo
A1: CODIGO | B1: PROPIETARIO(S) | C1: PREDIO | D1: ÁREA TECHADA | E1: ÁREA OCUPADA | F1: % PARTICIPACIÓN | G1: VALOR CUOTA | H1: AGUA CONSUMO | I1: SUMA
A2: PP-000 | B2: SIN IDENTIFICAR | C2: PP-LAV | F2: 0.004415 | G2: =ROUND(pres!$C$2*calculo!F2,2) -> 265.41 | H2: =IFERROR(VLOOKUP(C2,consumo_agua!$A$7:$AA$202,27,0),0) -> 213.82 | I2: =SUM(G2:H2) -> 479.23
A3: PP-001 | B3: AJK ASOCIADOS SAC | C3: DEPA-1605 | D3: 78.95 | E3: 78.95 | F3: 0.0044974 | G3: =ROUND(pres!$C$2*calculo!F3,2) -> 270.37 | H3: =IFERROR(VLOOKUP(C3,consumo_agua!$A$7:$AA$202,27,0),0) -> 15.49 | I3: =SUM(G3:H3) -> 285.86
A4: PP-001 | B4: AJK ASOCIADOS SAC | C4: ESTA-020 | D4: 0 | E4: 0 | F4: 0.001269 | G4: =ROUND(pres!$C$2*calculo!F4,2) -> 76.29 | H4: =IFERROR(VLOOKUP(C4,consumo_agua!$A$7:$AA$202,27,0),0) -> 0 | I4: =SUM(G4:H4) -> 76.29
A5: PP-002 | B5: ALBAN MALACHE CHABELI | C5: DEPA-612 | D5: 74.6 | E5: 74.6 | F5: 0.0044974 | G5: =ROUND(pres!$C$2*calculo!F5,2) -> 270.37 | H5: =IFERROR(VLOOKUP(C5,consumo_agua!$A$7:$AA$202,27,0),0) -> 24.79 | I5: =SUM(G5:H5) -> 295.16
A6: PP-002 | B6: ALBAN MALACHE CHABELI | C6: ESTA-067 | D6: 0 | E6: 0 | F6: 0.001269 | G6: =ROUND(pres!$C$2*calculo!F6,2) -> 76.29 | H6: =IFERROR(VLOOKUP(C6,consumo_agua!$A$7:$AA$202,27,0),0) -> 0 | I6: =SUM(G6:H6) -> 76.29
A7: PP-003 | B7: RUIZ JAVIER ALEJANDRO | C7: DEPA-811 | D7: 33 | E7: 33 | F7: 0.0026939 | G7: =ROUND(pres!$C$2*calculo!F7,2) -> 161.95 | H7: =IFERROR(VLOOKUP(C7,consumo_agua!$A$7:$AA$202,27,0),0) -> 9.3 | I7: =SUM(G7:H7) -> 171.25
A8: PP-004 | B8: ALEXANDER STRAHLE JURGEN | C8: DEPA-902 | D8: 77.05 | E8: 77.05 | F8: 0.0044974 | G8: =ROUND(pres!$C$2*calculo!F8,2) -> 270.37 | H8: =IFERROR(VLOOKUP(C8,consumo_agua!$A$7:$AA$202,27,0),0) -> 12.4 | I8: =SUM(G8:H8) -> 282.77
A9: PP-004 | B9: ALEXANDER STRAHLE JURGEN | C9: ESTA-042 | D9: 0 | E9: 0 | F9: 0.001269 | G9: =ROUND(pres!$C$2*calculo!F9,2) -> 76.29 | H9: =IFERROR(VLOOKUP(C9,consumo_agua!$A$7:$AA$202,27,0),0) -> 0 | I9: =SUM(G9:H9) -> 76.29
A10: PP-005 | B10: ALVA CUELLAR DUGLAS CONCEPCION | C10: DEPA-1205 | D10: 78.95 | E10: 78.95 | F10: 0.0044974 | G10: =ROUND(pres!$C$2*calculo!F10,2) -> 270.37 | H10: =IFERROR(VLOOKUP(C10,consumo_agua!$A$7:$AA$202,27,0),0) -> 55.78 | I10: =SUM(G10:H10) -> 326.15
A11: PP-005 | B11: ALVA CUELLAR DUGLAS CONCEPCION | C11: ESTA-077 | D11: 0 | E11: 0 | F11: 0.001269 | G11: =ROUND(pres!$C$2*calculo!F11,2) -> 76.29 | H11: =IFERROR(VLOOKUP(C11,consumo_agua!$A$7:$AA$202,27,0),0) -> 0 | I11: =SUM(G11:H11) -> 76.29
A12: PP-006 | B12: ALVARADO BRINGAS MILUSKA CARLA | C12: DEPA-1001 | D12: 92.5 | E12: 92.5 | F12: 0.0056773 | G12: =ROUND(pres!$C$2*calculo!F12,2) -> 341.3 | H12: =IFERROR(VLOOKUP(C12,consumo_agua!$A$7:$AA$202,27,0),0) -> 3.1 | I12: =SUM(G12:H12) -> 344.4
A13: PP-006 | B13: ALVARADO BRINGAS MILUSKA CARLA | C13: ESTA-063 | D13: 0 | E13: 0 | F13: 0.001269 | G13: =ROUND(pres!$C$2*calculo!F13,2) -> 76.29 | H13: =IFERROR(VLOOKUP(C13,consumo_agua!$A$7:$AA$202,27,0),0) -> 0 | I13: =SUM(G13:H13) -> 76.29
A14: PP-007 | B14: ANTON ENICE | C14: DEPA-610 | D14: 81 | E14: 81 | F14: 0.0044974 | G14: =ROUND(pres!$C$2*calculo!F14,2) -> 270.37 | H14: =IFERROR(VLOOKUP(C14,consumo_agua!$A$7:$AA$202,27,0),0) -> 15.49 | I14: =SUM(G14:H14) -> 285.86
... A163: PP-083 | B163: INDUSTRIAS GENERALES SAC | C163: ESTA-083 | D163: 0 | E163: 0 | F163: 0.001269 | G163: =ROUND(pres!$C$2*calculo!F163,2) -> 76.29 | H163: =IFERROR(VLOOKUP(C163,consumo_agua!$A$7:$AA$202,27,0),0) -> 0 | I163: =SUM(G163:H163) -> 76.29
A164: PP-084 | B164: INFANTES JHEYSON | G164: =ROUND(pres!$C$2*calculo!F164,2) -> 0 | H164: =IFERROR(VLOOKUP(C164,consumo_agua!$A$7:$AA$202,27,0),0) -> 0 | I164: =SUM(G164:H164) -> 0
A165: PP-084 | B165: INFANTES JHEYSON | C165: ESTA-133 | D165: 0 | E165: 0 | F165: 0.001269 | G165: =ROUND(pres!$C$2*calculo!F165,2) -> 76.29 | H165: =IFERROR(VLOOKUP(C165,consumo_agua!$A$7:$AA$202,27,0),0) -> 0 | I165: =SUM(G165:H165) -> 76.29
A166: PP-085 | B166: PARI NUÑEZ LEONOR | C166: DEPA-512 | D166: 74.6 | E166: 74.6 | F166: 0.0044974 | G166: =ROUND(pres!$C$2*calculo!F166,2) -> 270.37 | H166: =IFERROR(VLOOKUP(C166,consumo_agua!$A$7:$AA$202,27,0),0) -> 58.88 | I166: =SUM(G166:H166) -> 329.25
A167: PP-085 | B167: PARI NUÑEZ LEONOR | C167: ESTA-146 | D167: 0 | E167: 0 | F167: 0.001269 | G167: =ROUND(pres!$C$2*calculo!F167,2) -> 76.29 | H167: =IFERROR(VLOOKUP(C167,consumo_agua!$A$7:$AA$202,27,0),0) -> 0 | I167: =SUM(G167:H167) -> 76.29
A168: PP-086 | B168: IZQUIERDO ALATA LIAM JUAN PEDRO | C168: DEPA-710 | D168: 81 | E168: 81 | F168: 0.0044974 | G168: =ROUND(pres!$C$2*calculo!F168,2) -> 270.37 | H168: =IFERROR(VLOOKUP(C168,consumo_agua!$A$7:$AA$202,27,0),0) -> 24.79 | I168: =SUM(G168:H168) -> 295.16
A169: PP-086 | B169: IZQUIERDO ALATA LIAM JUAN PEDRO | C169: ESTA-117 | D169: 0 | E169: 0 | F169: 0.001269 | G169: =ROUND(pres!$C$2*calculo!F169,2) -> 76.29 | H169: =IFERROR(VLOOKUP(C169,consumo_agua!$A$7:$AA$202,27,0),0) -> 0 | I169: =SUM(G169:H169) -> 76.29
A170: PP-087 | B170: JARA CISNEROS RICHARD | C170: DEPA-1604 | D170: 76.15 | E170: 76.15 | F170: 0.0044974 | G170: =ROUND(pres!$C$2*calculo!F170,2) -> 270.37 | H170: =IFERROR(VLOOKUP(C170,consumo_agua!$A$7:$AA$202,27,0),0) -> 9.3 | I170: =SUM(G170:H170) -> 279.67
A171: PP-087 | B171: JARA CISNEROS RICHARD | C171: ESTA-129 | D171: 0 | E171: 0 | F171: 0.001269 | G171: =ROUND(pres!$C$2*calculo!F171,2) -> 76.29 | H171: =IFERROR(VLOOKUP(C171,consumo_agua!$A$7:$AA$202,27,0),0) -> 0 | I171: =SUM(G171:H171) -> 76.29
A172: PP-088 | B172: JIMENEZ CARMEN | C172: DEPA-508 | D172: 33.2 | E172: 33.2 | F172: 0.0026939 | G172: =ROUND(pres!$C$2*calculo!F172,2) -> 161.95 | H172: =IFERROR(VLOOKUP(C172,consumo_agua!$A$7:$AA$202,27,0),0) -> 0 | I172: =SUM(G172:H172) -> 161.95
A173: PP-088 | B173: JIMENEZ CARMEN | C173: DEPO-171 | D173: 0 | E173: 0 | F173: 0.0003675 | G173: =ROUND(pres!$C$2*calculo!F173,2) -> 22.09 | H173: =IFERROR(VLOOKUP(C173,consumo_agua!$A$7:$AA$202,27,0),0) -> 0 | I173: =SUM(G173:H173) -> 22.09
A174: PP-089 | B174: JO RENZO | C174: DEPA-1212 | D174: 74.6 | E174: 74.6 | F174: 0.0044974 | G174: =ROUND(pres!$C$2*calculo!F174,2) -> 270.37 | H174: =IFERROR(VLOOKUP(C174,consumo_agua!$A$7:$AA$202,27,0),0) -> 49.58 | I174: =SUM(G174:H174) -> 319.95
A175: PP-089 | B175: JO RENZO | C175: ESTA-085 | D175: 0 | E175: 0 | F175: 0.001269 | G175: =ROUND(pres!$C$2*calculo!F175,2) -> 76.29 | H175: =IFERROR(VLOOKUP(C175,consumo_agua!$A$7:$AA$202,27,0),0) -> 0 | I175: =SUM(G175:H175) -> 76.29
A176: PP-090 | B176: JURADO PAZ Y MIÑO VICTOR | C176: DEPA-703 | D176: 68 | E176: 68 | F176: 0.0044974 | G176: =ROUND(pres!$C$2*calculo!F176,2) -> 270.37 | H176: =IFERROR(VLOOKUP(C176,consumo_agua!$A$7:$AA$202,27,0),0) -> 0 | I176: =SUM(G176:H176) -> 270.37
... A382: PP-202 | B382: PALOMINO CRISTIAN | C382: ESTA-133 | D382: 0 | E382: 0 | F382: 0.001269 | G382: =ROUND(pres!$C$2*calculo!F382,2) -> 76.29 | H382: =IFERROR(VLOOKUP(C382,consumo_agua!$A$7:$AA$202,27,0),0) -> 0 | I382: =SUM(G382:H382) -> 76.29
A383: PP-LAV | B383: LAVANDERIA PRONTOMATIK | C383: PRONTOMATIK
D384: =SUM(D1:D383) -> 12767.37 | E384: =SUM(E1:E383) -> 12887.95 | F384: =SUM(F2:F383) -> 0.9999843 | G384: =SUM(G2:G383) -> 60116.18 | H384: =SUM(H1:H383) -> 4708.33 | I384: =SUM(I1:I383) -> 64824.51

Sheet cuota_resumen
C3: Valores
A4: CODIGO | B4: PROPIETARIO(S) | C4: PREDIOS | D4: VALOR CUOTA | E4: AGUA CONSUMO | F4: SUMA
A5: PP-001 | B5: AJK ASOCIADOS SAC | C5: 2 | D5: 346.66 | E5: 15.49 | F5: 362.15
A6: PP-002 | B6: ALBAN MALACHE CHABELI | C6: 2 | D6: 346.66 | E6: 24.79 | F6: 371.45
A7: PP-003 | B7: RUIZ JAVIER ALEJANDRO | C7: 1 | D7: 161.95 | E7: 9.3 | F7: 171.25
A8: PP-004 | B8: ALEXANDER STRAHLE JURGEN | C8: 2 | D8: 346.66 | E8: 12.4 | F8: 359.06
A9: PP-005 | B9: ALVA CUELLAR DUGLAS CONCEPCION | C9: 2 | D9: 346.66 | E9: 55.78 | F9: 402.44
A10: PP-006 | B10: ALVARADO BRINGAS MILUSKA CARLA | C10: 2 | D10: 417.59 | E10: 3.1 | F10: 420.69
A11: PP-007 | B11: ANTON ENICE | C11: 1 | D11: 270.37 | E11: 15.49 | F11: 285.86
A12: PP-008 | B12: APARCANA ROSADIO LUIS MIGUEL | C12: 2 | D12: 238.24 | E12: 15.49 | F12: 253.73
A13: PP-009 | B13: ASTO VARGAS HANS PIERRE | C13: 1 | D13: 161.95 | E13: 9.3 | F13: 171.25
A14: PP-010 | B14: AVENDAÑO SILVA MIRLEY JESUS | C14: 1 | D14: 76.29 | E14: 0 | F14: 76.29
A15: PP-011 | B15: AVILA JOEL ANTONIO | C15: 2 | D15: 346.66 | E15: 6.2 | F15: 352.86
A16: PP-012 | B16: AYAQUE LARICO ISAAC ALFREDO | C16: 2 | D16: 346.66 | E16: 9.3 | F16: 355.96
... A206: PP-202 | B206: PALOMINO CRISTIAN | C206: 2 | D206: 346.66 | E206: 12.4 | F206: 359.06
A207: PP-LAV | B207: LAVANDERIA PRONTOMATIK | C207: 1
A208: PP-000 | B208: SIN IDENTIFICAR | C208: 1 | D208: 265.41 | E208: 213.82 | F208: 479.23
A209: Total general | C209: 381 | D209: 60116.18 | E209: 4708.33 | F209: 64824.51

Sheet cuotas
A1: JUNTA DE PROPIETARIOS DEL EDIFICIO MULTIFAMILIAR "PACIFIK OCEAN TOWER"
A2: 20614642247
A3: Av. Bertolotto 850 - San Miguel
A5: codigo | B5: propietario | C5: predio | D5: saldo anterior | E5: 2026-01
A6: PP-000 | B6: SIN IDENTIFICAR | C6: E000 | D6: 897.99 | E6: 171.33
A7: PP-001 | B7: AJK ASOCIADOS SAC | C7: DEPA-1605 | D7: 377.02 | E7: 353.38
A8: PP-002 | B8: ALBAN MALACHE CHABELI | C8: DEPA-612 | D8: 395.44 | E8: 373.66
A9: PP-003 | B9: RUIZ JAVIER ALEJANDRO | C9: DEPA-811 | D9: 179.63 | E9: 168.13
A10: PP-004 | B10: ALEXANDER STRAHLE JURGEN | C10: DEPA-902 | D10: 0 | E10: 364.5
A11: PP-005 | B11: ALVA CUELLAR DUGLAS CONCEPCION | C11: DEPA-1205 | D11: 0 | E11: 397.23
A12: PP-006 | B12: ALVARADO BRINGAS MILUSKA CARLA | C12: DEPA-1001 | D12: 534.14 | E12: 506.22
A13: PP-007 | B13: ANTON ENICE | C13: DEPA-610 | D13: 1913.57 | E13: 296.71
A14: PP-008 | B14: APARCANA ROSADIO LUIS MIGUEL | C14: DEPA-606 | D14: 251.45 | E14: 244.18
A15: PP-009 | B15: ASTO VARGAS HANS PIERRE | C15: DEPA-1311 | D15: 3.34 | E15: 165.63
A16: PP-010 | B16: AVENDAÑO SILVA MIRLEY JESUS | C16: ESTA-087 | D16: 241.56 | E16: 76.29
A17: PP-011 | B17: AVILA JOEL ANTONIO | C17: DEPA-804 | D17: 0 | E17: 352.6
... A152: PP-146 | B152: ROSAS JHENIFER | C152: DEPA-204 | D152: 115.8 | E152: 198.92
A153: PP-147 | B153: RUBIANO NELSON | C153: DEPA-1507 | D153: 2128.87 | E153: 334.11 | G153: =+D153+E153 -> 2462.98 | H153: =+G153*1.05 -> 2586.129 | J153: 2496.05
A154: PP-148 | B154: RUIZ GUTIERREZ ROSA | C154: DEPA-704 | D154: 0 | E154: 361.53
A155: PP-149 | B155: SAAVEDRA MACHUCA DANY ELVIS | C155: DEPA-603 | D155: 2607.02 | E155: 273.34
A156: PP-150 | B156: SALINAS SOUZA CARLOS ENRIQUE JOSE ALFREDO | C156: DEPA-1106 | D156: 0 | E156: 260.33
A157: PP-151 | B157: SALVADOR NILS | C157: DEPA-1105 | D157: 790.89 | E157: 374.41
A158: PP-152 | B158: SAMANAMUD LOZANO NADIA | C158: DEPA-906 | D158: 1536.73 | E158: 241.21
A159: PP-153 | B159: SANCHEZ DIAZ RUBEN | C159: DEPA-711 | D159: 0 | E159: 173.85
A160: PP-154 | B160: SANCHEZ-SALAZAR OLCESE GLADYS MARIELA | C160: DEPA-206 | D160: 1080.96 | E160: 338.77
A161: PP-155 | B161: SANDOVAL AMASIFUEN EDWARD | C161: DEPA-1410 | D161: 835.59 | E161: 406.16
A162: PP-156 | B162: MONTES DE OCA BRAMOSIO MARIA GABY | C162: DEPA-1404 | D162: 0 | E162: 346.65
A163: PP-157 | B163: BUSTAMANTE EDUARDO - SARMIENTO INGRID | C163: DEPA-405 | D163: 414.48 | E163: 404.03
A164: PP-158 | B164: MEDINA SARMIENTO JAVIER | C164: DEPA-311 | D164: 182.41 | E164: 179.8
A165: PP-159 | B165: SAUÑE PACCO JOSE OSWALDO | C165: DEPA-1707 | D165: 0 | E165: 352.6
... A208: PP-202 | B208: PALOMINO CRISTIAN | C208: DEPA-1303 | D208: 368.86 | E208: 349.63
A209: PP-LAV | B209: LAVANDERIA PRONTOMATIK | C209: PP-LAV

Sheet ingresos
A1: JUNTA DE PROPIETARIOS DEL EDIFICIO MULTIFAMILIAR "PACIFIK OCEAN TOWER"
A2: 20614642247
A3: Av. Bertolotto 850 - San Miguel
A5: Fecha | B5: Descripción operación | C5: Monto | D5: Operación - Número | E5: Referencia | F5: codigo PP | G5: periodo x aplicar
A6: 46023 | C6: 0 | D6: 0 | E6: 0 | F6: PP-000
A7: 46023 | B7: TRAN.CTAS.TERC.BM | C7: 30 | D7: 03209955 | E7: ROJAS CACERES VITHIA MARCELA | G7: cine
A8: 46023 | B8: TRANSF.BCO.INTERBANK | C8: 100 | D8: 02847819 | E8: ALVAREZ-SALAS-CARLOS | G8: arcade
A9: 46023 | B9: TRAN.CTAS.TERC.BM | C9: 200 | D9: 02928341 | E9: LIANG NN YANQIU | G9: arcade
A10: 46023 | B10: TRAN.CTAS.TERC.BM | C10: 269.33 | D10: 03617458 | E10: TUPAYACHI VALLENAS DENIS ALFREDO | F10: PP-173 | G10: periodo anterior
A11: 46023 | B11: TRAN.CTAS.TERC.BM | C11: 368.33 | D11: 08573454 | E11: LIANG YANQIU | F11: PP-096 | G11: periodo anterior
A12: 46023 | B12: TRANSF.BCO.BBVA | C12: 372.09 | D12: 02705227 | E12: GIANELLA LIZETH NEIRA BUSTAMANTE | F12: PP-127 | G12: periodo anterior
A13: 46024 | B13: TRAN.CTAS.TERC.BM | C13: 30 | D13: 00794655 | E13: MONTESINOS CAMPOS NATALY MAGDALENA | G13: cine
A14: 46024 | B14: TRAN.CTAS.TERC.BM | C14: 30 | D14: 04534099 | E14: CHAVEZ JULCAHUANCA VANESSA ZORAIDA | G14: cine
A15: 46024 | B15: TRAN.CTAS.TERC.BM | C15: 40 | D15: 04819680 | E15: VALLEBUONA MAYTA LUIS ALBERTO | G15: parrilla
A16: 46024 | B16: TRAN.CTAS.TERC.BM | C16: 380.25 | D16: 00791169 | E16: HUANAY MARTINEZ FRANZ CESAR | F16: PP-080 | G16: periodo anterior
A17: 46024 | B17: TRAN.CTAS.TERC.BM | C17: 385.97 | D17: 03006094 | E17: FERRER CODINA MILAGROS DE JESUS | F17: PP-053 | G17: periodo anterior
A18: 46024 | B18: TRAN.CTAS.TERC.BM | C18: 389.72 | D18: 05389544 | E18: VEGA DIESTRA DAVID VICTOR | F18: PP-180 | G18: periodo anterior
A19: 46024 | B19: TRAN.CTAS.TERC.BM | C19: 398.66 | D19: 05823344 | E19: FLORES GARCIA KATIUSKA TERESA | F19: PP-031 | G19: periodo anterior
A20: 46024 | B20: TRANSF.BCO.BBVA | C20: 404.62 | D20: 02696269 | E20: DIEGO HERNAN MORALES X | F20: PP-078 | G20: periodo anterior
A21: 46024 | B21: TRANSF.BCO.INTERBANK | C21: 410.58 | D21: 02419310 | E21: ENRIQUEZ-ILLESCAS-LAURA | F21: PP-089 | G21: periodo anterior
A22: 46025 | B22: TRANSF.BCO.BBVA | C22: 30 | D22: 02799173 | E22: VICTOR DANIEL DE LA CRUZ SOLO | G22: cine
A23: 46025 | B23: TRAN.CTAS.TERC.BM | C23: 30 | D23: 00681111 | E23: MILAGROS MERCEDES BARRIENTOS FLORES | G23: cine
A24: 46025 | B24: TRAN.CTAS.TERC.BM | C24: 391.13 | D24: 04257108 | E24: LI NN XIAN YI | F24: PP-189 | G24: periodo anterior
A25: 46027 | B25: TRAN.CTAS.TERC.BM | C25: 254.32 | D25: 04138284 | E25: depa 708 | F25: PP-136 | G25: periodo anterior
A26: 46027 | B26: TRAN.CTAS.TERC.BM | C26: 254.43 | D26: 01810104 | E26: LOCK GOVEA JOSE EDILBERTO | F26: PP-067 | G26: periodo anterior
A27: 46027 | B27: TRAN.CTAS.TERC.BM | C27: 365.88 | D27: 05568200 | E27: depa 807 | F27: PP-164 | G27: periodo anterior
A28: 46027 | B28: TRAN.CTAS.TERC.BM | C28: 365.88 | D28: 05171425 | E28: depa 807 | F28: PP-164 | G28: periodo anterior
A29: 46027 | B29: TRAN.CTAS.TERC.BM | C29: 403.63 | D29: 04733331 | E29: TRAN.CTAS.TERC.BM | F29: PP-151 | G29: periodo anterior
A30: 46027 | B30: TRANSF.BCO.INTERBANK | C30: 529.77 | D30: 02918078 | E30: CHUMPITAZ-JORDAN-GIANFRANCO | F30: PP-182 | G30: periodo anterior
A31: 46028 | B31: TRAN.CTAS.TERC.BM | C31: 40 | D31: 01167585 | E31: TOLOSA ALVAREZ WILKENDRY ANTONIO | G31: parrilla
A32: 46028 | B32: TRANSF.BCO.SCOTIABANK | C32: 186 | D32: 02838839 | E32: ROSA TUME ZEGARRA | F32: PP-123 | G32: periodo anterior
A33: 46028 | B33: TRAN.CTAS.TERC.BM | C33: 303.3 | D33: 06339795 | E33: CHAVEZ MYLADY | F33: PP-036 | G33: periodo anterior
A34: 46029 | B34: TRAN.CTAS.TERC.HK | C34: 77.76 | D34: 06000739 | E34: ORELLANA VARGAS CARMEN ROSA | F34: PP-123 | G34: 2026-01
A35: 46029 | B35: TRANSF.BCO.BBVA | C35: 170.93 | D35: 02314420 | E35: SANCHEZ-SALAZAR OLCESE GLADYS MARIELA | F35: PP-154 | G35: periodo anterior
A36: 46029 | B36: TRAN.CTAS.TERC.BM | C36: 170.93 | D36: 00142069 | E36: PAOLA FABIOLA QUI�ONES PONCE DE LEON | F36: PP-187 | G36: periodo anterior
A37: 46029 | B37: TRAN.CTAS.TERC.BM | C37: 383.1 | D37: 01158104 | E37: CASTILLA PEREZ CARMELA FERMINA | F37: PP-029 | G37: periodo anterior
A38: 46029 | B38: TRAN.CTAS.TERC.BM | C38: 392.97 | D38: 01049363 | E38: CASTILLA PEREZ CARMELA FERMINA | F38: PP-029 | G38: periodo anterior
A39: 46029 | B39: TRAN.CTAS.TERC.BM | C39: 393.7 | D39: 03385120 | E39: TRAN.CTAS.TERC.BM | F39: PP-085 | G39: periodo anterior
A40: 46030 | B40: TRAN.CTAS.TERC.BM | C40: 4.51 | D40: 03475750 | E40: DE-LA-CRUZ DELGADO WALTER | F40: PP-044 | G40: periodo anterior
A41: 46030 | B41: TRANSF.BCO.INTERBANK | C41: 40 | D41: 02904936 | E41: BELLIDO-GUILLEN-LINO | G41: parrilla
A42: 46030 | B42: TRAN.CTAS.TERC.BM | C42: 182.5 | D42: 04638121 | E42: MENDOZA SALDANA FRANK ANDRE | F42: PP-038 | G42: periodo anterior
A43: 46030 | B43: TRANSF.BCO.BBVA | C43: 254.43 | D43: 02518085 | E43: RUBEN DARIO TORANZO SILVA | F43: PP-167 | G43: periodo anterior
A44: 46030 | B44: TRANSF.BCO.INTERBANK | C44: 340.91 | D44: 02292184 | E44: GUTIERREZ-ESQUICHA-OLIVER | F44: PP-105 | G44: periodo anterior
A45: 46030 | B45: TRAN.CTAS.TERC.BM | C45: 374.82 | D45: 03018563 | E45: GUTIERREZ GUERRERO YEISON MARTIN | F45: PP-074 | G45: periodo anterior
A46: 46030 | B46: TRAN.CTAS.TERC.BM | C46: 380.77 | D46: 03002185 | E46: DE-LA-CRUZ DELGADO WALTER | F46: PP-044 | G46: periodo anterior
A47: 46030 | B47: TRANSF.BCO.INTERBANK | C47: 449.69 | D47: 02265234 | E47: CALDERON-MINCHOLA-DENIS | F47: PP-018 | G47: periodo anterior
A48: 46031 | B48: TRANSF.BCO.INTERBANK | C48: 162.54 | D48: 02200714 | E48: MORALES-DURAND-DE-DURAN-ZANDRA | F48: PP-102 | G48: 2026-01
A49: 46031 | B49: TRANSF.BCO.INTERBANK | C49: 173.85 | D49: 02660627 | E49: ALVAREZ-SALAS-CARLOS | F49: PP-194 | G49: 2026-01
A50: 46031 | B50: TRANSF.BCO.INTERBANK | C50: 182.85 | D50: 02660627 | E50: ALVAREZ-SALAS-CARLOS | F50: PP-194 | G50: periodo anterior
A51: 46031 | B51: TRANSF.BCO.INTERBANK | C51: 194.2 | D51: 02184327 | E51: CARRILLO GALLO EDSON | F51: PP-026 | G51: periodo anterior
A52: 46031 | B52: TRAN.CTAS.TERC.BM | C52: 247.16 | D52: 04726952 | E52: MONTESINOS CAMPOS NATALY MAGDALENA | F52: PP-112 | G52: 2026-01
A53: 46031 | B53: TRAN.CTAS.TERC.BM | C53: 269.25 | D53: 01494617 | E53: VALDEZ CADENILLAS AGUSTIN | F53: PP-174 | G53: 2026-01
... A62: 46031 | B62: TRAN.CTAS.TERC.BM | C62: 633.76 | D62: 02742386 | E62: LIZARZABURU PETROZZI MIKEL ARITZ | F62: PP-097 | G62: 2026-01
A63: 46032 | B63: TRAN.CTAS.TERC.BM | C63: 40 | D63: 03349699 | E63: GARCIA ARCE ANDRES DANIEL | G63: parrilla
A64: 46032 | B64: TRAN.CTAS.TERC.BM | C64: 40 | D64: 01048107 | E64: FIGUEROA ALVARADO YNES LUCIA | G64: parrilla
A65: 46032 | B65: TRAN.CTAS.TERC.BM | C65: 100 | D65: 03010975 | E65: MALDONADO DE-LA-CRUZ NORA TERESA | G65: arcade
A66: 46032 | B66: TRAN.CTAS.TERC.BM | C66: 179.87 | D66: 03113512 | E66: MALDONADO DE-LA-CRUZ NORA TERESA | F66: PP-104 | G66: periodo anterior
A67: 46032 | B67: TRAN.CTAS.TERC.BM | C67: 303.24 | D67: 03836498 | E67: ROCA ZEGARRA RAQUEL JENIFFER | F67: PP-062 | G67: periodo anterior
A68: 46032 | B68: TRAN.CTAS.TERC.BM | C68: 327.84 | D68: 00730004 | E68: SILVA OLIVERA IVET JOHANA | F68: PP-023 | G68: periodo anterior
A69: 46032 | B69: TRAN.CTAS.TERC.BM | C69: 332.52 | D69: 05791971 | E69: CARDENAS MORIANO HEVELYNE HILDA | F69: PP-022 | G69: periodo anterior
A70: 46032 | B70: TRAN.CTAS.TERC.BM | C70: 359.34 | D70: 05018010 | E70: CAO NN DACHAO | F70: PP-021 | G70: 2026-01
A71: 46032 | B71: TRANSF.BCO.INTERBANK | C71: 373.43 | D71: 02934212 | E71: BERROSPI-SEVILLANOS-SEVILLANOS-JHOJAN KLAUS | F71: PP-115 | G71: 2026-01
A72: 46032 | B72: TRANSF.BCO.INTERBANK | C72: 395.68 | D72: 02175799 | E72: OCHOA-ALEJOS-CESAR | F72: PP-120 | G72: periodo anterior
A73: 46032 | B73: TRANSF.BCO.INTERBANK | C73: 395.68 | D73: 02934212 | E73: BERROSPI-SEVILLANOS-SEVILLANOS-JHOJAN KLAUS | F73: PP-115 | G73: periodo anterior
A74: 46032 | B74: TRAN.CTAS.TERC.BM | C74: 1189.03 | D74: 05245257 | E74: GAMERO OSCAR | F74: PP-055 | G74: periodo anterior
A75: 46032 | B75: TRAN.CTAS.TERC.BM | C75: 373.43 | D75: 05245257 | E75: GAMERO OSCAR | F75: PP-055 | G75: 2026-01
A76: 46033 | B76: TRAN.CTAS.TERC.BM | C76: 30 | D76: 02770423 | E76: ANGELICA MARIA FLORES TORRES | G76: cine
A77: 46033 | B77: TRAN.CTAS.TERC.BM | C77: 260.33 | D77: 02034068 | E77: SALINAS SOUZA CARLOS ENRIQUE JOSE ALFR | F77: PP-150 | G77: 2026-01
A78: 46033 | B78: TRAN.CTAS.TERC.BM | C78: 366.86 | D78: 01353408 | E78: TORRES VILLANTOY SUSAN VICTORIA | F78: PP-171 | G78: 2026-01
A79: 46033 | B79: TRAN.CTAS.TERC.BM | C79: 387.36 | D79: 01353408 | E79: TORRES VILLANTOY SUSAN VICTORIA | F79: PP-171 | G79: periodo anterior
A80: 46033 | B80: TRANSF.BCO.BBVA | C80: 418.91 | D80: 02015232 | E80: HELEN FRANCESCA HENOSTROZA CRUZ | F80: PP-077 | G80: periodo anterior
A81: 46033 | B81: TRAN.CTAS.TERC.BM | C81: 418.99 | D81: 02836574 | E81: PARI NUNEZ LEONOR | F81: PP-085 | G81: periodo anterior
A82: 46033 | B82: TRAN.CTAS.TERC.BM | C82: 563.94 | D82: 03064956 | E82: SOTO CONDORI GIANFRANCO | F82: PP-161 | G82: periodo anterior
A83: 46033 | B83: TRAN.CTAS.TERC.BM | C83: 831.62 | D83: 02977641 | E83: LOPEZ PARI SHEYLA KATHERINE | F83: PP-195 | G83: periodo anterior
A84: 46034 | B84: TRAN.CTAS.TERC.BM | C84: 40 | D84: 03231282 | E84: NEGRINI WITHER JORGE ENRIQUE | G84: parrilla
A85: 46034 | B85: TRAN.CTAS.TERC.BM | C85: 40 | D85: 01327165 | E85: LOPEZ PARI SHEYLA KATHERINE | G85: parrilla
A86: 46034 | B86: TRANSF.BCO.BBVA | C86: 40 | D86: 02891361 | E86: GIANELLA LIZETH NEIRA BUSTAMANTE | G86: parrilla
A87: 46034 | B87: TRANSF.BCO.INTERBANK | C87: 40 | D87: 02721640 | E87: DELGADO-SILVA-LUIS | G87: parrilla
A88: 46034 | B88: TRAN.CTAS.TERC.BM | C88: 180.93 | D88: 04199280 | E88: RENTERIA CHIOK MARIA ISABEL | F88: PP-139 | G88: periodo anterior
A89: 46034 | B89: TRANSF.BCO.INTERBANK | C89: 182.41 | D89: 02999153 | E89: BERMEJO-DE-LA-CRUZ-JOSE | F89: PP-168 | G89: periodo anterior
A90: 46034 | B90: TRAN.CTAS.TERC.BM | C90: 182.85 | D90: 04921090 | E90: PEREZ SANCHEZ KIRIA JAEL | F90: PP-168 | G90: periodo anterior
A91: 46034 | B91: TRANSF.BCO.SCOTIABANK | C91: 251.45 | D91: 02660772 | E91: M C V dni: 43795888 | F91: PP-093 | G91: periodo anterior
A92: 46034 | B92: TRAN.CTAS.TERC.BM | C92: 266.28 | D92: 02212696 | E92: MONZON JUAREZ MILAGROS DEL CARMEN | F92: PP-134 | G92: 2026-01
A93: 46034 | B93: TRAN.CTAS.TERC.BM | C93: 279.29 | D93: 01960247 | E93: DELGADO SALDANA ALBERTO ALEXANDE | F93: PP-179 | G93: 2026-01
A94: 46034 | B94: TRANSF.BCO.INTERBANK | C94: 311.19 | D94: 02053837 | E94: DELGADO-SILVA-LUIS | F94: PP-071 | G94: periodo anterior
A95: 46034 | B95: TRAN.CTAS.TERC.BM | C95: 347.19 | D95: 02223428 | E95: LIANG NN YANQIU | F95: PP-096 | G95: 2026-01
A96: 46034 | B96: TRAN.CTAS.TERC.BM | C96: 361.53 | D96: 00994572 | E96: YOUNG GUERRERO MARIA GISELLA | F96: PP-190 | G96: 2026-01
A97: 46034 | B97: TRAN.CTAS.TERC.BM | C97: 383.76 | D97: 02419849 | E97: GONZALES VIDAL MIGUEL ANGEL | F97: PP-065 | G97: periodo anterior
A98: 46034 | B98: TRANSF.BCO.NACION | C98: 395.44 | D98: 02793293 | E98: CARMEN MALACHE | F98: PP-002 | G98: periodo anterior
A99: 46034 | B99: TRAN.CTAS.TERC.BM | C99: 395.68 | D99: 03319508 | E99: FIGUEROA MARQUEZ ELIZABETH JANETH | F99: PP-181 | G99: periodo anterior
A100: 46035 | B100: TRANSF.BCO.INTERBANK | C100: 526.75 | D100: 02005044 | E100: GUTIERREZ-PECEROS-ALBERTO | F100: PP-075 | G100: periodo anterior
A101: 46036 | B101: TRAN.CTAS.TERC.BM | C101: 40 | D101: 02926360 | E101: VALLEBUONA MAYTA LUIS ALBERTO | G101: parrilla
A102: 46036 | B102: TRANSF.BCO.SCOTIABANK | C102: 76.29 | D102: 02589723 | E102: L V F ce:99999999 | F102: PP-116 | G102: 2026-01
A103: 46036 | B103: TRANSF.BCO.BBVA | C103: 300.26 | D103: 02772836 | E103: ANA CLAUDIA ARRESCURENAGA ORIHUELA | F103: PP-037 | G103: periodo anterior
A104: 46036 | B104: TRANSF.BCO.INTERBANK | C104: 303.09 | D104: 02247147 | E104: RODRIGUEZ-SOSA-TAMARA | F104: PP-142 | G104: 2026-01
A105: 46036 | B105: DE COMPANIA INCUBADORA | C105: =334.11+33.07 -> 367.18 | D105: 01260937 | E105: DE COMPANIA INCUBADORA | F105: PP-147 | G105: 2026-01
A106: 46036 | B106: TRAN.CTAS.TERC.BM | C106: 373.43 | D106: 00714353 | E106: MADUENO CHUMPITAZ LOURDES DE LOS ANGELES | F106: PP-196 | G106: 2026-01
A107: 46036 | B107: TRAN.CTAS.TERC.BM | C107: 580 | D107: 03096777 | E107: ZAPATA VELASCO ANGELA PATRICIA | G107: lounge
A108: 46036 | B108: DE COMPANIA INCUBADORA | C108: 2128.87 | D108: 01260937 | E108: DE COMPANIA INCUBADORA | F108: PP-147 | G108: periodo anterior
A109: 46037 | B109: TRANSF.BCO.SCOTIABANK | C109: 40 | D109: 02413093 | E109: J S C dni:72859311 | G109: parrilla
...

Sheet saldo
A1: JUNTA DE PROPIETARIOS DEL EDIFICIO MULTIFAMILIAR "PACIFIK OCEAN TOWER"
A2: 20614642247
A3: Av. Bertolotto 850 - San Miguel
A5: codigo | B5: propietario | C5: predio | D5: periodo anterior | E5: 2026-01 | F5: Saldo acumulado
A6: PP-001 | B6: AJK ASOCIADOS SAC | C6: DEPA-1605 | D6: =VLOOKUP($A6,cuotas!$A$5:$E$209,4,0)-SUMIFS(ingresos!$C:$C,ingresos!$F:$F,saldo!$A6,ingresos!$G:$G,saldo!D$5) -> 377.02 | E6: =VLOOKUP($A6,cuotas!$A$5:$E$209,5,0)-SUMIFS(ingresos!$C:$C,ingresos!$F:$F,saldo!$A6,ingresos!$G:$G,saldo!E$5) -> 353.38 | F6: =SUM(D6:E6) -> 730.4
A7: PP-002 | B7: ALBAN MALACHE CHABELI | C7: DEPA-612 | D7: =VLOOKUP($A7,cuotas!$A$5:$E$209,4,0)-SUMIFS(ingresos!$C:$C,ingresos!$F:$F,saldo!$A7,ingresos!$G:$G,saldo!D$5) -> 0 | E7: =VLOOKUP($A7,cuotas!$A$5:$E$209,5,0)-SUMIFS(ingresos!$C:$C,ingresos!$F:$F,saldo!$A7,ingresos!$G:$G,saldo!E$5) -> 0 | F7: =SUM(D7:E7) -> 0
A8: PP-003 | B8: RUIZ JAVIER ALEJANDRO | C8: DEPA-811 | D8: =VLOOKUP($A8,cuotas!$A$5:$E$209,4,0)-SUMIFS(ingresos!$C:$C,ingresos!$F:$F,saldo!$A8,ingresos!$G:$G,saldo!D$5) -> 0 | E8: =VLOOKUP($A8,cuotas!$A$5:$E$209,5,0)-SUMIFS(ingresos!$C:$C,ingresos!$F:$F,saldo!$A8,ingresos!$G:$G,saldo!E$5) -> 0 | F8: =SUM(D8:E8) -> 0
A9: PP-004 | B9: ALEXANDER STRAHLE JURGEN | C9: DEPA-902 | D9: =VLOOKUP($A9,cuotas!$A$5:$E$209,4,0)-SUMIFS(ingresos!$C:$C,ingresos!$F:$F,saldo!$A9,ingresos!$G:$G,saldo!D$5) -> 0 | E9: =VLOOKUP($A9,cuotas!$A$5:$E$209,5,0)-SUMIFS(ingresos!$C:$C,ingresos!$F:$F,saldo!$A9,ingresos!$G:$G,saldo!E$5) -> 364.5 | F9: =SUM(D9:E9) -> 364.5
A10: PP-005 | B10: ALVA CUELLAR DUGLAS CONCEPCION | C10: DEPA-1205 | D10: =VLOOKUP($A10,cuotas!$A$5:$E$209,4,0)-SUMIFS(ingresos!$C:$C,ingresos!$F:$F,saldo!$A10,ingresos!$G:$G,saldo!D$5) -> 0 | E10: =VLOOKUP($A10,cuotas!$A$5:$E$209,5,0)-SUMIFS(ingresos!$C:$C,ingresos!$F:$F,saldo!$A10,ingresos!$G:$G,saldo!E$5) -> 397.23 | F10: =SUM(D10:E10) -> 397.23
A11: PP-006 | B11: ALVARADO BRINGAS MILUSKA CARLA | C11: DEPA-1001 | D11: =VLOOKUP($A11,cuotas!$A$5:$E$209,4,0)-SUMIFS(ingresos!$C:$C,ingresos!$F:$F,saldo!$A11,ingresos!$G:$G,saldo!D$5) -> 0 | E11: =VLOOKUP($A11,cuotas!$A$5:$E$209,5,0)-SUMIFS(ingresos!$C:$C,ingresos!$F:$F,saldo!$A11,ingresos!$G:$G,saldo!E$5) -> 0 | F11: =SUM(D11:E11) -> 0
A12: PP-007 | B12: ANTON ENICE | C12: DEPA-610 | D12: =VLOOKUP($A12,cuotas!$A$5:$E$209,4,0)-SUMIFS(ingresos!$C:$C,ingresos!$F:$F,saldo!$A12,ingresos!$G:$G,saldo!D$5) -> 1913.57 | E12: =VLOOKUP($A12,cuotas!$A$5:$E$209,5,0)-SUMIFS(ingresos!$C:$C,ingresos!$F:$F,saldo!$A12,ingresos!$G:$G,saldo!E$5) -> 296.71 | F12: =SUM(D12:E12) -> 2210.28
A13: PP-008 | B13: APARCANA ROSADIO LUIS MIGUEL | C13: DEPA-606 | D13: =VLOOKUP($A13,cuotas!$A$5:$E$209,4,0)-SUMIFS(ingresos!$C:$C,ingresos!$F:$F,saldo!$A13,ingresos!$G:$G,saldo!D$5) -> 0 | E13: =VLOOKUP($A13,cuotas!$A$5:$E$209,5,0)-SUMIFS(ingresos!$C:$C,ingresos!$F:$F,saldo!$A13,ingresos!$G:$G,saldo!E$5) -> 0 | F13: =SUM(D13:E13) -> 0
A14: PP-009 | B14: ASTO VARGAS HANS PIERRE | C14: DEPA-1311 | D14: =VLOOKUP($A14,cuotas!$A$5:$E$209,4,0)-SUMIFS(ingresos!$C:$C,ingresos!$F:$F,saldo!$A14,ingresos!$G:$G,saldo!D$5) -> 3.34 | E14: =VLOOKUP($A14,cuotas!$A$5:$E$209,5,0)-SUMIFS(ingresos!$C:$C,ingresos!$F:$F,saldo!$A14,ingresos!$G:$G,saldo!E$5) -> 0 | F14: =SUM(D14:E14) -> 3.34
A15: PP-010 | B15: AVENDAÑO SILVA MIRLEY JESUS | C15: ESTA-087 | D15: =VLOOKUP($A15,cuotas!$A$5:$E$209,4,0)-SUMIFS(ingresos!$C:$C,ingresos!$F:$F,saldo!$A15,ingresos!$G:$G,saldo!D$5) -> 241.56 | E15: =VLOOKUP($A15,cuotas!$A$5:$E$209,5,0)-SUMIFS(ingresos!$C:$C,ingresos!$F:$F,saldo!$A15,ingresos!$G:$G,saldo!E$5) -> 76.29 | F15: =SUM(D15:E15) -> 317.85
A16: PP-011 | B16: AVILA JOEL ANTONIO | C16: DEPA-804 | D16: =VLOOKUP($A16,cuotas!$A$5:$E$209,4,0)-SUMIFS(ingresos!$C:$C,ingresos!$F:$F,saldo!$A16,ingresos!$G:$G,saldo!D$5) -> 0 | E16: =VLOOKUP($A16,cuotas!$A$5:$E$209,5,0)-SUMIFS(ingresos!$C:$C,ingresos!$F:$F,saldo!$A16,ingresos!$G:$G,saldo!E$5) -> 0 | F16: =SUM(D16:E16) -> 0
A17: PP-012 | B17: AYAQUE LARICO ISAAC ALFREDO | C17: DEPA-1602 | D17: =VLOOKUP($A17,cuotas!$A$5:$E$209,4,0)-SUMIFS(ingresos!$C:$C,ingresos!$F:$F,saldo!$A17,ingresos!$G:$G,saldo!D$5) -> 0 | E17: =VLOOKUP($A17,cuotas!$A$5:$E$209,5,0)-SUMIFS(ingresos!$C:$C,ingresos!$F:$F,saldo!$A17,ingresos!$G:$G,saldo!E$5) -> 0 | F17: =SUM(D17:E17) -> 0
... A208: PP-LAV | B208: LAVANDERIA PRONTOMATIK | C208: PP-LAV | D208: =VLOOKUP($A208,cuotas!$A$5:$E$209,4,0)-SUMIFS(ingresos!$C:$C,ingresos!$F:$F,saldo!$A208,ingresos!$G:$G,saldo!D$5) -> 0 | E208: =VLOOKUP($A208,cuotas!$A$5:$E$209,5,0)-SUMIFS(ingresos!$C:$C,ingresos!$F:$F,saldo!$A208,ingresos!$G:$G,saldo!E$5) -> 0 | F208: =SUM(D208:E208) -> 0

Sheet reciboxmes
A1: JUNTA DE PROPIETARIOS DEL EDIFICIO MULTIFAMILIAR "PACIFIK OCEAN TOWER"
A2: 20614642247
A3: Av. Bertolotto 850 - San Miguel
A5: RECIBO MANTENIMIENTO | H5: cuota del mes | I5: =VLOOKUP($D$19,cuota_resumen!$A:$F,6,0) -> 174.35
A7: Periodo | C7: Fecha emisión | E7: Fecha vencimiento | G7: Consumo agua (m3) | I7: Codigo Propietario
A8: 2026-febrero | C8: 46060 | E8: 46075 | G8: =IFERROR(VLOOKUP($C$22,consumo_agua!$A$7:$AA$202,25,0),0) -> 4 | I8: =$D$19 -> PP-038
A10: Titular 1 | C10: =VLOOKUP($I$8,cuotas!$A:$B,2,0) -> CHIROQUE FLOR LOZANO
A12: Titular 2
A14: Arrendatario
C19: CODIGO | D19: PP-038
C21: Predio | D21: % PARTICIPACIÓN | E21: VALOR CUOTA | F21: S/. AGUA CONSUMO | G21: SUMA
C22: DEPA-1011 | D22: 0.0026939 | E22: 161.95 | F22: 12.4 | G22: 174.35
C23: Total general | D23: 0.0026939 | E23: 161.95 | F23: 12.4 | G23: 174.35
A37: Informacion historica:
A38: cuotas emitidas | D38: abonos recibidos | H38: saldo por cobrar al mes anterior
A39: periodos ant. | B39: =VLOOKUP($D$19,cuotas!$A:$E,4,0) -> 175.13 | D39: codigo PP | E39: PP-038 | H39: periodos ant. | I39: =VLOOKUP($D$19,saldo!$A:$E,4,0) -> -7.37
A40: 46023 | B40: =VLOOKUP($D$19,cuotas!$A:$E,5,0) -> 171.22 | H40: 46023 | I40: =VLOOKUP($D$19,saldo!$A:$E,5,0) -> 171.22
D41: fechas | E41: Montos
B42: =SUM(B39:B41) -> 346.35 | D42: 46030 | E42: 182.5 | I42: =SUM(I39:I41) -> 163.85
D43: Total general | E43: 182.5 | H43: =IF($I$42<0,"*saldo a favor del propietario","-") -> -
A49: Recibo digital elaborado por:
A50: ALGORITMO ADMIN
