Workbook
Name agua_consumo: [1]agua!$B$10:$BZ$65
Name pp_anual26: pres!$C$2

Sheet pres
B2: PRESUPUESTO X DISTRIBUIR | C2: 60116
B4: agua potable 2025-12 | C4: =4776.4-900 -> 3876.4
C5: =SUM(C2:C4) -> 63992.4

Sheet consumo_agua
H1: recibo | I1: 4713.4 | L1: 4636.5 | O1: 5266.7 | R1: 2972.4 | U1: 3793.1 | X1: 3876.4
H2: m3 conteo | I2: =$G$203 -> 1262.229 | J2: <promedio | L2: =J203 -> 1115.961 | M2: <promedio | O2: =M203 -> 824.779 | P2: <promedio | R2: =P203 -> 1035.538 | U2: =S203 -> 1272.95 | X2: =V203 -> 1302.895 | Z2: <promedio
H3: c.u. x m3 | I3: =ROUND(I1/I2,4) -> 3.7342 | L3: =ROUND(L1/L2,4) -> 4.1547 | O3: =ROUND(O1/O2,4) -> 6.3856 | R3: =ROUND(R1/R2,4) -> 2.8704 | U3: =ROUND(U1/U2,4) -> 2.9798 | X3: =ROUND(X1/X2,4) -> 2.9752
A4: JUNTA DE PROPIETARIOS DEL EDIFICIO MULTIFAMILIAR " PACIFIK OCEAN TOWER"
A5: Historico - consumo de agua
A7: DEPAF | B7: MAYO | C7: consumo> | D7: JUNIO | E7: consumo> | F7: JULIO | G7: consumo> | H7: AGOSTO | I7: PEN-agua | J7: consumo> | K7: SET | L7: PEN-agua | M7: consumo> | N7: OCT | O7: PEN-agua | P7: consumo> | Q7: NOV | R7: PEN-agua | S7: consumo> | T7: DIC | U7: PEN-agua | V7: consumo> | W7: 46023 | X7: PEN-agua
A8: DEPA-101 | B8: 800 | C8: =D8-B8 -> 21 | D8: 821 | E8: =F8-D8 -> 22 | F8: 843 | G8: =H8-F8 -> 27 | H8: 870 | I8: =ROUND(G8*$I$3,2) -> 100.82 | J8: =K8-H8 -> 23 | K8: 893 | L8: =ROUND(J8*$L$3,2) -> 95.56 | M8: =N8-K8 -> 18 | N8: 911 | O8: =ROUND(M8*$O$3,2) -> 114.94 | P8: =Q8-N8 -> 19 | Q8: 930 | R8: =ROUND(P8*$R$3,2) -> 54.54 | S8: =+T8-Q8 -> 22 | T8: 952 | U8: =ROUND(S8*$U$3,2) -> 65.56 | V8: =+W8-T8 -> 24 | W8: 976 | X8: =V8*$X$3 -> 71.4048
A9: DEPA-102 | B9: 287 | C9: =D9-B9 -> 7 | D9: 294 | E9: =F9-D9 -> 4 | F9: 298 | G9: =H9-F9 -> 7 | H9: 305 | I9: =ROUND(G9*$I$3,2) -> 26.14 | J9: =K9-H9 -> 4 | K9: 309 | L9: =ROUND(J9*$L$3,2) -> 16.62 | M9: =N9-K9 -> 3 | N9: 312 | O9: =ROUND(M9*$O$3,2) -> 19.16 | P9: =Q9-N9 -> 3 | Q9: 315 | R9: =ROUND(P9*$R$3,2) -> 8.61 | S9: =+T9-Q9 -> 2 | T9: 317 | U9: =ROUND(S9*$U$3,2) -> 5.96 | V9: =+W9-T9 -> 2 | W9: 319 | X9: =V9*$X$3 -> 5.9504
A10: DEPA-103 | B10: 51 | C10: =D10-B10 -> 0 | D10: 51 | E10: =F10-D10 -> 0 | F10: 51 | G10: =H10-F10 -> 0 | H10: 51 | I10: =ROUND(G10*$I$3,2) -> 0 | J10: =K10-H10 -> 0 | K10: 51 | L10: =ROUND(J10*$L$3,2) -> 0 | M10: =N10-K10 -> 0 | N10: 51 | O10: =ROUND(M10*$O$3,2) -> 0 | P10: =Q10-N10 -> 0 | Q10: 51 | R10: =ROUND(P10*$R$3,2) -> 0 | S10: =+T10-Q10 -> 0 | T10: 51 | U10: =ROUND(S10*$U$3,2) -> 0 | V10: =+W10-T10 -> 0 | W10: 51 | X10: =V10*$X$3 -> 0
A11: DEPA-104 | B11: 327 | C11: =D11-B11 -> 5 | D11: 332 | E11: =F11-D11 -> 6 | F11: 338 | G11: =H11-F11 -> 7 | H11: 345 | I11: =ROUND(G11*$I$3,2) -> 26.14 | J11: =K11-H11 -> 5 | K11: 350 | L11: =ROUND(J11*$L$3,2) -> 20.77 | M11: =N11-K11 -> 5 | N11: 355 | O11: =ROUND(M11*$O$3,2) -> 31.93 | P11: =Q11-N11 -> 9 | Q11: 364 | R11: =ROUND(P11*$R$3,2) -> 25.83 | S11: =+T11-Q11 -> 8 | T11: 372 | U11: =ROUND(S11*$U$3,2) -> 23.84 | V11: =+W11-T11 -> 12 | W11: 384 | X11: =V11*$X$3 -> 35.7024
A12: DEPA-105 | B12: 532 | C12: =D12-B12 -> 10 | D12: 542 | E12: =F12-D12 -> 12 | F12: 554 | G12: =H12-F12 -> 8 | H12: 562 | I12: =ROUND(G12*$I$3,2) -> 29.87 | J12: =K12-H12 -> 13 | K12: 575 | L12: =ROUND(J12*$L$3,2) -> 54.01 | M12: =N12-K12 -> 10 | N12: 585 | O12: =ROUND(M12*$O$3,2) -> 63.86 | P12: =Q12-N12 -> 14 | Q12: 599 | R12: =ROUND(P12*$R$3,2) -> 40.19 | S12: =+T12-Q12 -> 13 | T12: 612 | U12: =ROUND(S12*$U$3,2) -> 38.74 | V12: =+W12-T12 -> 22 | W12: 634 | X12: =V12*$X$3 -> 65.4544
A13: DEPA-106 | B13: 396 | C13: =D13-B13 -> 0 | D13: 396 | E13: =F13-D13 -> 0 | F13: 396 | G13: =H13-F13 -> 1 | H13: 397 | I13: =ROUND(G13*$I$3,2) -> 3.73 | J13: =K13-H13 -> 2 | K13: 399 | L13: =ROUND(J13*$L$3,2) -> 8.31 | M13: =N13-K13 -> 5 | N13: 404 | O13: =ROUND(M13*$O$3,2) -> 31.93 | P13: =Q13-N13 -> 8 | Q13: 412 | R13: =ROUND(P13*$R$3,2) -> 22.96 | S13: =+T13-Q13 -> 9 | T13: 421 | U13: =ROUND(S13*$U$3,2) -> 26.82 | V13: =+W13-T13 -> 8 | W13: 429 | X13: =V13*$X$3 -> 23.8016
A14: DEPA-107 | B14: 25 | C14: =D14-B14 -> 0 | D14: 25 | E14: =F14-D14 -> 1 | F14: 26 | G14: =H14-F14 -> 0 | H14: 26 | I14: =ROUND(G14*$I$3,2) -> 0 | J14: =K14-H14 -> 0 | K14: 26 | L14: =ROUND(J14*$L$3,2) -> 0 | M14: =N14-K14 -> 1 | N14: 27 | O14: =ROUND(M14*$O$3,2) -> 6.39 | P14: =Q14-N14 -> 1 | Q14: 28 | R14: =ROUND(P14*$R$3,2) -> 2.87 | S14: =+T14-Q14 -> 0 | T14: 28 | U14: =ROUND(S14*$U$3,2) -> 0 | V14: =+W14-T14 -> 1 | W14: 29 | X14: =V14*$X$3 -> 2.9752
A15: DEPA-201 | B15: 128 | C15: =D15-B15 -> 8 | D15: 136 | E15: =F15-D15 -> 6 | F15: 142 | G15: =H15-F15 -> 11 | H15: 153 | I15: =ROUND(G15*$I$3,2) -> 41.08 | J15: =K15-H15 -> 8 | K15: 161 | L15: =ROUND(J15*$L$3,2) -> 33.24 | M15: =N15-K15 -> 4 | N15: 165 | O15: =ROUND(M15*$O$3,2) -> 25.54 | P15: =Q15-N15 -> 6 | Q15: 171 | R15: =ROUND(P15*$R$3,2) -> 17.22 | S15: =+T15-Q15 -> 9 | T15: 180 | U15: =ROUND(S15*$U$3,2) -> 26.82 | V15: =+W15-T15 -> 11 | W15: 191 | X15: =V15*$X$3 -> 32.7272
A16: DEPA-202 | B16: 95 | C16: =D16-B16 -> 6 | D16: 101 | E16: =F16-D16 -> 4 | F16: 105 | G16: =H16-F16 -> 6 | H16: 111 | I16: =ROUND(G16*$I$3,2) -> 22.41 | J16: =K16-H16 -> 3 | K16: 114 | L16: =ROUND(J16*$L$3,2) -> 12.46 | M16: =N16-K16 -> 4 | N16: 118 | O16: =ROUND(M16*$O$3,2) -> 25.54 | P16: =Q16-N16 -> 4 | Q16: 122 | R16: =ROUND(P16*$R$3,2) -> 11.48 | S16: =+T16-Q16 -> 5 | T16: 127 | U16: =ROUND(S16*$U$3,2) -> 14.9 | V16: =+W16-T16 -> 6 | W16: 133 | X16: =V16*$X$3 -> 17.8512
A17: DEPA-203 | B17: 234 | C17: =D17-B17 -> 4 | D17: 238 | E17: =F17-D17 -> 4 | F17: 242 | G17: =H17-F17 -> 8 | H17: 250 | I17: =ROUND(G17*$I$3,2) -> 29.87 | J17: =K17-H17 -> 3 | K17: 253 | L17: =ROUND(J17*$L$3,2) -> 12.46 | M17: =N17-K17 -> 4 | N17: 257 | O17: =ROUND(M17*$O$3,2) -> 25.54 | P17: =Q17-N17 -> 8 | Q17: 265 | R17: =ROUND(P17*$R$3,2) -> 22.96 | S17: =+T17-Q17 -> 55 | T17: 320 | U17: =ROUND(S17*$U$3,2) -> 163.89 | V17: =+W17-T17 -> 29 | W17: 349 | X17: =V17*$X$3 -> 86.2808 | Y17: *pablo
A18: DEPA-204 | B18: 145 | C18: =D18-B18 -> 4 | D18: 149 | E18: =F18-D18 -> 5 | F18: 154 | G18: =H18-F18 -> 7 | H18: 161 | I18: =ROUND(G18*$I$3,2) -> 26.14 | J18: =K18-H18 -> 5 | K18: 166 | L18: =ROUND(J18*$L$3,2) -> 20.77 | M18: =N18-K18 -> 4 | N18: 170 | O18: =ROUND(M18*$O$3,2) -> 25.54 | P18: =Q18-N18 -> 4 | Q18: 174 | R18: =ROUND(P18*$R$3,2) -> 11.48 | S18: =+T18-Q18 -> 6 | T18: 180 | U18: =ROUND(S18*$U$3,2) -> 17.88 | V18: =+W18-T18 -> 5 | W18: 185 | X18: =V18*$X$3 -> 14.876
A19: DEPA-205 | B19: 157 | C19: =D19-B19 -> 8 | D19: 165 | E19: =F19-D19 -> 7 | F19: 172 | G19: =H19-F19 -> 7 | H19: 179 | I19: =ROUND(G19*$I$3,2) -> 26.14 | J19: =K19-H19 -> 7 | K19: 186 | L19: =ROUND(J19*$L$3,2) -> 29.08 | M19: =N19-K19 -> 5 | N19: 191 | O19: =ROUND(M19*$O$3,2) -> 31.93 | P19: =Q19-N19 -> 3 | Q19: 194 | R19: =ROUND(P19*$R$3,2) -> 8.61 | S19: =+T19-Q19 -> 8 | T19: 202 | U19: =ROUND(S19*$U$3,2) -> 23.84 | V19: =+W19-T19 -> 9 | W19: 211 | X19: =V19*$X$3 -> 26.7768
A20: DEPA-206 | B20: 131 | C20: =D20-B20 -> 4 | D20: 135 | E20: =F20-D20 -> 4 | F20: 139 | G20: =H20-F20 -> 7 | H20: 146 | I20: =ROUND(G20*$I$3,2) -> 26.14 | J20: =K20-H20 -> 5 | K20: 151 | L20: =ROUND(J20*$L$3,2) -> 20.77 | M20: =N20-K20 -> 3 | N20: 154 | O20: =ROUND(M20*$O$3,2) -> 19.16 | P20: =Q20-N20 -> 2 | Q20: 156 | R20: =ROUND(P20*$R$3,2) -> 5.74 | S20: =+T20-Q20 -> 0 | T20: 156 | U20: =ROUND(S20*$U$3,2) -> 0 | V20: =+W20-T20 -> 1 | W20: 157 | X20: =V20*$X$3 -> 2.9752
A21: DEPA-207 | B21: 196 | C21: =D21-B21 -> 4 | D21: 200 | E21: =F21-D21 -> 4 | F21: 204 | G21: =H21-F21 -> 5 | H21: 209 | I21: =ROUND(G21*$I$3,2) -> 18.67 | J21: =K21-H21 -> 4 | K21: 213 | L21: =ROUND(J21*$L$3,2) -> 16.62 | M21: =N21-K21 -> 3 | N21: 216 | O21: =ROUND(M21*$O$3,2) -> 19.16 | P21: =Q21-N21 -> 5 | Q21: 221 | R21: =ROUND(P21*$R$3,2) -> 14.35 | S21: =+T21-Q21 -> 0 | T21: 221 | U21: =ROUND(S21*$U$3,2) -> 0 | V21: =+W21-T21 -> 7 | W21: 228 | X21: =V21*$X$3 -> 20.8264
A22: DEPA-208 | B22: 258 | C22: =D22-B22 -> 9 | D22: 267 | E22: =F22-D22 -> 9 | F22: 276 | G22: =H22-F22 -> 5 | H22: 281 | I22: =ROUND(G22*$I$3,2) -> 18.67 | J22: =K22-H22 -> 12 | K22: 293 | L22: =ROUND(J22*$L$3,2) -> 49.86 | M22: =N22-K22 -> 5 | N22: 298 | O22: =ROUND(M22*$O$3,2) -> 31.93 | P22: =Q22-N22 -> 8 | Q22: 306 | R22: =ROUND(P22*$R$3,2) -> 22.96 | S22: =+T22-Q22 -> 10 | T22: 316 | U22: =ROUND(S22*$U$3,2) -> 29.8 | V22: =+W22-T22 -> 9 | W22: 325 | X22: =V22*$X$3 -> 26.7768
A23: DEPA-209 | B23: 14 | C23: =D23-B23 -> 1 | D23: 15 | E23: =F23-D23 -> 1 | F23: 16 | G23: =H23-F23 -> 0 | H23: 16 | I23: =ROUND(G23*$I$3,2) -> 0 | J23: =K23-H23 -> 1 | K23: 17 | L23: =ROUND(J23*$L$3,2) -> 4.15 | M23: =N23-K23 -> 0 | N23: 17 | O23: =ROUND(M23*$O$3,2) -> 0 | P23: =Q23-N23 -> 1 | Q23: 18 | R23: =ROUND(P23*$R$3,2) -> 2.87 | S23: =+T23-Q23 -> 1 | T23: 19 | U23: =ROUND(S23*$U$3,2) -> 2.98 | V23: =+W23-T23 -> 0 | W23: 19 | X23: =V23*$X$3 -> 0
A24: DEPA-210 | B24: 332.49 | C24: =D24-B24 -> 16.86 | D24: 349.35 | E24: =F24-D24 -> 18.18 | F24: 367.53 | G24: =H24-F24 -> 15.545 | H24: 383.075 | I24: =ROUND(G24*$I$3,2) -> 58.05 | J24: =K24-H24 -> 16.925 | K24: 400 | L24: =ROUND(J24*$L$3,2) -> 70.32 | M24: =N24-K24 -> 13.082 | N24: 413.082 | O24: =ROUND(M24*$O$3,2) -> 83.54 | P24: =Q24-N24 -> 14.926 | Q24: 428.008 | R24: =ROUND(P24*$R$3,2) -> 42.84 | S24: =+T24-Q24 -> 3.567 | T24: 431.575 | U24: =ROUND(S24*$U$3,2) -> 10.63 | V24: =+W24-T24 -> 8.425 | W24: 440 | X24: =V24*$X$3 -> 25.06606
A25: DEPA-301 | B25: 72 | C25: =D25-B25 -> 1 | D25: 73 | E25: =F25-D25 -> 1 | F25: 74 | G25: =H25-F25 -> 2 | H25: 76 | I25: =ROUND(G25*$I$3,2) -> 7.47 | J25: =K25-H25 -> 1 | K25: 77 | L25: =ROUND(J25*$L$3,2) -> 4.15 | M25: =N25-K25 -> 0 | N25: 77 | O25: =ROUND(M25*$O$3,2) -> 0 | P25: =Q25-N25 -> 1 | Q25: 78 | R25: =ROUND(P25*$R$3,2) -> 2.87 | S25: =+T25-Q25 -> 0 | T25: 78 | U25: =ROUND(S25*$U$3,2) -> 0 | V25: =+W25-T25 -> 0 | W25: 78 | X25: =V25*$X$3 -> 0
A26: DEPA-302 | B26: 12 | C26: =D26-B26 -> 6 | D26: 18 | E26: =F26-D26 -> 4 | F26: 22 | G26: =H26-F26 -> 5 | H26: 27 | I26: =ROUND(G26*$I$3,2) -> 18.67 | J26: =K26-H26 -> 5 | K26: 32 | L26: =ROUND(J26*$L$3,2) -> 20.77 | M26: =N26-K26 -> 5 | N26: 37 | O26: =ROUND(M26*$O$3,2) -> 31.93 | P26: =Q26-N26 -> 9 | Q26: 46 | R26: =ROUND(P26*$R$3,2) -> 25.83 | S26: =+T26-Q26 -> 12 | T26: 58 | U26: =ROUND(S26*$U$3,2) -> 35.76 | V26: =+W26-T26 -> 11 | W26: 69 | X26: =V26*$X$3 -> 32.7272
A27: DEPA-303 | B27: 58 | C27: =D27-B27 -> 0 | D27: 58 | E27: =F27-D27 -> 0 | F27: 58 | G27: =H27-F27 -> 3 | H27: 61 | I27: =ROUND(G27*$I$3,2) -> 11.2 | J27: =K27-H27 -> 0 | K27: 61 | L27: =ROUND(J27*$L$3,2) -> 0 | M27: =N27-K27 -> 0 | N27: 61 | O27: =ROUND(M27*$O$3,2) -> 0 | P27: =Q27-N27 -> 1 | Q27: 62 | R27: =ROUND(P27*$R$3,2) -> 2.87 | S27: =+T27-Q27 -> 0 | T27: 62 | U27: =ROUND(S27*$U$3,2) -> 0 | V27: =+W27-T27 -> 1 | W27: 63 | X27: =V27*$X$3 -> 2.9752
A28: DEPA-304 | B28: 434 | C28: =D28-B28 -> 13 | D28: 447 | E28: =F28-D28 -> 13 | F28: 460 | G28: =H28-F28 -> 13 | H28: 473 | I28: =ROUND(G28*$I$3,2) -> 48.54 | J28: =K28-H28 -> 12 | K28: 485 | L28: =ROUND(J28*$L$3,2) -> 49.86 | M28: =N28-K28 -> 7 | N28: 492 | O28: =ROUND(M28*$O$3,2) -> 44.7 | P28: =Q28-N28 -> 6 | Q28: 498 | R28: =ROUND(P28*$R$3,2) -> 17.22 | S28: =+T28-Q28 -> 2 | T28: 500 | U28: =ROUND(S28*$U$3,2) -> 5.96 | V28: =+W28-T28 -> 4 | W28: 504 | X28: =V28*$X$3 -> 11.9008
A29: DEPA-305 | B29: 60.11 | C29: =D29-B29 -> 4.28 | D29: 64.39 | E29: =F29-D29 -> 4.77 | F29: 69.16 | G29: =H29-F29 -> 5.735 | H29: 74.895 | I29: =ROUND(G29*$I$3,2) -> 21.42 | J29: =K29-H29 -> 2.581 | K29: 77.476 | L29: =ROUND(J29*$L$3,2) -> 10.72 | M29: =N29-K29 -> 2.935 | N29: 80.411 | O29: =ROUND(M29*$O$3,2) -> 18.74 | P29: =Q29-N29 -> 4.589 | Q29: 85 | R29: =ROUND(P29*$R$3,2) -> 13.17 | S29: =+T29-Q29 -> 5.048 | T29: 90.048 | U29: =ROUND(S29*$U$3,2) -> 15.04 | V29: =+W29-T29 -> 5.952 | W29: 96 | X29: =V29*$X$3 -> 17.70839
... A122: DEPA-1103 | B122: 210 | C122: =D122-B122 -> 4 | D122: 214 | E122: =F122-D122 -> 4 | F122: 218 | G122: =H122-F122 -> 9 | H122: 227 | I122: =ROUND(G122*$I$3,2) -> 33.61 | J122: =K122-H122 -> 3 | K122: 230 | L122: =ROUND(J122*$L$3,2) -> 12.46 | M122: =N122-K122 -> 2 | N122: 232 | O122: =ROUND(M122*$O$3,2) -> 12.77 | P122: =Q122-N122 -> 4 | Q122: 236 | R122: =ROUND(P122*$R$3,2) -> 11.48 | S122: =+T122-Q122 -> 5 | T122: 241 | U122: =ROUND(S122*$U$3,2) -> 14.9 | V122: =+W122-T122 -> 10 | W122: 251 | X122: =V122*$X$3 -> 29.752
A123: DEPA-1104 | B123: 298 | C123: =D123-B123 -> 5 | D123: 303 | E123: =F123-D123 -> 4 | F123: 307 | G123: 5 | H123: 62 | I123: =ROUND(G123*$I$3,2) -> 18.67 | J123: =K123-H123 -> 13 | K123: 75 | L123: =ROUND(J123*$L$3,2) -> 54.01 | M123: =N123-K123 -> 9 | N123: 84 | O123: =ROUND(M123*$O$3,2) -> 57.47 | P123: =Q123-N123 -> 11 | Q123: 95 | R123: =ROUND(P123*$R$3,2) -> 31.57 | S123: =+T123-Q123 -> 12 | T123: 107 | U123: =ROUND(S123*$U$3,2) -> 35.76 | V123: =+W123-T123 -> 12 | W123: 119 | X123: =V123*$X$3 -> 35.7024 | Z123: *medidor nuevo val. 25/08/2025
A124: DEPA-1105 | B124: 380.08 | C124: =D124-B124 -> 10.82 | D124: 390.9 | E124: =F124-D124 -> 9.63 | F124: 400.53 | G124: =H124-F124 -> 11.706 | H124: 412.236 | I124: =ROUND(G124*$I$3,2) -> 43.71 | J124: =K124-H124 -> 12.277 | K124: 424.513 | L124: =ROUND(J124*$L$3,2) -> 51.01 | M124: =N124-K124 -> 8.038 | N124: 432.551 | O124: =ROUND(M124*$O$3,2) -> 51.33 | P124: =Q124-N124 -> 7.449 | Q124: 440 | R124: =ROUND(P124*$R$3,2) -> 21.38 | S124: =+T124-Q124 -> 12.669 | T124: 452.669 | U124: =ROUND(S124*$U$3,2) -> 37.75 | V124: =+W124-T124 -> 9.331 | W124: 462 | X124: =V124*$X$3 -> 27.761591
A125: DEPA-1106 | B125: 35 | C125: =D125-B125 -> 1 | D125: 36 | E125: =F125-D125 -> 0 | F125: 36 | G125: =H125-F125 -> 1 | H125: 37 | I125: =ROUND(G125*$I$3,2) -> 3.73 | J125: =K125-H125 -> 0 | K125: 37 | L125: =ROUND(J125*$L$3,2) -> 0 | M125: =N125-K125 -> 0 | N125: 37 | O125: =ROUND(M125*$O$3,2) -> 0 | P125: =Q125-N125 -> 1 | Q125: 38 | R125: =ROUND(P125*$R$3,2) -> 2.87 | S125: =+T125-Q125 -> 0 | T125: 38 | U125: =ROUND(S125*$U$3,2) -> 0 | V125: =+W125-T125 -> 0 | W125: 38 | X125: =V125*$X$3 -> 0
A126: DEPA-1107 | B126: 288 | C126: =D126-B126 -> 5 | D126: 293 | E126: =F126-D126 -> 9 | F126: 302 | G126: =H126-F126 -> 8 | H126: 310 | I126: =ROUND(G126*$I$3,2) -> 29.87 | J126: =K126-H126 -> 8 | K126: 318 | L126: =ROUND(J126*$L$3,2) -> 33.24 | M126: =N126-K126 -> 3 | N126: 321 | O126: =ROUND(M126*$O$3,2) -> 19.16 | P126: =Q126-N126 -> 5 | Q126: 326 | R126: =ROUND(P126*$R$3,2) -> 14.35 | S126: =+T126-Q126 -> 9 | T126: 335 | U126: =ROUND(S126*$U$3,2) -> 26.82 | V126: =+W126-T126 -> 8 | W126: 343 | X126: =V126*$X$3 -> 23.8016
A127: DEPA-1108 | B127: 137 | C127: =D127-B127 -> 2 | D127: 139 | E127: =F127-D127 -> 3 | F127: 142 | G127: =H127-F127 -> 5 | H127: 147 | I127: =ROUND(G127*$I$3,2) -> 18.67 | J127: =K127-H127 -> 2 | K127: 149 | L127: =ROUND(J127*$L$3,2) -> 8.31 | M127: =N127-K127 -> 2 | N127: 151 | O127: =ROUND(M127*$O$3,2) -> 12.77 | P127: =Q127-N127 -> 3 | Q127: 154 | R127: =ROUND(P127*$R$3,2) -> 8.61 | S127: =+T127-Q127 -> 3 | T127: 157 | U127: =ROUND(S127*$U$3,2) -> 8.94 | V127: =+W127-T127 -> 3 | W127: 160 | X127: =V127*$X$3 -> 8.9256
A128: DEPA-1109 | B128: 199 | C128: =D128-B128 -> 4 | D128: 203 | E128: =F128-D128 -> 3 | F128: 206 | G128: =H128-F128 -> 5 | H128: 211 | I128: =ROUND(G128*$I$3,2) -> 18.67 | J128: =K128-H128 -> 4 | K128: 215 | L128: =ROUND(J128*$L$3,2) -> 16.62 | M128: =N128-K128 -> 3 | N128: 218 | O128: =ROUND(M128*$O$3,2) -> 19.16 | P128: =Q128-N128 -> 3 | Q128: 221 | R128: =ROUND(P128*$R$3,2) -> 8.61 | S128: =+T128-Q128 -> 4 | T128: 225 | U128: =ROUND(S128*$U$3,2) -> 11.92 | V128: =+W128-T128 -> 2 | W128: 227 | X128: =V128*$X$3 -> 5.9504
A129: DEPA-1110 | B129: 278.12 | C129: =D129-B129 -> 5.13 | D129: 283.25 | E129: =F129-D129 -> 6.05 | F129: 289.3 | G129: =H129-F129 -> 7.15 | H129: 296.45 | I129: =ROUND(G129*$I$3,2) -> 26.7 | J129: =K129-H129 -> 5.854 | K129: 302.304 | L129: =ROUND(J129*$L$3,2) -> 24.32 | M129: =N129-K129 -> 4.304 | N129: 306.608 | O129: =ROUND(M129*$O$3,2) -> 27.48 | P129: =Q129-N129 -> 4.392 | Q129: 311 | R129: =ROUND(P129*$R$3,2) -> 12.61 | S129: =+T129-Q129 -> 7.308 | T129: 318.308 | U129: =ROUND(S129*$U$3,2) -> 21.78 | V129: =+W129-T129 -> 4.692 | W129: 323 | X129: =V129*$X$3 -> 13.959638
A130: DEPA-1111 | B130: 141.87 | C130: =D130-B130 -> 7 | D130: 148.87 | E130: =F130-D130 -> 6.35 | F130: 155.22 | G130: =H130-F130 -> 6.582 | H130: 161.802 | I130: =ROUND(G130*$I$3,2) -> 24.58 | J130: =K130-H130 -> 6.058 | K130: 167.86 | L130: =ROUND(J130*$L$3,2) -> 25.17 | M130: =N130-K130 -> 4.032 | N130: 171.892 | O130: =ROUND(M130*$O$3,2) -> 25.75 | P130: =Q130-N130 -> 5.108 | Q130: 177 | R130: =ROUND(P130*$R$3,2) -> 14.66 | S130: =+T130-Q130 -> 6.588 | T130: 183.588 | U130: =ROUND(S130*$U$3,2) -> 19.63 | V130: =+W130-T130 -> 6.412 | W130: 190 | X130: =V130*$X$3 -> 19.076982
A131: DEPA-1112 | B131: 239 | C131: =D131-B131 -> 18 | D131: 257 | E131: =F131-D131 -> 7 | F131: 264 | G131: =H131-F131 -> 13 | H131: 277 | I131: =ROUND(G131*$I$3,2) -> 48.54 | J131: =K131-H131 -> 9 | K131: 286 | L131: =ROUND(J131*$L$3,2) -> 37.39 | M131: =N131-K131 -> 7 | N131: 293 | O131: =ROUND(M131*$O$3,2) -> 44.7 | P131: =Q131-N131 -> 8 | Q131: 301 | R131: =ROUND(P131*$R$3,2) -> 22.96 | S131: =+T131-Q131 -> 10 | T131: 311 | U131: =ROUND(S131*$U$3,2) -> 29.8 | V131: =+W131-T131 -> 8 | W131: 319 | X131: =V131*$X$3 -> 23.8016
A132: DEPA-1201 | B132: 617 | C132: =D132-B132 -> 12 | D132: 629 | E132: =F132-D132 -> 20 | F132: 649 | G132: =H132-F132 -> 22 | H132: =496+175 -> 671 | I132: =ROUND(G132*$I$3,2) -> 82.15 | J132: =K132-H132 -> 20 | K132: =511+180 -> 691 | L132: =ROUND(J132*$L$3,2) -> 83.09 | M132: =N132-K132 -> 15 | N132: =522+184 -> 706 | O132: =ROUND(M132*$O$3,2) -> 95.78 | P132: =Q132-N132 -> 17 | Q132: =535+188 -> 723 | R132: =ROUND(P132*$R$3,2) -> 48.8 | S132: =+T132-Q132 -> 22 | T132: =552+193 -> 745 | U132: =ROUND(S132*$U$3,2) -> 65.56 | V132: =+W132-T132 -> 21 | W132: =567+199 -> 766 | X132: =V132*$X$3 -> 62.4792
A133: DEPA-1204 | B133: 113 | C133: =D133-B133 -> 7 | D133: 120 | E133: =F133-D133 -> 6 | F133: 126 | G133: =H133-F133 -> 7 | H133: 133 | I133: =ROUND(G133*$I$3,2) -> 26.14 | J133: =K133-H133 -> 6 | K133: 139 | L133: =ROUND(J133*$L$3,2) -> 24.93 | M133: =N133-K133 -> 5 | N133: 144 | O133: =ROUND(M133*$O$3,2) -> 31.93 | P133: =Q133-N133 -> 6 | Q133: 150 | R133: =ROUND(P133*$R$3,2) -> 17.22 | S133: =+T133-Q133 -> 9 | T133: 159 | U133: =ROUND(S133*$U$3,2) -> 26.82 | V133: =+W133-T133 -> 8 | W133: 167 | X133: =V133*$X$3 -> 23.8016 | Y133: Falta depa 1203
A134: DEPA-1205 | B134: 438 | C134: =D134-B134 -> 8 | D134: 446 | E134: =F134-D134 -> 9 | F134: 455 | G134: 9 | H134: 91 | I134: =ROUND(G134*$I$3,2) -> 33.61 | J134: =K134-H134 -> 13 | K134: 104 | L134: =ROUND(J134*$L$3,2) -> 54.01 | M134: =N134-K134 -> 9 | N134: 113 | O134: =ROUND(M134*$O$3,2) -> 57.47 | P134: =Q134-N134 -> 13 | Q134: 126 | R134: =ROUND(P134*$R$3,2) -> 37.32 | S134: =+T134-Q134 -> 15 | T134: 141 | U134: =ROUND(S134*$U$3,2) -> 44.7 | V134: =+W134-T134 -> 17 | W134: 158 | X134: =V134*$X$3 -> 50.5784 | Z134: *medidor nuevo val. 25/08/2025
A135: DEPA-1206 | B135: 83 | C135: =D135-B135 -> 0 | D135: 83 | E135: =F135-D135 -> 1 | F135: 84 | G135: =H135-F135 -> 0 | H135: 84 | I135: =ROUND(G135*$I$3,2) -> 0 | J135: =K135-H135 -> 0 | K135: 84 | L135: =ROUND(J135*$L$3,2) -> 0 | M135: =N135-K135 -> 1 | N135: 85 | O135: =ROUND(M135*$O$3,2) -> 6.39 | P135: =Q135-N135 -> 0 | Q135: 85 | R135: =ROUND(P135*$R$3,2) -> 0 | S135: =+T135-Q135 -> 1 | T135: 86 | U135: =ROUND(S135*$U$3,2) -> 2.98 | V135: =+W135-T135 -> 2 | W135: 88 | X135: =V135*$X$3 -> 5.9504
A136: DEPA-1207 | B136: 152 | C136: =D136-B136 -> 6 | D136: 158 | E136: =F136-D136 -> 7 | F136: 165 | G136: =H136-F136 -> 8 | H136: 173 | I136: =ROUND(G136*$I$3,2) -> 29.87 | J136: =K136-H136 -> 8 | K136: 181 | L136: =ROUND(J136*$L$3,2) -> 33.24 | M136: =N136-K136 -> 4 | N136: 185 | O136: =ROUND(M136*$O$3,2) -> 25.54 | P136: =Q136-N136 -> 5 | Q136: 190 | R136: =ROUND(P136*$R$3,2) -> 14.35 | S136: =+T136-Q136 -> 3 | T136: 193 | U136: =ROUND(S136*$U$3,2) -> 8.94 | V136: =+W136-T136 -> 3 | W136: 196 | X136: =V136*$X$3 -> 8.9256
A137: DEPA-1208 | B137: 114 | C137: =D137-B137 -> 0 | D137: 114 | E137: =F137-D137 -> 2 | F137: 116 | G137: =H137-F137 -> 1 | H137: 117 | I137: =ROUND(G137*$I$3,2) -> 3.73 | J137: =K137-H137 -> 1 | K137: 118 | L137: =ROUND(J137*$L$3,2) -> 4.15 | M137: =N137-K137 -> 1 | N137: 119 | O137: =ROUND(M137*$O$3,2) -> 6.39 | P137: =Q137-N137 -> 2 | Q137: 121 | R137: =ROUND(P137*$R$3,2) -> 5.74 | S137: =+T137-Q137 -> 1 | T137: 122 | U137: =ROUND(S137*$U$3,2) -> 2.98 | V137: =+W137-T137 -> 2 | W137: 124 | X137: =V137*$X$3 -> 5.9504
A138: DEPA-1209 | B138: 108 | C138: =D138-B138 -> 5 | D138: 113 | E138: =F138-D138 -> 10 | F138: 123 | G138: =H138-F138 -> 3 | H138: 126 | I138: =ROUND(G138*$I$3,2) -> 11.2 | J138: =K138-H138 -> 2 | K138: 128 | L138: =ROUND(J138*$L$3,2) -> 8.31 | M138: =N138-K138 -> 3 | N138: 131 | O138: =ROUND(M138*$O$3,2) -> 19.16 | P138: =Q138-N138 -> 4 | Q138: 135 | R138: =ROUND(P138*$R$3,2) -> 11.48 | S138: =+T138-Q138 -> 3 | T138: 138 | U138: =ROUND(S138*$U$3,2) -> 8.94 | V138: =+W138-T138 -> 4 | W138: 142 | X138: =V138*$X$3 -> 11.9008
A139: DEPA-1210 | B139: 283.29 | C139: =D139-B139 -> 6.71 | D139: 290 | E139: =F139-D139 -> 5.73 | F139: 295.73 | G139: =H139-F139 -> 8.715 | H139: 304.445 | I139: =ROUND(G139*$I$3,2) -> 32.54 | J139: =K139-H139 -> 9.455 | K139: 313.9 | L139: =ROUND(J139*$L$3,2) -> 39.28 | M139: =N139-K139 -> 5.419 | N139: 319.319 | O139: =ROUND(M139*$O$3,2) -> 34.6 | P139: =Q139-N139 -> 6.681 | Q139: 326 | R139: =ROUND(P139*$R$3,2) -> 19.18 | S139: =+T139-Q139 -> 9.117 | T139: 335.117 | U139: =ROUND(S139*$U$3,2) -> 27.17 | V139: =+W139-T139 -> 8.883 | W139: 344 | X139: =V139*$X$3 -> 26.428702
A140: DEPA-1211 | B140: 166.09 | C140: =D140-B140 -> 1.47 | D140: 167.56 | E140: =F140-D140 -> 1.87 | F140: 169.43 | G140: =H140-F140 -> 1.649 | H140: 171.079 | I140: =ROUND(G140*$I$3,2) -> 6.16 | J140: =K140-H140 -> 2.391 | K140: 173.47 | L140: =ROUND(J140*$L$3,2) -> 9.93 | M140: =N140-K140 -> 1.834 | N140: 175.304 | O140: =ROUND(M140*$O$3,2) -> 11.71 | P140: =Q140-N140 -> 1.696 | Q140: 177 | R140: =ROUND(P140*$R$3,2) -> 4.87 | S140: =+T140-Q140 -> 3.879 | T140: 180.879 | U140: =ROUND(S140*$U$3,2) -> 11.56 | V140: =+W140-T140 -> 2.121 | W140: 183 | X140: =V140*$X$3 -> 6.3103992
A141: DEPA-1212 | B141: 152 | C141: =D141-B141 -> 0 | D141: 152 | E141: =F141-D141 -> 0 | F141: 152 | G141: =H141-F141 -> 2 | H141: 154 | I141: =ROUND(G141*$I$3,2) -> 7.47 | J141: =K141-H141 -> 7 | K141: 161 | L141: =ROUND(J141*$L$3,2) -> 29.08 | M141: =N141-K141 -> 9 | N141: 170 | O141: =ROUND(M141*$O$3,2) -> 57.47 | P141: =Q141-N141 -> 11 | Q141: 181 | R141: =ROUND(P141*$R$3,2) -> 31.57 | S141: =+T141-Q141 -> 15 | T141: 196 | U141: =ROUND(S141*$U$3,2) -> 44.7 | V141: =+W141-T141 -> 16 | W141: 212 | X141: =V141*$X$3 -> 47.6032
A142: DEPA-1301 | B142: 96 | C142: =D142-B142 -> 1 | D142: 97 | E142: =F142-D142 -> 2 | F142: 99 | G142: =H142-F142 -> 2 | H142: 101 | I142: =ROUND(G142*$I$3,2) -> 7.47 | J142: =K142-H142 -> 2 | K142: 103 | L142: =ROUND(J142*$L$3,2) -> 8.31 | M142: =N142-K142 -> 1 | N142: 104 | O142: =ROUND(M142*$O$3,2) -> 6.39 | P142: =Q142-N142 -> 3 | Q142: 107 | R142: =ROUND(P142*$R$3,2) -> 8.61 | S142: =+T142-Q142 -> 2 | T142: 109 | U142: =ROUND(S142*$U$3,2) -> 5.96 | V142: =+W142-T142 -> 3 | W142: 112 | X142: =V142*$X$3 -> 8.9256
A143: DEPA-1302 | B143: 145 | C143: =D143-B143 -> 7 | D143: 152 | E143: =F143-D143 -> 6 | F143: 158 | G143: =H143-F143 -> 7 | H143: 165 | I143: =ROUND(G143*$I$3,2) -> 26.14 | J143: =K143-H143 -> 10 | K143: 175 | L143: =ROUND(J143*$L$3,2) -> 41.55 | M143: =N143-K143 -> 2 | N143: 177 | O143: =ROUND(M143*$O$3,2) -> 12.77 | P143: =Q143-N143 -> 6 | Q143: 183 | R143: =ROUND(P143*$R$3,2) -> 17.22 | S143: =+T143-Q143 -> 8 | T143: 191 | U143: =ROUND(S143*$U$3,2) -> 23.84 | V143: =+W143-T143 -> 8 | W143: 199 | X143: =V143*$X$3 -> 23.8016
A144: DEPA-1303 | B144: 178 | C144: =D144-B144 -> 4 | D144: 182 | E144: =F144-D144 -> 4 | F144: 186 | G144: =H144-F144 -> 4 | H144: 190 | I144: =ROUND(G144*$I$3,2) -> 14.94 | J144: =K144-H144 -> 2 | K144: 192 | L144: =ROUND(J144*$L$3,2) -> 8.31 | M144: =N144-K144 -> 0 | N144: 192 | O144: =ROUND(M144*$O$3,2) -> 0 | P144: =Q144-N144 -> 2 | Q144: 194 | R144: =ROUND(P144*$R$3,2) -> 5.74 | S144: =+T144-Q144 -> 1 | T144: 195 | U144: =ROUND(S144*$U$3,2) -> 2.98 | V144: =+W144-T144 -> 1 | W144: 196 | X144: =V144*$X$3 -> 2.9752
A145: DEPA-1304 | B145: 284 | C145: =D145-B145 -> 2 | D145: 286 | E145: =F145-D145 -> 3 | F145: 289 | G145: =H145-F145 -> 0 | H145: 289 | I145: =ROUND(G145*$I$3,2) -> 0 | J145: =K145-H145 -> 1 | K145: 290 | L145: =ROUND(J145*$L$3,2) -> 4.15 | M145: =N145-K145 -> 2 | N145: 292 | O145: =ROUND(M145*$O$3,2) -> 12.77 | P145: =Q145-N145 -> 5 | Q145: 297 | R145: =ROUND(P145*$R$3,2) -> 14.35 | S145: =+T145-Q145 -> 10 | T145: 307 | U145: =ROUND(S145*$U$3,2) -> 29.8 | V145: =+W145-T145 -> 5 | W145: 312 | X145: =V145*$X$3 -> 14.876
A146: DEPA-1305 | B146: 329.91 | C146: =D146-B146 -> 14.85 | D146: 344.76 | E146: =F146-D146 -> 12.56 | F146: 357.32 | G146: =H146-F146 -> 13.693 | H146: 371.013 | I146: =ROUND(G146*$I$3,2) -> 51.13 | J146: =K146-H146 -> 11.689 | K146: 382.702 | L146: =ROUND(J146*$L$3,2) -> 48.56 | M146: =N146-K146 -> 8.202 | N146: 390.904 | O146: =ROUND(M146*$O$3,2) -> 52.37 | P146: =Q146-N146 -> 9.096 | Q146: 400 | R146: =ROUND(P146*$R$3,2) -> 26.11 | S146: =+T146-Q146 -> 14.66 | T146: 414.66 | U146: =ROUND(S146*$U$3,2) -> 43.68 | V146: =+W146-T146 -> 14.34 | W146: 429 | X146: =V146*$X$3 -> 42.664368
... A158: DEPA-1405 | B158: 129.72 | C158: =D158-B158 -> 4.44 | D158: 134.16 | E158: =F158-D158 -> 5.04 | F158: 139.2 | G158: =H158-F158 -> -0.2 | H158: 139 | I158: =ROUND(G158*$I$3,2) -> -0.75 | J158: =K158-H158 -> 1.419 | K158: 140.419 | L158: =ROUND(J158*$L$3,2) -> 5.9 | M158: =N158-K158 -> 1.451 | N158: 141.87 | O158: =ROUND(M158*$O$3,2) -> 9.27 | P158: =Q158-N158 -> 1.13 | Q158: 143 | R158: =ROUND(P158*$R$3,2) -> 3.24 | S158: =+T158-Q158 -> 1.553 | T158: 144.553 | U158: =ROUND(S158*$U$3,2) -> 4.63 | V158: =+W158-T158 -> 1.447 | W158: 146 | X158: =V158*$X$3 -> 4.3051144
A159: DEPA-1406 | B159: 155 | C159: =D159-B159 -> 1 | D159: 156 | E159: =F159-D159 -> 2 | F159: 158 | G159: 2 | H159: 16 | I159: =ROUND(G159*$I$3,2) -> 7.47 | J159: =K159-H159 -> 2 | K159: 18 | L159: =ROUND(J159*$L$3,2) -> 8.31 | M159: =N159-K159 -> 0 | N159: 18 | O159: =ROUND(M159*$O$3,2) -> 0 | P159: =Q159-N159 -> 4 | Q159: 22 | R159: =ROUND(P159*$R$3,2) -> 11.48 | S159: =+T159-Q159 -> 0 | T159: 22 | U159: =ROUND(S159*$U$3,2) -> 0 | V159: =+W159-T159 -> 0 | W159: 22 | X159: =V159*$X$3 -> 0 | Z159: *medidor nuevo val. 25/08/2025
A160: DEPA-1407 | B160: 210 | C160: =D160-B160 -> 5 | D160: 215 | E160: =F160-D160 -> 4 | F160: 219 | G160: =H160-F160 -> 5 | H160: 224 | I160: =ROUND(G160*$I$3,2) -> 18.67 | J160: =K160-H160 -> 5 | K160: 229 | L160: =ROUND(J160*$L$3,2) -> 20.77 | M160: =N160-K160 -> 3 | N160: 232 | O160: =ROUND(M160*$O$3,2) -> 19.16 | P160: =Q160-N160 -> 3 | Q160: 235 | R160: =ROUND(P160*$R$3,2) -> 8.61 | S160: =+T160-Q160 -> 3 | T160: 238 | U160: =ROUND(S160*$U$3,2) -> 8.94 | V160: =+W160-T160 -> 5 | W160: 243 | X160: =V160*$X$3 -> 14.876
A161: DEPA-1408 | B161: 98.6 | C161: =D161-B161 -> 1.2 | D161: 99.8 | E161: =F161-D161 -> 1.2 | F161: 101 | G161: 1 | H161: 27 | I161: =ROUND(G161*$I$3,2) -> 3.73 | J161: =K161-H161 -> 3 | K161: 30 | L161: =ROUND(J161*$L$3,2) -> 12.46 | M161: =N161-K161 -> 3 | N161: 33 | O161: =ROUND(M161*$O$3,2) -> 19.16 | P161: =Q161-N161 -> 4 | Q161: 37 | R161: =ROUND(P161*$R$3,2) -> 11.48 | S161: =+T161-Q161 -> 4 | T161: 41 | U161: =ROUND(S161*$U$3,2) -> 11.92 | V161: =+W161-T161 -> 4 | W161: 45 | X161: =V161*$X$3 -> 11.9008 | Z161: *medidor nuevo val. 25/08/2025
A162: DEPA-1409 | B162: 168 | C162: =D162-B162 -> 5 | D162: 173 | E162: =F162-D162 -> 3 | F162: 176 | G162: =H162-F162 -> 6 | H162: 182 | I162: =ROUND(G162*$I$3,2) -> 22.41 | J162: =K162-H162 -> 5 | K162: 187 | L162: =ROUND(J162*$L$3,2) -> 20.77 | M162: =N162-K162 -> 2 | N162: 189 | O162: =ROUND(M162*$O$3,2) -> 12.77 | P162: =Q162-N162 -> 1 | Q162: 190 | R162: =ROUND(P162*$R$3,2) -> 2.87 | S162: =+T162-Q162 -> 1 | T162: 191 | U162: =ROUND(S162*$U$3,2) -> 2.98 | V162: =+W162-T162 -> 3 | W162: 194 | X162: =V162*$X$3 -> 8.9256
A163: DEPA-1410 | B163: 477.26 | C163: =D163-B163 -> 11.14 | D163: 488.4 | E163: =F163-D163 -> 11.6 | F163: 500 | G163: =H163-F163 -> 12.123 | H163: 512.123 | I163: =ROUND(G163*$I$3,2) -> 45.27 | J163: =K163-H163 -> 10.271 | K163: 522.394 | L163: =ROUND(J163*$L$3,2) -> 42.67 | M163: =N163-K163 -> 8.541 | N163: 530.935 | O163: =ROUND(M163*$O$3,2) -> 54.54 | P163: =Q163-N163 -> 8.065 | Q163: 539 | R163: =ROUND(P163*$R$3,2) -> 23.15 | S163: =+T163-Q163 -> 11.424 | T163: 550.424 | U163: =ROUND(S163*$U$3,2) -> 34.04 | V163: =+W163-T163 -> 12.576 | W163: 563 | X163: =V163*$X$3 -> 37.416115
A164: DEPA-1411 | B164: 139.2 | C164: =D164-B164 -> 2.6 | D164: 141.8 | E164: =F164-D164 -> 1.21 | F164: 143.01 | G164: 2 | H164: 134.388 | I164: =ROUND(G164*$I$3,2) -> 7.47 | J164: =K164-H164 -> 0.465 | K164: 134.853 | L164: =ROUND(J164*$L$3,2) -> 1.93 | M164: =N164-K164 -> 1.071 | N164: 135.924 | O164: =ROUND(M164*$O$3,2) -> 6.84 | P164: =Q164-N164 -> 0.076 | Q164: 136 | R164: =ROUND(P164*$R$3,2) -> 0.22 | S164: =+T164-Q164 -> 2.232 | T164: 138.232 | U164: =ROUND(S164*$U$3,2) -> 6.65 | V164: =+W164-T164 -> 1.768 | W164: 140 | X164: =V164*$X$3 -> 5.2601536
A165: DEPA-1412 | B165: 519 | C165: =D165-B165 -> 10 | D165: 529 | E165: =F165-D165 -> 13 | F165: 542 | G165: =H165-F165 -> 14 | H165: 556 | I165: =ROUND(G165*$I$3,2) -> 52.28 | J165: =K165-H165 -> 11 | K165: 567 | L165: =ROUND(J165*$L$3,2) -> 45.7 | M165: =N165-K165 -> 9 | N165: 576 | O165: =ROUND(M165*$O$3,2) -> 57.47 | P165: =Q165-N165 -> 11 | Q165: 587 | R165: =ROUND(P165*$R$3,2) -> 31.57 | S165: =+T165-Q165 -> 10 | T165: 597 | U165: =ROUND(S165*$U$3,2) -> 29.8 | V165: =+W165-T165 -> 2 | W165: 599 | X165: =V165*$X$3 -> 5.9504
A166: DEPA-1501 | B166: 65 | C166: =D166-B166 -> 2 | D166: 67 | E166: =F166-D166 -> 1 | F166: 68 | G166: =H166-F166 -> 1 | H166: 69 | I166: =ROUND(G166*$I$3,2) -> 3.73 | J166: =K166-H166 -> 0 | K166: 69 | L166: =ROUND(J166*$L$3,2) -> 0 | M166: =N166-K166 -> 0 | N166: 69 | O166: =ROUND(M166*$O$3,2) -> 0 | P166: =Q166-N166 -> 1 | Q166: 70 | R166: =ROUND(P166*$R$3,2) -> 2.87 | S166: =+T166-Q166 -> 2 | T166: 72 | U166: =ROUND(S166*$U$3,2) -> 5.96 | V166: =+W166-T166 -> 10 | W166: 82 | X166: =V166*$X$3 -> 29.752
A167: DEPA-1502 | B167: 225 | C167: =D167-B167 -> 14 | D167: 239 | E167: =F167-D167 -> 11 | F167: 250 | G167: =H167-F167 -> 6 | H167: 256 | I167: =ROUND(G167*$I$3,2) -> 22.41 | J167: =K167-H167 -> 4 | K167: 260 | L167: =ROUND(J167*$L$3,2) -> 16.62 | M167: =N167-K167 -> 15 | N167: 275 | O167: =ROUND(M167*$O$3,2) -> 95.78 | P167: =Q167-N167 -> 8 | Q167: 283 | R167: =ROUND(P167*$R$3,2) -> 22.96 | S167: =+T167-Q167 -> 8 | T167: 291 | U167: =ROUND(S167*$U$3,2) -> 23.84 | V167: =+W167-T167 -> 7 | W167: 298 | X167: =V167*$X$3 -> 20.8264
A168: DEPA-1503 | B168: 338 | C168: =D168-B168 -> 9 | D168: 347 | E168: =F168-D168 -> 6 | F168: 353 | G168: =H168-F168 -> 9 | H168: 362 | I168: =ROUND(G168*$I$3,2) -> 33.61 | J168: =K168-H168 -> 7 | K168: 369 | L168: =ROUND(J168*$L$3,2) -> 29.08 | M168: =N168-K168 -> 5 | N168: 374 | O168: =ROUND(M168*$O$3,2) -> 31.93 | P168: =Q168-N168 -> 6 | Q168: 380 | R168: =ROUND(P168*$R$3,2) -> 17.22 | S168: =+T168-Q168 -> 6 | T168: 386 | U168: =ROUND(S168*$U$3,2) -> 17.88 | V168: =+W168-T168 -> 9 | W168: 395 | X168: =V168*$X$3 -> 26.7768
A169: DEPA-1504 | B169: 231 | C169: =D169-B169 -> 3 | D169: 234 | E169: =F169-D169 -> 4 | F169: 238 | G169: =H169-F169 -> 2 | H169: 240 | I169: =ROUND(G169*$I$3,2) -> 7.47 | J169: =K169-H169 -> 2 | K169: 242 | L169: =ROUND(J169*$L$3,2) -> 8.31 | M169: =N169-K169 -> 2 | N169: 244 | O169: =ROUND(M169*$O$3,2) -> 12.77 | P169: =Q169-N169 -> 3 | Q169: 247 | R169: =ROUND(P169*$R$3,2) -> 8.61 | S169: =+T169-Q169 -> 0 | T169: 247 | U169: =ROUND(S169*$U$3,2) -> 0 | V169: =+W169-T169 -> 3 | W169: 250 | X169: =V169*$X$3 -> 8.9256
A170: DEPA-1505 | B170: 321.39 | C170: =D170-B170 -> 12.38 | D170: 333.77 | E170: =F170-D170 -> 9.65 | F170: 343.42 | G170: =H170-F170 -> 7.543 | H170: 350.963 | I170: =ROUND(G170*$I$3,2) -> 28.17 | J170: =K170-H170 -> 6.037 | K170: 357 | L170: =ROUND(J170*$L$3,2) -> 25.08 | M170: =N170-K170 -> 1.599 | N170: 358.599 | O170: =ROUND(M170*$O$3,2) -> 10.21 | P170: =Q170-N170 -> 0.401 | Q170: 359 | R170: =ROUND(P170*$R$3,2) -> 1.15 | S170: =+T170-Q170 -> 0.821 | T170: 359.821 | U170: =ROUND(S170*$U$3,2) -> 2.45 | V170: =+W170-T170 -> 0.179 | W170: 360 | X170: =V170*$X$3 -> 0.5325608
A171: DEPA-1506 | B171: 227 | C171: =D171-B171 -> 3 | D171: 230 | E171: =F171-D171 -> 4 | F171: 234 | G171: =H171-F171 -> 5 | H171: 239 | I171: =ROUND(G171*$I$3,2) -> 18.67 | J171: =K171-H171 -> 3 | K171: 242 | L171: =ROUND(J171*$L$3,2) -> 12.46 | M171: =N171-K171 -> 2 | N171: 244 | O171: =ROUND(M171*$O$3,2) -> 12.77 | P171: =Q171-N171 -> 2 | Q171: 246 | R171: =ROUND(P171*$R$3,2) -> 5.74 | S171: =+T171-Q171 -> 2 | T171: 248 | U171: =ROUND(S171*$U$3,2) -> 5.96 | V171: =+W171-T171 -> 4 | W171: 252 | X171: =V171*$X$3 -> 11.9008
A172: DEPA-1507 | B172: 368 | C172: =D172-B172 -> 12 | D172: 380 | E172: =F172-D172 -> 13 | F172: 393 | G172: =H172-F172 -> 14 | H172: 407 | I172: =ROUND(G172*$I$3,2) -> 52.28 | J172: =K172-H172 -> 13 | K172: 420 | L172: =ROUND(J172*$L$3,2) -> 54.01 | M172: =N172-K172 -> 7 | N172: 427 | O172: =ROUND(M172*$O$3,2) -> 44.7 | P172: =Q172-N172 -> 11 | Q172: 438 | R172: =ROUND(P172*$R$3,2) -> 31.57 | S172: =+T172-Q172 -> 12 | T172: 450 | U172: =ROUND(S172*$U$3,2) -> 35.76 | V172: =+W172-T172 -> 14 | W172: 464 | X172: =V172*$X$3 -> 41.6528
A173: DEPA-1508 | B173: 168 | C173: =D173-B173 -> 4 | D173: 172 | E173: =F173-D173 -> 3 | F173: 175 | G173: =H173-F173 -> 3 | H173: 178 | I173: =ROUND(G173*$I$3,2) -> 11.2 | J173: =K173-H173 -> 1 | K173: 179 | L173: =ROUND(J173*$L$3,2) -> 4.15 | M173: =N173-K173 -> 2 | N173: 181 | O173: =ROUND(M173*$O$3,2) -> 12.77 | P173: =Q173-N173 -> 4 | Q173: 185 | R173: =ROUND(P173*$R$3,2) -> 11.48 | S173: =+T173-Q173 -> 1 | T173: 186 | U173: =ROUND(S173*$U$3,2) -> 2.98 | V173: =+W173-T173 -> 3 | W173: 189 | X173: =V173*$X$3 -> 8.9256
A174: DEPA-1509 | B174: 125 | C174: =D174-B174 -> 7 | D174: 132 | E174: =F174-D174 -> 5 | F174: 137 | G174: =H174-F174 -> 6 | H174: 143 | I174: =ROUND(G174*$I$3,2) -> 22.41 | J174: =K174-H174 -> 5 | K174: 148 | L174: =ROUND(J174*$L$3,2) -> 20.77 | M174: =N174-K174 -> 3 | N174: 151 | O174: =ROUND(M174*$O$3,2) -> 19.16 | P174: =Q174-N174 -> 5 | Q174: 156 | R174: =ROUND(P174*$R$3,2) -> 14.35 | S174: =+T174-Q174 -> 4 | T174: 160 | U174: =ROUND(S174*$U$3,2) -> 11.92 | V174: =+W174-T174 -> 1 | W174: 161 | X174: =V174*$X$3 -> 2.9752
A175: DEPA-1510 | B175: 214.34 | C175: =D175-B175 -> 6.57 | D175: 220.91 | E175: =F175-D175 -> 6.91 | F175: 227.82 | G175: =H175-F175 -> 5.21 | H175: 233.03 | I175: =ROUND(G175*$I$3,2) -> 19.46 | J175: =K175-H175 -> 7.364 | K175: 240.394 | L175: =ROUND(J175*$L$3,2) -> 30.6 | M175: =N175-K175 -> 5.971 | N175: 246.365 | O175: =ROUND(M175*$O$3,2) -> 38.13 | P175: =Q175-N175 -> 5.635 | Q175: 252 | R175: =ROUND(P175*$R$3,2) -> 16.17 | S175: =+T175-Q175 -> 8.473 | T175: 260.473 | U175: =ROUND(S175*$U$3,2) -> 25.25 | V175: =+W175-T175 -> 16.527 | W175: 277 | X175: =V175*$X$3 -> 49.17113
A176: DEPA-1511 | B176: 95.56 | C176: =D176-B176 -> 2.18 | D176: 97.74 | E176: =F176-D176 -> 2.58 | F176: 100.32 | G176: =H176-F176 -> 2.879 | H176: 103.199 | I176: =ROUND(G176*$I$3,2) -> 10.75 | J176: =K176-H176 -> 2.076 | K176: 105.275 | L176: =ROUND(J176*$L$3,2) -> 8.63 | M176: =N176-K176 -> 1.185 | N176: 106.46 | O176: =ROUND(M176*$O$3,2) -> 7.57 | P176: =Q176-N176 -> 1.54 | Q176: 108 | R176: =ROUND(P176*$R$3,2) -> 4.42 | S176: =+T176-Q176 -> 1.922 | T176: 109.922 | U176: =ROUND(S176*$U$3,2) -> 5.73 | V176: =+W176-T176 -> 1.078 | W176: 111 | X176: =V176*$X$3 -> 3.2072656
... A185: DEPA-1608 | B185: 122 | C185: =D185-B185 -> 1 | D185: 123 | E185: =F185-D185 -> 1 | F185: 124 | G185: =H185-F185 -> 1 | H185: 125 | I185: =ROUND(G185*$I$3,2) -> 3.73 | J185: =K185-H185 -> 2 | K185: 127 | L185: =ROUND(J185*$L$3,2) -> 8.31 | M185: =N185-K185 -> 0 | N185: 127 | O185: =ROUND(M185*$O$3,2) -> 0 | P185: =Q185-N185 -> 2 | Q185: 129 | R185: =ROUND(P185*$R$3,2) -> 5.74 | S185: =+T185-Q185 -> 1 | T185: 130 | U185: =ROUND(S185*$U$3,2) -> 2.98 | V185: =+W185-T185 -> 1 | W185: 131 | X185: =V185*$X$3 -> 2.9752
A186: DEPA-1609 | B186: 320 | C186: =D186-B186 -> 10 | D186: 330 | E186: =F186-D186 -> 11 | F186: 341 | G186: 11 | H186: 138 | I186: =ROUND(G186*$I$3,2) -> 41.08 | J186: =K186-H186 -> 11 | K186: 149 | L186: =ROUND(J186*$L$3,2) -> 45.7 | M186: =N186-K186 -> 9 | N186: 158 | O186: =ROUND(M186*$O$3,2) -> 57.47 | P186: =Q186-N186 -> 11 | Q186: 169 | R186: =ROUND(P186*$R$3,2) -> 31.57 | S186: =+T186-Q186 -> 13 | T186: 182 | U186: =ROUND(S186*$U$3,2) -> 38.74 | V186: =+W186-T186 -> 13 | W186: 195 | X186: =V186*$X$3 -> 38.6776 | Z186: *medidor nuevo val. 25/08/2025
A187: DEPA-1610 | B187: 247.37 | C187: =D187-B187 -> 5.29 | D187: 252.66 | E187: =F187-D187 -> 8.74 | F187: 261.4 | G187: =H187-F187 -> 5.683 | H187: 267.083 | I187: =ROUND(G187*$I$3,2) -> 21.22 | J187: =K187-H187 -> 8.815 | K187: 275.898 | L187: =ROUND(J187*$L$3,2) -> 36.62 | M187: =N187-K187 -> 5.525 | N187: 281.423 | O187: =ROUND(M187*$O$3,2) -> 35.28 | P187: =Q187-N187 -> 4.577 | Q187: 286 | R187: =ROUND(P187*$R$3,2) -> 13.14 | S187: =+T187-Q187 -> 8.217 | T187: 294.217 | U187: =ROUND(S187*$U$3,2) -> 24.49 | V187: =+W187-T187 -> 6.783 | W187: 301 | X187: =V187*$X$3 -> 20.180782
A188: DEPA-1611 | B188: 125.9 | C188: =D188-B188 -> 0.63 | D188: 126.53 | E188: =F188-D188 -> 0.34 | F188: 126.87 | G188: =H188-F188 -> 0.089 | H188: 126.959 | I188: =ROUND(G188*$I$3,2) -> 0.33 | J188: =K188-H188 -> 2.716 | K188: 129.675 | L188: =ROUND(J188*$L$3,2) -> 11.28 | M188: =N188-K188 -> 1.653 | N188: 131.328 | O188: =ROUND(M188*$O$3,2) -> 10.56 | P188: =Q188-N188 -> 1.672 | Q188: 133 | R188: =ROUND(P188*$R$3,2) -> 4.8 | S188: =+T188-Q188 -> 2.741 | T188: 135.741 | U188: =ROUND(S188*$U$3,2) -> 8.17 | V188: =+W188-T188 -> 4.259 | W188: 140 | X188: =V188*$X$3 -> 12.671377
A189: DEPA-1612 | B189: 440 | C189: =D189-B189 -> 12 | D189: 452 | E189: =F189-D189 -> 10 | F189: 462 | G189: =H189-F189 -> 12 | H189: 474 | I189: =ROUND(G189*$I$3,2) -> 44.81 | J189: =K189-H189 -> 8 | K189: 482 | L189: =ROUND(J189*$L$3,2) -> 33.24 | M189: =N189-K189 -> 7 | N189: 489 | O189: =ROUND(M189*$O$3,2) -> 44.7 | P189: =Q189-N189 -> 9 | Q189: 498 | R189: =ROUND(P189*$R$3,2) -> 25.83 | S189: =+T189-Q189 -> 7 | T189: 505 | U189: =ROUND(S189*$U$3,2) -> 20.86 | V189: =+W189-T189 -> 9 | W189: 514 | X189: =V189*$X$3 -> 26.7768
A190: DEPA-1701 | B190: 295 | C190: =D190-B190 -> 5 | D190: 300 | E190: =F190-D190 -> 3 | F190: 303 | G190: =H190-F190 -> 5 | H190: 308 | I190: =ROUND(G190*$I$3,2) -> 18.67 | J190: =K190-H190 -> 1 | K190: 309 | L190: =ROUND(J190*$L$3,2) -> 4.15 | M190: =N190-K190 -> 0 | N190: 309 | O190: =ROUND(M190*$O$3,2) -> 0 | P190: =Q190-N190 -> 4 | Q190: 313 | R190: =ROUND(P190*$R$3,2) -> 11.48 | S190: =+T190-Q190 -> 1 | T190: 314 | U190: =ROUND(S190*$U$3,2) -> 2.98 | V190: =+W190-T190 -> 4 | W190: 318 | X190: =V190*$X$3 -> 11.9008
A191: DEPA-1702 | B191: 182 | C191: =D191-B191 -> 0 | D191: 182 | E191: =F191-D191 -> 0 | F191: 182 | G191: =H191-F191 -> 0 | H191: 182 | I191: =ROUND(G191*$I$3,2) -> 0 | J191: =K191-H191 -> 0 | K191: 182 | L191: =ROUND(J191*$L$3,2) -> 0 | M191: =N191-K191 -> 0 | N191: 182 | O191: =ROUND(M191*$O$3,2) -> 0 | P191: =Q191-N191 -> 0 | Q191: 182 | R191: =ROUND(P191*$R$3,2) -> 0 | S191: =+T191-Q191 -> 0 | T191: 182 | U191: =ROUND(S191*$U$3,2) -> 0 | V191: =+W191-T191 -> 0 | W191: 182 | X191: =V191*$X$3 -> 0
A192: DEPA-1703 | B192: 188 | C192: =D192-B192 -> 8 | D192: 196 | E192: =F192-D192 -> 9 | F192: 205 | G192: =H192-F192 -> 11 | H192: 216 | I192: =ROUND(G192*$I$3,2) -> 41.08 | J192: =K192-H192 -> 4 | K192: 220 | L192: =ROUND(J192*$L$3,2) -> 16.62 | M192: =N192-K192 -> 2 | N192: 222 | O192: =ROUND(M192*$O$3,2) -> 12.77 | P192: =Q192-N192 -> 3 | Q192: 225 | R192: =ROUND(P192*$R$3,2) -> 8.61 | S192: =+T192-Q192 -> 2 | T192: 227 | U192: =ROUND(S192*$U$3,2) -> 5.96 | V192: =+W192-T192 -> 5 | W192: 232 | X192: =V192*$X$3 -> 14.876
A193: DEPA-1704 | B193: 268 | C193: =D193-B193 -> 11 | D193: 279 | E193: =F193-D193 -> 9 | F193: 288 | G193: =H193-F193 -> 5 | H193: 293 | I193: =ROUND(G193*$I$3,2) -> 18.67 | J193: =K193-H193 -> 3 | K193: 296 | L193: =ROUND(J193*$L$3,2) -> 12.46 | M193: =N193-K193 -> 3 | N193: 299 | O193: =ROUND(M193*$O$3,2) -> 19.16 | P193: =Q193-N193 -> 5 | Q193: 304 | R193: =ROUND(P193*$R$3,2) -> 14.35 | S193: =+T193-Q193 -> 7 | T193: 311 | U193: =ROUND(S193*$U$3,2) -> 20.86 | V193: =+W193-T193 -> 9 | W193: 320 | X193: =V193*$X$3 -> 26.7768
A194: DEPA-1705 | B194: 192.26 | C194: =D194-B194 -> 5.07 | D194: 197.33 | E194: =F194-D194 -> 5.22 | F194: 202.55 | G194: =H194-F194 -> 6.519 | H194: 209.069 | I194: =ROUND(G194*$I$3,2) -> 24.34 | J194: =K194-H194 -> 10.792 | K194: 219.861 | L194: =ROUND(J194*$L$3,2) -> 44.84 | M194: =N194-K194 -> 7.701 | N194: 227.562 | O194: =ROUND(M194*$O$3,2) -> 49.18 | P194: =Q194-N194 -> 9.438 | Q194: 237 | R194: =ROUND(P194*$R$3,2) -> 27.09 | S194: =+T194-Q194 -> 12.126 | T194: 249.126 | U194: =ROUND(S194*$U$3,2) -> 36.13 | V194: =+W194-T194 -> 10.874 | W194: 260 | X194: =V194*$X$3 -> 32.352325
A195: DEPA-1706 | B195: 141 | C195: =D195-B195 -> 1 | D195: 142 | E195: =F195-D195 -> 2 | F195: 144 | G195: =H195-F195 -> 2 | H195: 146 | I195: =ROUND(G195*$I$3,2) -> 7.47 | J195: =K195-H195 -> 0 | K195: 146 | L195: =ROUND(J195*$L$3,2) -> 0 | M195: =N195-K195 -> 6 | N195: 152 | O195: =ROUND(M195*$O$3,2) -> 38.31 | P195: =Q195-N195 -> 6 | Q195: 158 | R195: =ROUND(P195*$R$3,2) -> 17.22 | S195: =+T195-Q195 -> 4 | T195: 162 | U195: =ROUND(S195*$U$3,2) -> 11.92 | V195: =+W195-T195 -> 4 | W195: 166 | X195: =V195*$X$3 -> 11.9008
A196: DEPA-1707 | B196: 179 | C196: =D196-B196 -> 8 | D196: 187 | E196: =F196-D196 -> 4 | F196: 191 | G196: =H196-F196 -> 7 | H196: 198 | I196: =ROUND(G196*$I$3,2) -> 26.14 | J196: =K196-H196 -> 5 | K196: 203 | L196: =ROUND(J196*$L$3,2) -> 20.77 | M196: =N196-K196 -> 4 | N196: 207 | O196: =ROUND(M196*$O$3,2) -> 25.54 | P196: =Q196-N196 -> 4 | Q196: 211 | R196: =ROUND(P196*$R$3,2) -> 11.48 | S196: =+T196-Q196 -> 5 | T196: 216 | U196: =ROUND(S196*$U$3,2) -> 14.9 | V196: =+W196-T196 -> 2 | W196: 218 | X196: =V196*$X$3 -> 5.9504
A197: DEPA-1708 | B197: 59 | C197: =D197-B197 -> 2 | D197: 61 | E197: =F197-D197 -> 0 | F197: 61 | G197: =H197-F197 -> 21 | H197: 82 | I197: =ROUND(G197*$I$3,2) -> 78.42 | J197: =K197-H197 -> 0 | K197: 82 | L197: =ROUND(J197*$L$3,2) -> 0 | M197: =N197-K197 -> 0 | N197: 82 | O197: =ROUND(M197*$O$3,2) -> 0 | P197: =Q197-N197 -> 0 | Q197: 82 | R197: =ROUND(P197*$R$3,2) -> 0 | S197: =+T197-Q197 -> 0 | T197: 82 | U197: =ROUND(S197*$U$3,2) -> 0 | V197: =+W197-T197 -> 0 | W197: 82 | X197: =V197*$X$3 -> 0
A198: DEPA-1709 | B198: 277 | C198: =D198-B198 -> 3 | D198: 280 | E198: =F198-D198 -> 3 | F198: 283 | G198: =H198-F198 -> 5 | H198: 288 | I198: =ROUND(G198*$I$3,2) -> 18.67 | J198: =K198-H198 -> 3 | K198: 291 | L198: =ROUND(J198*$L$3,2) -> 12.46 | M198: =N198-K198 -> 2 | N198: 293 | O198: =ROUND(M198*$O$3,2) -> 12.77 | P198: =Q198-N198 -> 4 | Q198: 297 | R198: =ROUND(P198*$R$3,2) -> 11.48 | S198: =+T198-Q198 -> 3 | T198: 300 | U198: =ROUND(S198*$U$3,2) -> 8.94 | V198: =+W198-T198 -> 4 | W198: 304 | X198: =V198*$X$3 -> 11.9008
... A201: DEPA-1712 | B201: 244 | C201: =D201-B201 -> 5 | D201: 249 | E201: =F201-D201 -> 5 | F201: 254 | G201: =H201-F201 -> 6 | H201: 260 | I201: =ROUND(G201*$I$3,2) -> 22.41 | J201: =K201-H201 -> 5 | K201: 265 | L201: =ROUND(J201*$L$3,2) -> 20.77 | M201: =N201-K201 -> 3 | N201: 268 | O201: =ROUND(M201*$O$3,2) -> 19.16 | P201: =Q201-N201 -> 6 | Q201: 274 | R201: =ROUND(P201*$R$3,2) -> 17.22 | S201: =+T201-Q201 -> 5 | T201: 279 | U201: =ROUND(S201*$U$3,2) -> 14.9 | V201: =+W201-T201 -> 7 | W201: 286 | X201: =V201*$X$3 -> 20.8264
A202: PP-LAV | K202: 1571 | M202: =N202-K202 -> 36 | N202: 1607 | O202: =ROUND(M202*$O$3,2) -> 229.88 | P202: =Q202-N202 -> 44 | Q202: 1651 | R202: =ROUND(P202*$R$3,2) -> 126.3 | S202: =+T202-Q202 -> 37 | T202: 1688 | U202: =ROUND(S202*$U$3,2) -> 110.25 | V202: =+W202-T202 -> 48 | W202: 1736 | X202: =V202*$X$3 -> 142.8096
B203: =SUM(B7:B201) -> 43735.03 | C203: =SUM(C7:C201) -> 1151.35 | D203: =SUM(D7:D201) -> 44886.38 | E203: =SUM(E7:E201) -> 1109.89 | F203: =SUM(F7:F201) -> 45996.27 | G203: =SUM(G7:G201) -> 1262.229 | H203: =SUM(H7:H201) -> 46191.877 | I203: =SUM(I7:I201) -> 4713.38 | J203: =SUM(J7:J201) -> 1115.961 | L203: =SUM(L7:L201) -> 4636.29 | M203: =SUM(M7:M202) -> 824.779 | O203: =SUM(O7:O202) -> 5266.8 | P203: =SUM(P7:P202) -> 1035.538 | R203: =SUM(R7:R202) -> 2972.21 | S203: =SUM(S7:S202) -> 1272.95 | U203: =SUM(U7:U202) -> 3793.31 | V203: =SUM(V7:V202) -> 1302.895 | X203: =SUM(X7:X202) -> 3876.3732

Sheet RESUMEN_mes
C3: Valores
A4: CODIGO | B4: PROPIETARIO(S) | C4: Suma de VALOR CUOTA | D4: Suma de AGUA CONSUMO | E4: Suma de SUMA
A5: PP-000 | B5: SIN IDENTIFICAR | C5: 171.3306 | D5: 0 | E5: 171.3306
A6: PP-001 | B6: AJK ASOCIADOS SAC | C6: 346.6529 | D6: 6.7269272 | E6: 353.37983
A7: PP-002 | B7: ALBAN MALACHE CHABELI | C7: 346.6529 | D7: 27.011841 | E7: 373.66474
A8: PP-003 | B8: RUIZ JAVIER ALEJANDRO | C8: 161.94649 | D8: 6.1854408 | E8: 168.13193
A9: PP-004 | B9: ALEXANDER STRAHLE JURGEN | C9: 346.6529 | D9: 17.8512 | E9: 364.5041
A10: PP-005 | B10: ALVA CUELLAR DUGLAS CONCEPCION | C10: 346.6529 | D10: 50.5784 | E10: 397.2313
A11: PP-006 | B11: ALVARADO BRINGAS MILUSKA CARLA | C11: 503.24306 | D11: 2.9752 | E11: 506.21826
A12: PP-007 | B12: ANTON ENICE | C12: 270.3657 | D12: 26.345396 | E12: 296.71109
A13: PP-008 | B13: APARCANA ROSADIO LUIS MIGUEL | C13: 238.2337 | D13: 5.9504 | E13: 244.1841
A14: PP-009 | B14: ASTO VARGAS HANS PIERRE | C14: 161.94649 | D14: 3.6862728 | E14: 165.63277
A15: PP-010 | B15: AVENDAÑO SILVA MIRLEY JESUS | C15: 76.287204 | D15: 0 | E15: 76.287204
A16: PP-011 | B16: AVILA JOEL ANTONIO | C16: 346.6529 | D16: 5.9504 | E16: 352.6033
... A208: PP-202 | B208: PALOMINO CRISTIAN | C208: 346.6529 | D208: 2.9752 | E208: 349.6281
A209: Total general | C209: 60462.665 | D209: 3879.3484 | E209: 64342.013

Sheet calculo
A1: CODIGO | B1: PROPIETARIO(S) | C1: PREDIO | D1: ÁREA TECHADA | E1: ÁREA OCUPADA | F1: % PARTICIPACIÓN | G1: VALOR CUOTA | H1: AGUA CONSUMO | I1: SUMA
A2: PP-000 | B2: SIN IDENTIFICAR | C2: E000 | D2: 0 | E2: 0 | F2: 0.00285 | G2: =pp_anual26*F2 -> 171.3306 | H2: =IFERROR(VLOOKUP(C2,consumo_agua!$A$7:$X$202,24,0),0) -> 0 | I2: =SUM(G2:H2) -> 171.3306
A3: PP-001 | B3: AJK ASOCIADOS SAC | C3: DEPA-1605 | D3: 78.95 | E3: 78.95 | F3: 0.0044974 | G3: =pp_anual26*F3 -> 270.3657 | H3: =IFERROR(VLOOKUP(C3,consumo_agua!$A$7:$X$202,24,0),0) -> 6.7269272 | I3: =SUM(G3:H3) -> 277.09263
A4: PP-001 | B4: AJK ASOCIADOS SAC | C4: ESTA-020 | D4: 0 | E4: 0 | F4: 0.001269 | G4: =pp_anual26*F4 -> 76.287204 | H4: =IFERROR(VLOOKUP(C4,consumo_agua!$A$7:$X$202,24,0),0) -> 0 | I4: =SUM(G4:H4) -> 76.287204
A5: PP-002 | B5: ALBAN MALACHE CHABELI | C5: DEPA-612 | D5: 74.6 | E5: 74.6 | F5: 0.0044974 | G5: =pp_anual26*F5 -> 270.3657 | H5: =IFERROR(VLOOKUP(C5,consumo_agua!$A$7:$X$202,24,0),0) -> 27.011841 | I5: =SUM(G5:H5) -> 297.37754
A6: PP-002 | B6: ALBAN MALACHE CHABELI | C6: ESTA-067 | D6: 0 | E6: 0 | F6: 0.001269 | G6: =pp_anual26*F6 -> 76.287204 | H6: =IFERROR(VLOOKUP(C6,consumo_agua!$A$7:$X$202,24,0),0) -> 0 | I6: =SUM(G6:H6) -> 76.287204
A7: PP-003 | B7: RUIZ JAVIER ALEJANDRO | C7: DEPA-811 | D7: 33 | E7: 33 | F7: 0.0026939 | G7: =pp_anual26*F7 -> 161.94649 | H7: =IFERROR(VLOOKUP(C7,consumo_agua!$A$7:$X$202,24,0),0) -> 6.1854408 | I7: =SUM(G7:H7) -> 168.13193
A8: PP-004 | B8: ALEXANDER STRAHLE JURGEN | C8: DEPA-902 | D8: 77.05 | E8: 77.05 | F8: 0.0044974 | G8: =pp_anual26*F8 -> 270.3657 | H8: =IFERROR(VLOOKUP(C8,consumo_agua!$A$7:$X$202,24,0),0) -> 17.8512 | I8: =SUM(G8:H8) -> 288.2169
A9: PP-004 | B9: ALEXANDER STRAHLE JURGEN | C9: ESTA-042 | D9: 0 | E9: 0 | F9: 0.001269 | G9: =pp_anual26*F9 -> 76.287204 | H9: =IFERROR(VLOOKUP(C9,consumo_agua!$A$7:$X$202,24,0),0) -> 0 | I9: =SUM(G9:H9) -> 76.287204
A10: PP-005 | B10: ALVA CUELLAR DUGLAS CONCEPCION | C10: DEPA-1205 | D10: 78.95 | E10: 78.95 | F10: 0.0044974 | G10: =pp_anual26*F10 -> 270.3657 | H10: =IFERROR(VLOOKUP(C10,consumo_agua!$A$7:$X$202,24,0),0) -> 50.5784 | I10: =SUM(G10:H10) -> 320.9441
A11: PP-005 | B11: ALVA CUELLAR DUGLAS CONCEPCION | C11: ESTA-077 | D11: 0 | E11: 0 | F11: 0.001269 | G11: =pp_anual26*F11 -> 76.287204 | H11: =IFERROR(VLOOKUP(C11,consumo_agua!$A$7:$X$202,24,0),0) -> 0 | I11: =SUM(G11:H11) -> 76.287204
A12: PP-006 | B12: ALVARADO BRINGAS MILUSKA CARLA | C12: DEPA-1001 | D12: 92.5 | E12: 92.5 | F12: 0.0056773 | G12: =pp_anual26*F12 -> 341.29657 | H12: =IFERROR(VLOOKUP(C12,consumo_agua!$A$7:$X$202,24,0),0) -> 2.9752 | I12: =SUM(G12:H12) -> 344.27177
A13: PP-006 | B13: ALVARADO BRINGAS MILUSKA CARLA | C13: ESTA-063 | D13: 0 | E13: 0 | F13: 0.0026939 | G13: =pp_anual26*F13 -> 161.94649 | H13: =IFERROR(VLOOKUP(C13,consumo_agua!$A$7:$X$202,24,0),0) -> 0 | I13: =SUM(G13:H13) -> 161.94649
... A383: PP-LAV | B383: LAVANDERIA PRONTOMATIK | C383: PP-LAV | D383: 0 | E383: 0 | F383: 0 | G383: =pp_anual26*F383 -> 0 | H383: =IFERROR(VLOOKUP(C383,consumo_agua!$A$7:$X$202,24,0),0) -> 142.8096 | I383: =SUM(G383:H383) -> 142.8096
D384: =SUM(D1:D383) -> 12835.37 | E384: =SUM(E1:E383) -> 12955.95 | F384: =SUM(F1:F383) -> 1.0057666 | G384: =SUM(G1:G383) -> 60462.665 | H384: =SUM(H1:H383) -> 3879.3484 | I384: =SUM(I1:I383) -> 64342.013

Sheet egresos
A1: Fecha | B1: Descripción operación | C1: Monto | D1: Operación - Número | E1: Referencia2
A2: 45895 | B2: IMPUESTO ITF | C2: -6.35 | D2: 00000000
A3: 45898 | B3: IMPUESTO ITF | C3: -0.1 | D3: 00000000
A4: 45899 | B4: ENVIO.EST.CTA | C4: -5.5 | D4: 00922526
A5: 45900 | B5: COM.MANTENIM | C5: -35 | D5: 00000000
A6: 45905 | B6: IMPUESTO ITF | C6: -0.05 | D6: 00000000
A7: 45909 | B7: EMIS. CHEQ DE GERENCIA | C7: -50016.5 | D7: 00216355
A8: 45909 | B8: IMPUESTO ITF | C8: -2.5 | D8: 00000000
A9: 45925 | B9: EMIS.CHEQ GEREN VENT | C9: -50014 | D9: 00073300
A10: 45925 | B10: COMISIONES CARTA ORDEN | C10: -60 | D10: 00070749
A11: 45930 | B11: COM.MANTENIM | C11: -35 | D11: 00000000
A12: 45930 | B12: ENVIO.EST.CTA | C12: -5.5 | D12: 00923700
A13: 45937 | B13: IMPUESTO ITF | C13: -0.05 | D13: 00000000
A14: 45945 | B14: A 194 35396121 0 | C14: -1724 | D14: 01284674 | E14: MANT CISTERNAS Y BOMBA
A15: 45945 | B15: TRANFERENCIA CCE | C15: -1084.3 | D15: 04022457
A16: 45945 | B16: A 192 74404443 0 | C16: -804 | D16: 01286577 | E16: PACIFIK MANT PRENVENTI
A17: 45945 | B17: A 191 74870101 0 | C17: -500 | D17: 01286103 | E17: REEMBOLSO GARANTIA DEP
A18: 45945 | B18: A 193 03842884 0 | C18: -430 | D18: 01286102 | E18: REEMBOLSO GARANTIA DEP
A19: 45945 | B19: A 191 7786938 0 | C19: -300 | D19: 01287551 | E19: SERVICIOS EXTRAS LIMPI
A20: 45945 | B20: IMPUESTO ITF | C20: -0.1 | D20: 00000000
A21: 45950 | B21: IMPUESTO ITF | C21: -0.05 | D21: 00000000
A22: 45953 | B22: IMPUESTO ITF | C22: -0.05 | D22: 00000000
A23: 45954 | B23: TRANFERENCIA CCE | C23: -24430.3 | D23: 04012974
A24: 45954 | B24: A 191 2097589 0 | C24: -1374 | D24: 01162648 | E24: material limpieza paci
A25: 45954 | B25: A 193 04699499 0 | C25: -1000 | D25: 01163128 | E25: Audit gestion dos anos
A26: 45954 | B26: A 191 97211880 0 | C26: -580 | D26: 01161183 | E26: RG depa 1212 lounge an
A27: 45954 | B27: A 191 04291231 0 | C27: -500 | D27: 01160717 | E27: reembolso garantia DEP
A28: 45954 | B28: A 191 39132335 0 | C28: -500 | D28: 01160225 | E28: RG depa 207 lounge 251
A29: 45954 | B29: A 191 01775351 0 | C29: -500 | D29: 01161184 | E29: RG depa 1002 lounge 25
A30: 45954 | B30: A 193 35382222 0 | C30: -450 | D30: 01163129 | E30: REEMBOLSO GARANTIA DEP
A31: 45954 | B31: A 191 29719140 0 | C31: -430 | D31: 01162144 | E31: reembolso garantia DEP
A32: 45954 | B32: A 192 97940244 0 | C32: -330 | D32: 01161182 | E32: reembolso garantia dep
A33: 45954 | B33: A 191 08348364 0 | C33: -300 | D33: 01161679 | E33: Honorarios agosto y se
A34: 45954 | B34: A 193 76088550 0 | C34: -167.9 | D34: 01162647 | E34: reembolso internet mov
A35: 45954 | B35: A 193 17476343 0 | C35: -100 | D35: 01161678 | E35: RG depa 312 arcade 251
... A37: 45954 | B37: A 193 04699499 0 | C37: -99.9 | D37: 01161185 | E37: Internet Pacifik 20250
A38: 45954 | B38: IMPUESTO ITF | C38: -1.3 | D38: 00000000
A39: 45958 | B39: A 194 2636555 0 | C39: -2080 | D39: 01111134 | E39: 50 LUMINARIAS CON SENS
A40: 45958 | B40: A 194 2636555 0 | C40: -2080 | D40: 01172874 | E40: SALDO 50 LUMINARIAS CO
A41: 45958 | B41: A 191 2367445 0 | C41: -690 | D41: 01108214 | E41: ANTICIPO 40 INSTALACIO
A42: 45958 | B42: IMPUESTO ITF | C42: -0.2 | D42: 00000000
A43: 45960 | B43: A 194 35396121 0 | C43: -2986 | D43: 01011671 | E43: 60 saldo mant bombas y
A44: 45960 | B44: A 192 74404443 0 | C44: -1206 | D44: 01008192 | E44: saldo 60 mant camaras
A45: 45960 | B45: A 193 25372364 0 | C45: -950 | D45: 01008692 | E45: 202509 mant piscina pi
A46: 45960 | B46: A 194 2636555 0 | C46: -320 | D46: 01008193 | E46: diez luminarias adicio
A47: 45960 | B47: A 191 7786938 0 | C47: -300 | D47: 01010181 | E47: 202510 plus adicionale
A48: 45960 | B48: A 193 71013755 0 | C48: -200 | D48: 01009692 | E48: 202510 octubre mant ja
A49: 45960 | B49: A 192 77423480 0 | C49: -180 | D49: 01010672 | E49: son 09 nueve limpieza
A50: 45960 | B50: A 193 04699499 0 | C50: -164 | D50: 01011172 | E50: proyecto luminarias ad
A51: 45960 | B51: A 192 70157524 0 | C51: -100 | D51: 01009187 | E51: Son cinco 5 limpieza p
A52: 45960 | B52: TLC 0050S3 MANT OCT | C52: -13.85 | D52: 00000000
A53: 45960 | B53: IMPUESTO ITF | C53: -0.15 | D53: 00000000
A54: 45961 | B54: COM.MANTENIM | C54: -35 | D54: 00000000
A55: 45961 | B55: ENVIO.EST.CTA | C55: -5.5 | D55: 00925459
A56: 45964 | B56: PLUZ000003017922 | C56: -16552 | D56: 04163492
A57: 45964 | B57: SEDA000007458225 | C57: -5072.4 | D57: 04166043
A58: 45964 | B58: A 191 2367445 0 | C58: -1435 | D58: 01164543 | E58: Saldo proyecto luminar
A59: 45964 | B59: A 193 2409247 0 | C59: -1000 | D59: 01166041 | E59: ANTICIPO 40 CORRECTIVO
A60: 45964 | B60: A 193 25372364 0 | C60: -950 | D60: 01165536 | E60: 2510 mant piscina espe
A61: 45964 | B61: A 193 38445350 0 | C61: -500 | D61: 01164059 | E61: RG LOUNGE DEPA 1405
A62: 45964 | B62: A 193 93935334 0 | C62: -500 | D62: 01164058 | E62: RG LOUNGE DEPA 301
A63: 45964 | B63: A 193 16143407 0 | C63: -430 | D63: 01165044 | E63: RG lounge con extensio
A64: 45964 | B64: PLUZ000003017921 | C64: -173 | D64: 04166042
A65: 45964 | B65: TDPC000756853236 | C65: -105.9 | D65: 04164544
A66: 45964 | B66: A 191 97211880 0 | C66: -100 | D66: 01166516 | E66: RG arcade depa 1212
A67: 45964 | B67: IMPUESTO ITF | C67: -1.15 | D67: 00000000
A68: 45966 | B68: IMPUESTO ITF | C68: -0.05 | D68: 00000000
A69: 45968 | B69: IMPUESTO ITF | C69: -0.05 | D69: 00000000
A70: 45969 | B70: A 193 2409247 0 | C70: -1500 | D70: 01012388 | E70: 2511 SALDO CORRECTIVO
A71: 45969 | B71: A 193 2409247 0 | C71: -1000 | D71: 01015366 | E71: 2511 MANT PREVENTIVO A
A72: 45969 | B72: A 193 71013755 0 | C72: -200 | D72: 01014872 | E72: 2510 MANT JARDINERIA A
A73: 45970 | B73: IMPUESTO ITF | C73: -0.1 | D73: 00000000
A74: 45974 | B74: A 194 35487825 0 | C74: -925 | D74: 01193850 | E74: anticipo instalacion s
A75: 45974 | B75: A 191 08348364 0 | C75: -500 | D75: 01194336 | E75: anticipo conexion puer
A76: 45974 | B76: A 192 33757449 0 | C76: -100 | D76: 01192888 | E76: RG DEPA 701 ARCADE
A77: 45974 | B77: A 194 38316782 0 | C77: -100 | D77: 01194819 | E77: RG arcade depa 809
A78: 45975 | B78: TRANFERENCIA CCE | C78: -354.3 | D78: 04001596
A79: 45975 | B79: A 193 31380710 0 | C79: -280 | D79: 01009103 | E79: RG LOUNGE DEPA 208
A80: 45977 | B80: IMPUESTO ITF | C80: -0.05 | D80: 00000000
A81: 45978 | B81: IMPUESTO ITF | C81: -0.05 | D81: 00000000
A82: 45979 | B82: IMPUESTO ITF | C82: -0.1 | D82: 00000000
A83: 45981 | B83: TRANFERENCIA CCE | C83: -24430.3 | D83: 04024517
A84: 45981 | B84: A 194 35487825 0 | C84: -925 | D84: 01288171 | E84: SALDO FRENO HIDRAULICO
A85: 45981 | B85: A 193 04699499 0 | C85: -920.4 | D85: 01290072 | E85: RCC admin puerta piso
A86: 45981 | B86: A 194 35396121 0 | C86: -600 | D86: 01291054 | E86: Mant correctivo tuberi
A87: 45981 | B87: A 191 08348364 0 | C87: -500 | D87: 01290568 | E87: SALDO MANT CORRECTIVO
A88: 45981 | B88: A 191 02193176 0 | C88: -500 | D88: 01288640 | E88: RG depa 1004 lounge
A89: 45981 | B89: A 194 37261014 0 | C89: -500 | D89: 01289088 | E89: RG depa 1011 lounge
A90: 45981 | B90: PLUZ000003017921 | C90: -141.5 | D90: 04290569
A91: 45981 | B91: IMPUESTO ITF | C91: -1.2 | D91: 00000000
A92: 45984 | B92: IMPUESTO ITF | C92: -0.1 | D92: 00000000
A93: 45985 | B93: IMPUESTO ITF | C93: -0.05 | D93: 00000000
A94: 45986 | B94: IMPUESTO ITF | C94: -0.1 | D94: 00000000
A95: 45987 | B95: TLC 0050S3 MANT NOV | C95: -41.45 | D95: 00000000
A96: 45988 | B96: IMPUESTO ITF | C96: -0.55 | D96: 00000000
A97: 45989 | B97: PLUZ000003017922 | C97: -14598 | D97: 04236770
A98: 45989 | B98: SEDA000007458225 | C98: -5193.1 | D98: 04237253
A99: 45989 | B99: A 193 2409247 0 | C99: -1000 | D99: 01238194 | E99: ANTICIPO correctivos a
A100: 45989 | B100: A 193 17476343 0 | C100: -500 | D100: 01237709 | E100: RG lounge depa 305
A101: 45989 | B101: A 192 25252848 0 | C101: -500 | D101: 01237252 | E101: RG lounge depa 1512
...

Sheet tablas
A1: anexo
A2: 2025-01
A3: 2025-02
A4: 2025-03
A5: 2025-04
A6: 2025-05
A7: 2025-06
A8: 2025-07
A9: 2025-08
A10: 2025-09
A11: 2025-10
A12: 2025-11
... A20: sin identificar

Sheet codigos
A1: CODIGO | B1: PROPIETARIO(S) | C1: propiedad
A2: PP-000 | B2: SIN IDENTIFICAR | C2: E000
A3: PP-001 | B3: AJK ASOCIADOS SAC | C3: DEPA-1605
A4: PP-002 | B4: ALBAN MALACHE CHABELI | C4: DEPA-612
A5: PP-003 | B5: RUIZ JAVIER ALEJANDRO | C5: DEPA-811
A6: PP-004 | B6: ALEXANDER STRAHLE JURGEN | C6: DEPA-902
A7: PP-005 | B7: ALVA CUELLAR DUGLAS CONCEPCION | C7: DEPA-1205
A8: PP-006 | B8: ALVARADO BRINGAS MILUSKA CARLA | C8: DEPA-1001
A9: PP-007 | B9: ANTON ENICE | C9: DEPA-610
A10: PP-008 | B10: APARCANA ROSADIO LUIS MIGUEL | C10: DEPA-606
A11: PP-009 | B11: ASTO VARGAS HANS PIERRE | C11: DEPA-1311
A12: PP-010 | B12: AVENDAÑO SILVA MIRLEY JESUS | C12: ESTA-087
... A205: PP-LAV | B205: LAVANDERIA PRONTOMATIK | C205: PP-LAV

Sheet ingresos
A1: mes | B1: fecha | C1: glosa | D1: valor soles | E1: operación nro. | F1: codigo | G1: anexo | H1: detalle-referencia
A2: 8 | B2: 45870 | C2: varios | D2: 0 | E2: 9999999 | F2: PP-000 | H2: GENERICO
A3: 8 | B3: 45895 | C3: TRANSF.BCO.INTERBANK | D3: 306.42 | E3: 02130246 | F3: PP-017 | G3: 2025-08 | H3: BLAS-OLIVER-LIDIA | I3: 5
A4: 8 | B4: 45895 | C4: TRAN.CTAS.TERC.BM | D4: 580 | E4: 01030013 | G4: lounge | H4: BUSTAMANTE RUIZ EDUARDO CARLOS | I4: 6
A5: 8 | B5: 45895 | C5: TRAN.CTAS.TERC.BM | D5: 333.9 | E5: 01528693 | F5: PP-022 | G5: 2025-07 | H5: CARDENAS MORIANO HEVELYNE HILDA | I5: 5
A6: 8 | B6: 45895 | C6: TRAN.CTAS.TERC.BM | D6: 411.38 | E6: 04244321 | F6: PP-128 | G6: 2025-08 | H6: CELI GUTIERREZ DIANA KARINA | I6: 7
A7: 8 | B7: 45895 | C7: TRAN.CTAS.TERC.BM | D7: 275.58 | E7: 04079146 | F7: PP-090 | G7: 2025-08 | H7: CUBA REYES ANGIE CONSUELO LESLIE | I7: 5
A8: 8 | B8: 45895 | C8: TRAN.CTAS.TERC.BM | D8: 168.8 | E8: 01403678 | F8: PP-082 | G8: 2025-08 | H8: HUERTA HUERTA CARLA ALESSANDRA | I8: 5
A9: 8 | B9: 45895 | C9: TRANSF.BCO.BBVA | D9: 23.37 | E9: 02276178 | F9: PP-039 | G9: 2025-08 | H9: JOSE AUGUSTO CANDELA ROJAS | I9: 5
A10: 8 | B10: 45895 | C10: TRANSF.BCO.BBVA | D10: 372.01 | E10: 02271919 | F10: PP-190 | G10: 2025-08 | H10: MARIA GISELLA YOUNG GUERRERO | I10: 5
A11: 8 | B11: 45895 | C11: TRAN.CTAS.TERC.BM | D11: 301.72 | E11: 01860628 | F11: PP-108 | G11: 2025-08 | H11: MENDOZA BAZAN SILVIA VERONICA | I11: 4
A12: 8 | B12: 45895 | C12: TRAN.CTAS.TERC.BM | D12: 455.51 | E12: 03214653 | F12: PP-119 | G12: 2025-08 | H12: NUNEZ ESTRADA YULY CRISTINA | I12: 7
A13: 8 | B13: 45895 | C13: TRAN.CTAS.TERC.HK | D13: 168.8 | E13: 06046753 | F13: PP-122 | G13: 2025-08 | H13: OLIVARES SAAVEDRA JAIME ALBERTO | I13: 5
A14: 8 | B14: 45895 | C14: TRANSF.BCO.INTERBANK | D14: 404.47 | E14: 02185017 | F14: PP-129 | G14: 2025-08 | H14: ORE-ROSARIO-CRISTOPHER | I14: 6
A15: 8 | B15: 45895 | C15: TRAN.CTAS.TERC.BM | D15: 380.04 | E15: 04046820 | F15: PP-145 | G15: 2025-08 | H15: REGALADO SANTANA MARIA CELINDA | I15: 6
A16: 8 | B16: 45895 | C16: ENTREGA C/CHEQUES FUE | D16: 127565.13 | E16: 00788858 | F16: PACIFIK | G16: sin identificar | H16: VENTANILLA | I16: 3
... A23: 8 | B23: 45896 | C23: TRAN.CTAS.TERC.BM | D23: 261.5 | E23: 00157192 | F23: PP-094 | G23: 2025-08 | H23: MEJIA TURRIATE DEBORA DICK | I23: 5
A24: 8 | B24: 45896 | C24: TRAN.CTAS.TERC.BM | D24: 580 | E24: 00589497 | G24: lounge | H24: MILUSKA CRIS TAPIA CASARETTO | I24: 6
A25: 8 | B25: 45896 | C25: TRAN.CTAS.TERC.BM | D25: 265.23 | E25: 00669135 | F25: PP-046 | G25: 2025-08 | H25: MILUSKA CRIS TAPIA CASARETTO | I25: 6
A26: 8 | B26: 45896 | C26: TRANSF.BCO.INTERBANK | D26: 507.9 | E26: 02556593 | F26: PP-137 | G26: 2025-08 | H26: RAMOS-REQUEJO-MABEL | I26: 6
A27: 8 | B27: 45896 | C27: TRAN.CTAS.TERC.BM | D27: 379.48 | E27: 00603438 | F27: PP-045 | G27: 2025-08 | H27: RUIZ SANDOVAL FLOR DE MARIA | I27: 5
A28: 8 | B28: 45896 | C28: TRAN.CTAS.TERC.BM | D28: 175.82 | E28: 05034305 | F28: PP-081 | G28: 2025-08 | H28: TIPON GALVIS MICHAEL | I28: 5
A29: 8 | B29: 45896 | C29: TRAN.CTAS.TERC.BM | D29: 195.06 | E29: 03392234 | F29: PP-174 | G29: 2025-08 | H29: VALDEZ CADENILLAS AGUSTIN | I29: 8
A30: 8 | B30: 45896 | C30: TRAN.CTAS.TERC.BM | D30: 165.07 | E30: 01737357 | F30: PP-175 | G30: 2025-08 | H30: VALDIVIA OBANDO OSCAR EDMUNDO FRANCISCO | I30: 2
A31: 8 | B31: 45896 | C31: DEPOSITO AG 971093 | D31: 468 | E31: 00048102 | F31: PP-186 | G31: 2025-08 | I31: 5
A32: 8 | B32: 45897 | C32: DEPOSITO AG 981945 | D32: 429.4 | E32: 00090790 | F32: PP-058 | G32: 2025-08 | H32: CISNEROS CAHUANA JUANA CLENIA | I32: 5
A33: 8 | B33: 45897 | C33: TRAN.CTAS.TERC.BM | D33: 374.56 | E33: 03212730 | F33: PP-040 | G33: 2025-08 | H33: CORDERO VILCA PEDRO LUIS | I33: 7
A34: 8 | B34: 45897 | C34: TRANSF.BCO.SCOTIABANK | D34: 181.74 | E34: 02868748 | F34: PP-009 | G34: 2025-08 | H34: DIEGO SEGURA MENDEZ | I34: 5
A35: 8 | B35: 45897 | C35: TRANSF.BCO.INTERBANK | D35: 316.65 | E35: 02132541 | F35: PP-142 | G35: 2025-08 | H35: GARCIA-SUAREZ-CARLOS | I35: 5
A36: 8 | B36: 45897 | C36: TRAN.CTAS.TERC.BM | D36: 243.49 | E36: 01430615 | F36: PP-184 | G36: 2025-08 | H36: GUERRERO GUERRERO BENNER ROLAN | I36: 5
A37: 8 | B37: 45897 | C37: TRAN.CTAS.TERC.BM | D37: 202.41 | E37: 04731144 | F37: PP-158 | G37: 2025-08 | H37: MEDINA SARMIENTO JAVIER | I37: 4
A38: 8 | B38: 45897 | C38: TRAN.CTAS.TERC.BM | D38: 312.92 | E38: 00668414 | F38: PP-068 | G38: 2025-08 | H38: MONICA JULIE GUERRERO ABARCA | I38: 6
A39: 8 | B39: 45897 | C39: TRANSF.BCO.INTERBANK | D39: 175.66 | E39: 02267630 | F39: PP-102 | G39: 2025-08 | H39: MORALES-DURAND-DE-DURAN-ZANDRA | I39: 7
A40: 8 | B40: 45897 | C40: TRAN.CTAS.TERC.BM | D40: 372.01 | E40: 01569667 | F40: PP-118 | G40: 2025-08 | H40: NEIRA UN JAN MILAGROS ANDREA | I40: 7
A41: 8 | B41: 45897 | C41: TRAN.CTAS.TERC.HK | D41: 77.76 | E41: 06017738 | F41: PP-123 | G41: 2025-07 | H41: ORELLANA VARGAS CARMEN ROSA | I41: 10
A42: 8 | B42: 45898 | C42: DE BERTOLOTTO INVESTME | D42: 2056.59 | E42: 02050826 | F42: PP-016 | G42: 2025-08 | H42: BERTOLOTTO INVESTMENTS S.A.C. | I42: 3
A43: 8 | B43: 45898 | C43: TRAN.CTAS.TERC.BM | D43: 389.76 | E43: 04758347 | F43: PP-044 | G43: 2025-07 | H43: DE-LA-CRUZ DELGADO WALTER | I43: 5
... A58: 8 | B58: 45899 | C58: TRANSF.BCO.INTERBANK | D58: 191.21 | E58: 02477847 | F58: PP-035 | G58: 2025-08 | H58: CHAVEZ-TAGLE-SISLEY | I58: 5
A59: 8 | B59: 45899 | C59: TRANSF.BCO.SCOTIABANK | D59: 30 | E59: 02575512 | G59: cine | H59: EDWARD SANDOVAL AMASIFUEN | I59: 6
A60: 8 | B60: 45899 | C60: TRAN.CTAS.TERC.BM | D60: 394.41 | E60: 02466805 | F60: PP-181 | G60: 2025-08 | H60: FIGUEROA MARQUEZ ELIZABETH JANETH | I60: 5
A61: 8 | B61: 45899 | C61: TRAN.CTAS.TERC.BM | D61: 189.6 | E61: 05405035 | F61: PP-121 | G61: 2025-08 | H61: GUTIERREZ CORDOVA ANGELA PIERINA | I61: 7
A62: 8 | B62: 45899 | C62: TRAN.CTAS.TERC.BM | D62: 368.27 | E62: 04379962 | F62: PP-074 | G62: 2025-08 | H62: GUTIERREZ GUERRERO YEISON MARTIN | I62: 4
A63: 8 | B63: 45899 | C63: TRANSF.BCO.SCOTIABANK | D63: 375.74 | E63: 02641744 | F63: PP-092 | G63: 2025-08 | H63: JOSE LAMADRID MESONES | I63: 6
A64: 8 | B64: 45899 | C64: TRAN.CTAS.TERC.BM | D64: 407.07 | E64: 02159673 | F64: PP-085 | G64: 2025-08 | H64: PARI NUNEZ LEONOR | I64: 4
A65: 8 | B65: 45899 | C65: TRANSF.BCO.INTERBANK | D65: 383.21 | E65: 02969072 | F65: PP-042 | G65: 2025-08 | H65: PUJOL-CORRECHER-EDUARDO | I65: 7
A66: 8 | B66: 45899 | C66: TRANSF.BCO.INTERBANK | D66: 12.55 | E66: 02969072 | F66: PP-042 | G66: 2025-09 | H66: PUJOL-CORRECHER-EDUARDO | I66: 7
A67: 8 | B67: 45899 | C67: TRAN.CTAS.TERC.BM | D67: 378.24 | E67: 06316368 | F67: PP-171 | G67: 2025-08 | H67: TORRES VILLANTOY SUSAN VICTORIA | I67: 6
A68: 8 | B68: 45899 | C68: TRAN.CTAS.TERC.BM | D68: 405.61 | E68: 04057037 | F68: PP-193 | G68: 2025-08 | H68: ZAPATA VELASCO ANGELA PATRICIA | I68: 6
A69: 8 | B69: 45900 | C69: TRAN.CTAS.TERC.BM | D69: 328.03 | E69: 04243181 | F69: PP-023 | G69: 2025-07 | H69: CARDENAS MORIANO WOLFGAN ANGEL | I69: 3
A70: 8 | B70: 45900 | C70: TRAN.CTAS.TERC.BM | D70: 327.97 | E70: 04243181 | F70: PP-023 | G70: 2025-08 | H70: CARDENAS MORIANO WOLFGAN ANGEL | I70: 3
A71: 8 | B71: 45900 | C71: TRAN.CTAS.TERC.BM | D71: 77.76 | E71: 01147563 | F71: PP-062 | G71: 2025-08 | H71: GODOY ACOSTA NORA EULALIA | I71: 10
... A82: 9 | B82: 45901 | C82: TRAN.CTAS.TERC.BM | D82: 507.13 | E82: 02550065 | F82: PP-101 | G82: 2025-08 | H82: LOREDO RODRIGUEZ CESAR ANTONIO | I82: 5
A83: 9 | B83: 45901 | C83: TRAN.CTAS.TERC.BM | D83: 580 | E83: 06469783 | G83: lounge | H83: MILAGROS MERCEDES BARRIENTOS FLORES | I83: 0
A84: 9 | B84: 45901 | C84: TRAN.CTAS.TERC.BM | D84: 282.24 | E84: 02699038 | F84: PP-134 | G84: 2025-08 | H84: MONZON JUAREZ MILAGROS DEL CARMEN | I84: 6
A85: 9 | B85: 45901 | C85: TRAN.CTAS.TERC.BM | D85: 463.74 | E85: 02316241 | F85: PP-085 | G85: 2025-07 | H85: PARI NUNEZ LEONOR | I85: 4
A86: 9 | B86: 45901 | C86: TRANSF.BCO.SCOTIABANK | D86: 180.01 | E86: 02128282 | F86: PP-123 | G86: 2025-08 | H86: ROSA TUME ZEGARRA | I86: 10
A87: 9 | B87: 45901 | C87: TRAN.CTAS.TERC.BM | D87: 712.81 | E87: 02959876 | F87: PP-064 | G87: 2025-08 | H87: ROSARIO TORRES PATRICIA DEL CARMEN | I87: 7
A88: 9 | B88: 45901 | C88: TRAN.CTAS.TERC.BM | D88: 379.48 | E88: 01044775 | F88: PP-159 | G88: 2025-08 | H88: SAUNE PACCO JOSE OSWALDO | I88: 5
A89: 9 | B89: 45901 | C89: TRAN.CTAS.TERC.BM | D89: 543.97 | E89: 01502596 | F89: PP-140 | G89: 2025-08 | H89: VALDIVIESO LIDIA-O-RIOS NILTON | I89: 4
A90: 9 | B90: 45901 | C90: TRAN.CTAS.TERC.BM | D90: 383.21 | E90: 05134217 | F90: PP-180 | G90: 2025-08 | H90: VEGA DIESTRA DAVID VICTOR | I90: 4
A91: 9 | B91: 45902 | C91: TRAN.CTAS.TERC.BM | D91: 360.8 | E91: 00485389 | F91: PP-089 | G91: 2025-08 | H91: CASTILLO MERCEDES ANA ISABEL | I91: 7
A92: 9 | B92: 45902 | C92: TRAN.CTAS.TERC.BM | D92: 580 | E92: 05044572 | G92: lounge | H92: CASTRO BARRERA ANITA MARITZA | I92: 5
A93: 9 | B93: 45902 | C93: TRAN.CTAS.TERC.HK | D93: 172.54 | E93: 06046144 | F93: PP-191 | G93: 2025-08 | H93: GESTORA DE INVERSIONES INMOBILIARIAS S.A.C. | I93: 4
A94: 9 | B94: 45902 | C94: TRAN.CTAS.TERC.BM | D94: 261.5 | E94: 01916544 | F94: PP-131 | G94: 2025-08 | H94: IZQUIERDO ALATA LIAM JUAN PEDRO | I94: 5
A95: 9 | B95: 45902 | C95: TRAN.CTAS.TERC.BM | D95: 372.79 | E95: 06953028 | F95: PP-189 | G95: 2025-08 | H95: LIANG NN YANQIU | I95: 4
A96: 9 | B96: 45902 | C96: TRAN.CTAS.TERC.BM | D96: 178.67 | E96: 03904694 | F96: PP-104 | G96: 2025-07 | H96: MALDONADO DE-LA-CRUZ NORA TERESA | I96: 5
A97: 9 | B97: 45902 | C97: TRANSF.BCO.INTERBANK | D97: 381.36 | E97: 02236557 | F97: PP-120 | G97: 2025-07 | H97: OCHOA-ALEJOS-CESAR | I97: 5
A98: 9 | B98: 45902 | C98: TRANSF.BCO.BBVA | D98: 364.54 | E98: 02838531 | F98: PP-162 | G98: 2025-08 | H98: ORLANDO SULLCAHUAMAN OTERO | I98: 5
A99: 9 | B99: 45902 | C99: TRAN.CTAS.TERC.BM | D99: 304.71 | E99: 05551900 | F99: PP-098 | G99: 2025-07 | H99: SANALEA REANO-DE-LLANO YOLANDA | I99: 2
A100: 9 | B100: 45903 | C100: TRANSF.BCO.BBVA | D100: 265.23 | E100: 02008577 | F100: PP-112 | G100: 2025-08 | H100: ALEXANDER ANDRES BAYONA QUISPE | I100: 4
A101: 9 | B101: 45903 | C101: TRAN.CTAS.TERC.BM | D101: 386.94 | E101: 01063239 | F101: PP-005 | G101: 2025-08 | H101: ALVA CUELLAR DUGLAS CONCEPCION | I101: 5
A102: 9 | B102: 45903 | C102: TRAN.CTAS.TERC.BM | D102: 383.21 | E102: 03703496 | F102: PP-165 | G102: 2025-08 | H102: TINEDO LOPEZ PEDRO LUIS | I102: 5
A103: 9 | B103: 45904 | C103: TRANSF.BCO.NACION | D103: 392.7 | E103: 02603044 | F103: PP-002 | G103: 2025-08 | H103: CARMEN MALACHE | I103: 5
A104: 9 | B104: 45904 | C104: TRAN.CTAS.TERC.BM | D104: 368.27 | E104: 04658131 | F104: PP-172 | G104: 2025-08 | H104: SALVATIERRA TORRES ROGGER DANNY | I104: 4
... A112: 9 | B112: 45905 | C112: TRAN.CTAS.TERC.BM | D112: 172.12 | E112: 05316678 | F112: PP-038 | G112: 2025-08 | H112: MENDOZA SALDANA FRANK ANDRE | I112: 4
A113: 9 | B113: 45905 | C113: TRAN.CTAS.TERC.BM | D113: 580 | E113: 01712136 | G113: lounge | H113: NEIRA UN-JAN MILAGROS ANDREA | I113: 7
A114: 9 | B114: 45905 | C114: DEPOSITO AG 986604 | D114: 187.59 | E114: 00273490 | F114: PP-088 | G114: 2025-08 | H114: PARDO NAVARRO KENNEDY | I114: 3
A115: 9 | B115: 45906 | C115: TRANSF.BCO.INTERBANK | D115: 327.86 | E115: 02932196 | F115: PP-052 | G115: 2025-08 | H115: FALCON-RAMOS-CAROLINA | I115: 4
A116: 9 | B116: 45907 | C116: TRAN.CTAS.TERC.BM | D116: 641.05 | E116: 02734607 | F116: PP-013 | G116: 2025-08 | H116: BOZA VILLAVICENCIO ROSA ISABEL | I116: 4
A117: 9 | B117: 45908 | C117: TRAN.CTAS.TERC.BM | D117: 445.24 | E117: 02630529 | F117: PP-015 | G117: 2025-08 | H117: BENITES BALDOCEDA MARIA DE LOS ANGELES | I117: 8
A118: 9 | B118: 45908 | C118: TRAN.CTAS.TERC.BM | D118: 180.01 | E118: 02630529 | F118: PP-153 | G118: 2025-08 | H118: BENITES BALDOCEDA MARIA DE LOS ANGELES | I118: 6
A119: 9 | B119: 45908 | C119: TRAN.CTAS.TERC.BM | D119: 261.5 | E119: 02630529 | F119: PP-163 | G119: 2025-08 | H119: BENITES BALDOCEDA MARIA DE LOS ANGELES | I119: 5
A120: 9 | B120: 45908 | C120: TRAN.CTAS.TERC.BM | D120: 464.76 | E120: 01125667 | F120: PP-157 | G120: 2025-08 | H120: BUSTAMANTE RUIZ EDUARDO CARLOS | I120: 6
A121: 9 | B121: 45908 | C121: TRANSF.BCO.BBVA | D121: 40 | E121: 02777843 | G121: parrilla | H121: LUIS FERNANDO DELGADO SILVA | I121: 4
A122: 9 | B122: 45908 | C122: TRAN.CTAS.TERC.BM | D122: 401.88 | E122: 03234701 | F122: PP-178 | G122: 2025-08 | H122: VALLEBUONA MAYTA LUIS ALBERTO | I122: 6
A123: 9 | B123: 45908 | C123: TRAN.CTAS.TERC.BM | D123: 40 | E123: 03239190 | G123: parrilla | H123: VALLEBUONA MAYTA LUIS ALBERTO | I123: 6
A124: 9 | B124: 45908 | C124: TRAN.CTAS.TERC.BM | D124: 446.4 | E124: 01061359 | F124: PP-188 | G124: 2025-08 | H124: YAIPEN PANTOJA ALEXIS | I124: 4
A125: 9 | B125: 45909 | C125: TRANSF.BCO.BBVA | D125: 580 | E125: 02120334 | G125: lounge | H125: LOURDES DE LOS ANGEL MADUE�O CHUMPITAZ | I125: 5
A126: 9 | B126: 45910 | C126: TRANSF.BCO.INTERBANK | D126: 502.27 | E126: 02335804 | F126: PP-075 | G126: 2025-08 | H126: GUTIERREZ-PECEROS-ALBERTO | I126: 5
A127: 9 | B127: 45910 | C127: TRANSF.BCO.BBVA | D127: 394.36 | E127: 02498486 | F127: PP-077 | G127: 2025-08 | H127: HELEN FRANCESCA HENOSTROZA CRUZ | I127: 4
A128: 9 | B128: 45911 | C128: ENTR.EFEC. 0567303 | D128: 178.4 | E128: 00567303 | F128: PP-194 | G128: 2025-08 | H128: ALVARES PEÑA CARLOS EDUARDO | I128: 4
A129: 9 | B129: 45911 | C129: TRAN.CTAS.TERC.BM | D129: 80 | E129: 03369136 | G129: parrilla | H129: ANDRADES ROMA JOSE MARCELO | I129: 0
A130: 9 | B130: 45911 | C130: TRAN.CTAS.TERC.BM | D130: 40 | E130: 00309424 | G130: parrilla | H130: MILUSKA CRIS TAPIA CASARETTO | I130: 6
A131: 9 | B131: 45911 | C131: TRAN.CTAS.TERC.BM | D131: 272.7 | E131: 04116946 | F131: PP-173 | G131: 2025-08 | H131: TUPAYACHI VALLENAS DENIS ALFREDO | I131: 3
A132: 9 | B132: 45912 | C132: TRAN.CTAS.TERC.BM | D132: 40 | E132: 04315211 | G132: parrilla | H132: BUSTAMANTE RUIZ EDUARDO CARLOS | I132: 6
A133: 9 | B133: 45912 | C133: TRANSF.BCO.INTERBANK | D133: 580 | E133: 02692875 | G133: lounge | H133: CHAUCA-DE-LOS-SANTOS-PATRICIA | I133: 9
A134: 9 | B134: 45912 | C134: TRANSF.BCO.PICHINCHA | D134: 598.17 | E134: 00052658 | F134: PP-100 | G134: 2025-08 | H134: LOPEZ FORTUNATO | I134: 9
A135: 9 | B135: 45912 | C135: TRAN.CTAS.TERC.BM | D135: 580 | E135: 03004245 | G135: lounge | H135: LU BEJARANO PAMELA MILAGROS | I135: 0
A136: 9 | B136: 45912 | C136: TRAN.CTAS.TERC.HK | D136: 77.76 | E136: 06038055 | F136: PP-123 | G136: 2025-08 | H136: ORELLANA VARGAS CARMEN ROSA | I136: 10
A137: 9 | B137: 45912 | C137: TRANSF.BCO.INTERBANK | D137: 180.18 | E137: 02607176 | F137: PP-026 | G137: 2025-07 | H137: TOLOSA-ALVARES-WILKENDRY | I137: 6
...

Sheet cuotas_emitidas
A1: CODIGO | B1: PROPIETARIO(S) | C1: propiedad | D1: 2023 | E1: 2024 | F1: 2025-01 | G1: 2025-02 | H1: 2025-03 | I1: 2025-04 | J1: 2025-05 | K1: 2025-06 | L1: 2025-07 | M1: 2025-08 | N1: 2025-09 | O1: 2025-10 | P1: 2025-11 | Q1: 2025-12 | R1: acumulado
A2: PP-000 | B2: SIN IDENTIFICAR | C2: E000 | M2: 174.63 | N2: 180.84 | O2: 180.84 | P2: 180.84 | Q2: 180.84 | R2: =SUM(D2:Q2) -> 897.99
A3: PP-001 | B3: AJK ASOCIADOS SAC | C3: DEPA-1605 | F3: 0 | G3: 0 | H3: 0 | I3: 0 | J3: 0 | K3: 385.31 | L3: 382.13 | M3: 368.11 | N3: 378.78 | O3: 377.16 | P3: 370.23 | Q3: 377.02 | R3: =SUM(D3:Q3) -> 2638.74
A4: PP-002 | B4: ALBAN MALACHE CHABELI | C4: DEPA-612 | M4: 392.7 | N4: 404.17 | O4: 408.64 | P4: 387.14 | Q4: 395.44 | R4: =SUM(D4:Q4) -> 1988.09
A5: PP-003 | B5: RUIZ JAVIER ALEJANDRO | C5: DEPA-811 | M5: 173.01 | N5: 179.66 | O5: 178.54 | P5: 172.94 | Q5: 179.63 | R5: =SUM(D5:Q5) -> 883.78
A6: PP-004 | B6: ALEXANDER STRAHLE JURGEN | C6: DEPA-902 | M6: 379.5 | N6: 386.65 | O6: 385.04 | P6: 380.23 | Q6: 383.76 | R6: =SUM(D6:Q6) -> 1915.18
A7: PP-005 | B7: ALVA CUELLAR DUGLAS CONCEPCION | C7: DEPA-1205 | M7: 386.94 | N7: 419.89 | O7: 423.35 | P7: 403.2 | Q7: 410.58 | R7: =SUM(D7:Q7) -> 2043.96
A8: PP-006 | B8: ALVARADO BRINGAS MILUSKA CARLA | C8: DEPA-1001 | M8: 516.68 | N8: 531.16 | O8: 531.16 | P8: 531.16 | Q8: 534.14 | R8: =SUM(D8:Q8) -> 2644.3
A9: PP-007 | B9: ANTON ENICE | C9: DEPA-610 | F9: 0 | G9: 0 | H9: 0 | I9: 0 | J9: 0 | K9: 0 | L9: 324.29 | M9: 312.03 | N9: 327.24 | O9: 324.7 | P9: 306.74 | Q9: 318.57 | R9: =SUM(D9:Q9) -> 1913.57
A10: PP-008 | B10: APARCANA ROSADIO LUIS MIGUEL | C10: DEPA-606 | M10: 242.83 | N10: 255.6 | O10: 257.84 | P10: 254.32 | Q10: 251.45 | R10: =SUM(D10:Q10) -> 1262.04
A11: PP-009 | B11: ASTO VARGAS HANS PIERRE | C11: DEPA-1311 | M11: 181.74 | N11: 183.67 | O11: 183.15 | P11: 176.23 | Q11: 182.14 | R11: =SUM(D11:Q11) -> 906.93
A12: PP-010 | B12: AVENDAÑO SILVA MIRLEY JESUS | C12: ESTA-087 | F12: 0 | G12: 0 | H12: 0 | I12: 0 | J12: 0 | K12: 0 | L12: 80.52 | M12: 77.76 | N12: 80.52 | O12: 80.52 | P12: 80.52 | Q12: 80.52 | R12: =SUM(D12:Q12) -> 480.36
A13: PP-011 | B13: AVILA JOEL ANTONIO | C13: DEPA-804 | F13: 0 | G13: 0 | H13: 0 | I13: 0 | J13: 0 | K13: 0 | L13: 377.49 | M13: 357.07 | N13: 374.19 | O13: 365.88 | P13: 368.75 | Q13: 368.86 | R13: =SUM(D13:Q13) -> 2212.24
A14: PP-012 | B14: AYAQUE LARICO ISAAC ALFREDO | C14: DEPA-1602 | M14: 357.07 | N14: 370.03 | O14: 365.88 | P14: 371.62 | Q14: 365.88 | R14: =SUM(D14:Q14) -> 1830.48
A15: PP-013 | B15: BADA CARPIO OSCAR | C15: DEPA-101 | M15: 641.05 | N15: 654.98 | O15: 674.36 | P15: 613.96 | Q15: 624.98 | R15: =SUM(D15:Q15) -> 3209.33
A16: PP-014 | B16: HENDRICK OSCAR / HENDRICKLUISA | C16: DEPA-1101 | M16: 425.63 | N16: 440.75 | O16: 440.75 | P16: 440.75 | Q16: 440.75 | R16: =SUM(D16:Q16) -> 2188.63
A17: PP-015 | B17: BENITES CERNA CARLOS ENRIQUE | C17: DEPA-1006 | M17: 445.24 | N17: 447.3 | O17: 447.92 | P17: 441.54 | Q17: 440.26 | R17: =SUM(D17:Q17) -> 2222.26
A18: PP-016 | B18: BERTOLOTTO INVESTMENTS S.A.C | C18: DEPA-1703 | M18: 2056.59 | N18: 1268.22 | O18: 1264.37 | P18: 1099.17 | Q18: 1096.52 | R18: =SUM(D18:Q18) -> 6784.87
A19: PP-017 | B19: BLAS OLIVER LIDIA ROSALVA | C19: DEPA-1609 | M19: 306.42 | N19: 320.47 | O19: 332.24 | P19: 306.34 | Q19: 313.51 | R19: =SUM(D19:Q19) -> 1578.98
A20: PP-018 | B20: CALDERON MINCHOLA JUAN CARLOS | C20: DEPA-1401 | F20: 0 | G20: 0 | H20: 0 | I20: 0 | J20: 0 | K20: 456.23 | L20: 456.23 | M20: 445 | N20: 453.21 | O20: 453.52 | P20: 449.36 | Q20: 449.69 | R20: =SUM(D20:Q20) -> 3163.24
A21: PP-019 | B21: CANCINO APAZA MARYLIN MARYBEL | C21: DEPA-1504 | F21: 0 | G21: 0 | H21: 0 | I21: 0 | J21: 0 | K21: 369.75 | L21: 377.49 | M21: 360.81 | N21: 374.19 | O21: 378.65 | P21: 374.49 | Q21: 365.88 | R21: =SUM(D21:Q21) -> 2601.26
A22: PP-020 | B22: CANEDO TAPIA MANUEL HERNAN | C22: DEPA-1710 | M22: 411.66 | N22: 434.92 | O22: 434.56 | P22: 403.19 | Q22: 418.32 | R22: =SUM(D22:Q22) -> 2102.65
A23: PP-021 | B23: CAO DACHAO | C23: DEPA-1310 | M23: 365.78 | N23: 385.43 | O23: 382.69 | P23: 374.78 | Q23: 382.97 | R23: =SUM(D23:Q23) -> 1891.65
A24: PP-022 | B24: CARDENAS MORIANO HEVELYNE HILDA | C24: DEPA-1607 | F24: 0 | G24: 0 | H24: 0 | I24: 0 | J24: 0 | K24: 0 | L24: 333.9 | M24: 342.91 | N24: 341.92 | O24: 346.99 | P24: 331.64 | Q24: 332.52 | R24: =SUM(D24:Q24) -> 2029.88
A25: PP-023 | B25: CARDENAS MORIANO WOLFGAN ANGEL | C25: DEPA-1107 | F25: 0 | G25: 0 | H25: 0 | I25: 0 | J25: 0 | K25: 0 | L25: 328.03 | M25: 327.97 | N25: 341.92 | O25: 327.84 | P25: 323.03 | Q25: 335.5 | R25: =SUM(D25:Q25) -> 1984.29
A26: PP-024 | B26: CARMONA DIAZ MERY | C26: DEPA-1201 | M26: 950.48 | N26: 982.26 | O26: 994.95 | P26: 947.97 | Q26: 964.73 | R26: =SUM(D26:Q26) -> 4840.39
A27: PP-025 | B27: CARRASCO BEAS ALFREDO EDILBERTO | C27: DEPA-1306 | M27: 242.83 | N27: 251.45 | O27: 251.45 | P27: 251.45 | Q27: 251.45 | R27: =SUM(D27:Q27) -> 1248.63
A28: PP-026 | B28: CARRILLO GALLO EDSON | C28: DEPA-611 | F28: 0 | G28: 0 | H28: 0 | I28: 0 | J28: 0 | K28: 0 | L28: 180.18 | M28: 187.7 | N28: 197.87 | O28: 208.18 | P28: 188.79 | Q28: 194.25 | R28: =SUM(D28:Q28) -> 1156.97
A29: PP-027 | B29: CARRILLO PINEDA FERNANDO | C29: ESTA-140 | M29: 77.76 | N29: 80.52 | O29: 80.52 | P29: 80.52 | Q29: 80.52 | R29: =SUM(D29:Q29) -> 399.84
A30: PP-028 | B30: CASAS JOSE | C30: DEPA-1002 | M30: 401.88 | N30: 419.89 | O30: 416.96 | P30: 400.32 | Q30: 404.62 | R30: =SUM(D30:Q30) -> 2043.67
A31: PP-029 | B31: CASTILLA PEREZ CARMELA FERMINA | C31: DEPA-1204 | F31: 0 | G31: 0 | H31: 0 | I31: 0 | J31: 385.23 | K31: 401 | L31: 392.97 | M31: 379.48 | N31: 390.81 | O31: 397.81 | P31: 383.1 | Q31: 392.7 | R31: =SUM(D31:Q31) -> 3123.1
A32: PP-030 | B32: CASTRO ALMEIDA RAUL ARMANDO | C32: DEPA-1403 | F32: 0 | G32: 0 | H32: 0 | I32: 0 | J32: 0 | K32: 0 | L32: 396.84 | M32: 394.42 | N32: 403.27 | O32: 410.58 | P32: 388.84 | Q32: 389.72 | R32: =SUM(D32:Q32) -> 2383.67
A33: PP-031 | B33: CASTRO BARRERA ANITA MARITZA | C33: DEPA-407 | M33: 401.88 | N33: 415.74 | O33: 429.74 | P33: 394.58 | Q33: 398.66 | R33: =SUM(D33:Q33) -> 2040.6
A34: PP-032 | B34: SOLARI ATOCHE MARIA CECILIA | C34: DEPA-907 | F34: 0 | G34: 0 | H34: 0 | I34: 0 | J34: 0 | K34: 358.89 | L34: 324.06 | M34: 275.58 | N34: 285.36 | O34: 298.13 | P34: 285.36 | Q34: 306.22 | R34: =SUM(D34:Q34) -> 2133.6
A35: PP-033 | B35: CHAFLOQUE MORENO ALEXIS JHONNY | C35: DEPA-1312 | F35: 0 | G35: 0 | H35: 0 | I35: 0 | J35: 0 | K35: 0 | L35: 324.06 | M35: 312.92 | N35: 322.75 | O35: 330.06 | P35: 308.32 | Q35: 321.12 | R35: =SUM(D35:Q35) -> 1919.23
A36: PP-034 | B36: CHAVEZ JULCAHUANCA VANESSA | C36: DEPA-1111 | F36: 0 | G36: 0 | H36: 0 | I36: 0 | J36: 197.44 | K36: 195.43 | L36: 198.02 | M36: 189.65 | N36: 196.1 | O36: 196.68 | P36: 185.59 | Q36: 190.56 | R36: =SUM(D36:Q36) -> 1549.47
A37: PP-035 | B37: CHAVEZ TAGLE SISLEY | C37: DEPA-609 | F37: 0 | G37: 0 | H37: 0 | I37: 0 | J37: 0 | K37: 0 | L37: 182.54 | M37: 191.21 | N37: 191.7 | O37: 202.86 | P37: 185.28 | Q37: 188.81 | R37: =SUM(D37:Q37) -> 1142.4
A38: PP-036 | B38: CHAVEZ MYLADY | C38: DEPA-510 | F38: 0 | G38: 0 | H38: 0 | I38: 0 | J38: 0 | K38: 0 | L38: 307.88 | M38: 275.58 | N38: 335.45 | O38: 313.69 | P38: 300.13 | Q38: 303.3 | R38: =SUM(D38:Q38) -> 1836.03
A39: PP-037 | B39: CHIA ALEGRE JORGE WILLIAMS | C39: DEPA-202 | M39: 297.98 | N39: 297.83 | O39: 310.9 | P39: 296.84 | Q39: 300.26 | R39: =SUM(D39:Q39) -> 1503.81
A40: PP-038 | B40: CHIROQUE FLOR LOZANO | C40: DEPA-1011 | M40: 172.12 | N40: 184.66 | O40: 186.24 | P40: 178.33 | Q40: 182.5 | R40: =SUM(D40:Q40) -> 903.85
A41: PP-039 | B41: CISNEROS ISLA GLORIA LEONOR | C41: DEPO-160 | M41: 23.37 | N41: 23.37 | O41: 23.37 | P41: 23.37 | Q41: 23.37 | R41: =SUM(D41:Q41) -> 116.85
A42: PP-040 | B42: CORDERO VILCA PEDRO LUIS | C42: DEPA-1610 | M42: 374.56 | N42: 402.5 | O42: 401.16 | P42: 379.02 | Q42: 390.37 | R42: =SUM(D42:Q42) -> 1947.61
A43: PP-041 | B43: CORNEJO JORGE JOSE ADRIAN | C43: DEPA-104 | F43: 0 | G43: 0 | H43: 0 | I43: 0 | J43: 0 | K43: 0 | L43: 385.23 | M43: 379.48 | N43: 386.65 | O43: 397.81 | P43: 391.71 | Q43: 389.72 | R43: =SUM(D43:Q43) -> 2330.6
A44: PP-042 | B44: CORRECHER DEL TORO GURMENSINDA | C44: DEPA-503 | M44: 383.21 | N44: 390.81 | O44: 391.42 | P44: 380.23 | Q44: 386.74 | R44: =SUM(D44:Q44) -> 1932.41
A45: PP-043 | B45: CURAHUA SANCHEZ FLOR DE MARIA | C45: DEPA-105 | F45: 0 | G45: 0 | H45: 0 | I45: 0 | J45: 0 | K45: 0 | L45: 462.96 | M45: 867.1 | N45: 909.51 | O45: 927.38 | P45: 898.14 | Q45: 898.56 | R45: =SUM(D45:Q45) -> 4963.65
A46: PP-044 | B46: DE LA CRUZ DELGADO WALTER | C46: DEPA-410 | F46: 0 | G46: 0 | H46: 0 | I46: 0 | J46: 0 | K46: 0 | L46: 389.76 | M46: 383.29 | N46: 389.7 | O46: 393.21 | P46: 380.77 | Q46: 385.28 | R46: =SUM(D46:Q46) -> 2322.01
A47: PP-045 | B47: RUIZ FLOR DE MARIA | C47: DEPA-205 | M47: 379.48 | N47: 394.96 | O47: 397.81 | P47: 374.49 | Q47: 389.72 | R47: =SUM(D47:Q47) -> 1936.46
A48: PP-046 | B48: DE MATTEIS DANIELE | C48: DEPA-1509 | M48: 265.23 | N48: 272.22 | O48: 270.61 | P48: 265.8 | Q48: 263.37 | R48: =SUM(D48:Q48) -> 1337.23
A49: PP-047 | B49: DIAZ QUINTANA DAVID ENRIQUE | C49: DEPA-304 | F49: 0 | G49: 0 | H49: 0 | I49: 0 | J49: 0 | K49: 0 | L49: 416.19 | M49: 401.88 | N49: 415.74 | O49: 410.58 | P49: 383.1 | Q49: 371.84 | R49: =SUM(D49:Q49) -> 2399.33
A50: PP-048 | B50: DURANGO CHAVEZ OLGA KARINA | C50: DEPA-1210 | F50: 0 | G50: 0 | H50: 0 | I50: 0 | J50: 0 | K50: 0 | L50: 311.33 | M50: 308.12 | N50: 324.64 | O50: 319.96 | P50: 304.54 | Q50: 312.53 | R50: =SUM(D50:Q50) -> 1881.12
A51: PP-049 | B51: HARO CABALLERO CAROL ELIZABETH | C51: DEPA-904 | M51: 413.2 | N51: 401.66 | O51: 414.74 | P51: 409.29 | Q51: 410.06 | R51: =SUM(D51:Q51) -> 2048.95
A52: PP-050 | B52: ESPINOZA PACHECO ELBIA ELIZABETH | C52: DEPA-409 | M52: 172.54 | N52: 175.08 | O52: 183.7 | P52: 173.8 | Q52: 173.91 | R52: =SUM(D52:Q52) -> 879.03
A53: PP-051 | B53: ESTRADA DIANA | C53: DEPA-1102 | M53: 301.72 | N53: 310.29 | O53: 310.9 | P53: 299.71 | Q53: 300.26 | R53: =SUM(D53:Q53) -> 1522.88
A54: PP-052 | B54: FALCON RAMOS CAROLINA FRANCHESKA | C54: DEPA-707 | M54: 327.86 | N54: 318.6 | O54: 323.67 | P54: 308.32 | Q54: 324.1 | R54: =SUM(D54:Q54) -> 1602.55
A55: PP-053 | B55: FERRER MILAGROS | C55: DEPA-1004 | M55: 383.21 | N55: 411.58 | O55: 410.58 | P55: 385.97 | Q55: 395.68 | R55: =SUM(D55:Q55) -> 1987.02
A56: PP-054 | B56: FUENTES ALARCON PERVIS | C56: DEPA-604 | F56: 0 | G56: 0 | H56: 0 | I56: 0 | J56: 0 | K56: 0 | L56: 412.32 | M56: 386.95 | N56: 415.74 | O56: 410.58 | P56: 394.58 | Q56: 407.6 | R56: =SUM(D56:Q56) -> 2427.77
A57: PP-055 | B57: GAMERO OSCAR | C57: DEPA-1612 | M57: 398.15 | N57: 399.12 | O57: 410.58 | P57: 391.71 | Q57: 386.74 | R57: =SUM(D57:Q57) -> 1986.3
A58: PP-056 | B58: GARCIA ARCE ANDRES DANIEL | C58: DEPA-903 | F58: 0 | G58: 0 | H58: 0 | I58: 0 | J58: 0 | K58: 0 | L58: 373.62 | M58: 368.28 | N58: 382.5 | O58: 372.27 | P58: 374.49 | Q58: 386.74 | R58: =SUM(D58:Q58) -> 2257.9
A59: PP-057 | B59: GARCIA TEJADA NORMA YSABEL | C59: DEPA-1502 | M59: 297.98 | N59: 301.98 | O59: 381.14 | P59: 308.32 | Q59: 309.2 | R59: =SUM(D59:Q59) -> 1598.62
A60: PP-058 | B60: GARCIA JOSE | C60: DEPA-501 | M60: 429.4 | N60: 444.9 | O60: 447.2 | P60: 440.8 | Q60: 450 | R60: =SUM(D60:Q60) -> 2212.3
A61: PP-059 | B61: GARFIAS HURTADO MARISOL | C61: DEPA-1402 | F61: 0 | G61: 0 | H61: 0 | I61: 0 | J61: 485.1 | K61: 485.1 | L61: 488.97 | M61: 468.43 | N61: 487.95 | O61: 471.94 | P61: 466.49 | Q61: 476.2 | R61: =SUM(D61:Q61) -> 3830.18
A62: PP-060 | B62: GAVIDIA DIAZ ROSA TANIA | C62: ESTA-106 | F62: 0 | G62: 0 | H62: 0 | I62: 0 | J62: 0 | K62: 80.52 | L62: 80.52 | M62: 77.76 | N62: 80.52 | O62: 80.52 | P62: 80.52 | Q62: 80.52 | R62: =SUM(D62:Q62) -> 560.88
A63: PP-061 | B63: GHERSI GIURFA DANIEL DAVID | C63: DEPA-712 | F63: 0 | G63: 0 | H63: 0 | I63: 0 | J63: 0 | K63: 0 | L63: 396.65 | M63: 387.51 | N63: 402.66 | O63: 396.98 | P63: 383.7 | Q63: 395.24 | R63: =SUM(D63:Q63) -> 2362.74
A64: PP-062 | B64: GODOY ACOSTA NORA EULALIA | C64: DEPA-1003 | M64: 372.01 | N64: 390.81 | O64: 378.65 | P64: 377.36 | Q64: 383.76 | R64: =SUM(D64:Q64) -> 1902.59
A65: PP-063 | B65: GOMEZ BARTRA JOHANNA GORGETE | C65: DEPA-602 | F65: 0 | G65: 0 | H65: 0 | I65: 0 | J65: 0 | K65: 0 | L65: 373.62 | M65: 364.64 | N65: 374.19 | O65: 372.27 | P65: 370.62 | Q65: 371.84 | R65: =SUM(D65:Q65) -> 2227.18
A66: PP-064 | B66: GOMEZ VILLENA ROLANDO MARTIN | C66: DEPA-701 | M66: 727.75 | N66: 763.06 | O66: 770.06 | P66: 749.61 | Q66: 756.01 | R66: =SUM(D66:Q66) -> 3766.49
A67: PP-065 | B67: GONZALES VIDAL MIGUEL ANGEL | C67: DEPA-404 | F67: 0 | G67: 0 | H67: 0 | I67: 0 | J67: 0 | K67: 0 | L67: 389.1 | M67: 379.48 | N67: 386.65 | O67: 391.42 | P67: 377.36 | Q67: 383.76 | R67: =SUM(D67:Q67) -> 2307.77
A68: PP-066 | B68: GONZALES LUIS | C68: DEPA-312 | M68: 402.26 | N68: 417.86 | O68: 424.85 | P68: 394.68 | Q68: 412.48 | R68: =SUM(D68:Q68) -> 2052.13
A69: PP-067 | B69: LOCK GOVEA JOSE | C69: DEPA-406 | M69: 242.83 | N69: 251.45 | O69: 251.45 | P69: 254.32 | Q69: 254.43 | R69: =SUM(D69:Q69) -> 1254.48
A70: PP-068 | B70: GUERRERO ABARCA MONICA JULIE | C70: DEPA-307 | M70: 312.92 | N70: 318.6 | O70: 317.29 | P70: 308.32 | Q70: 312.18 | R70: =SUM(D70:Q70) -> 1569.31
A71: PP-069 | B71: GUERRERO GUERRERO JEAN MARCO | C71: DEPA-908 | M71: 187.48 | N71: 187.55 | O71: 183.7 | P71: 176.67 | Q71: 179.87 | R71: =SUM(D71:Q71) -> 915.27
A72: PP-070 | B72: GUERRERO GUERRERO KETY FAGNI | C72: DEPA-909 | F72: 0 | G72: 0 | H72: 0 | I72: 0 | J72: 0 | K72: 0 | L72: 182.54 | M72: 180.01 | N72: 179.24 | O72: 183.7 | P72: 179.54 | Q72: 179.87 | R72: =SUM(D72:Q72) -> 1084.9
A73: PP-071 | B73: GUERRERO JIMENEZ SERGIO | C73: DEPA-302 | M73: 294.25 | N73: 306.13 | O73: 317.29 | P73: 311.19 | Q73: 321.12 | R73: =SUM(D73:Q73) -> 1549.98
A74: PP-072 | B74: GUERRERO SERGIO | C74: DEPA-403 | F74: 0 | G74: 0 | H74: 0 | I74: 0 | J74: 0 | K74: 80.52 | L74: 80.52 | M74: 383.21 | N74: 411.6 | O74: 404.2 | P74: 391.7 | Q74: 392.7 | R74: =SUM(D74:Q74) -> 2144.45
A75: PP-073 | B75: GUIMARAY RICARDO | C75: DEPA-209 | M75: 165.07 | N75: 175.08 | O75: 170.93 | P75: 173.8 | Q75: 173.91 | R75: =SUM(D75:Q75) -> 858.79
A76: PP-074 | B76: GUTIERREZ GUERRERO YEISON MARTIN | C76: DEPA-1603 | M76: 368.27 | N76: 374.19 | O76: 378.65 | P76: 374.49 | Q76: 374.82 | R76: =SUM(D76:Q76) -> 1870.42
A77: PP-075 | B77: GUTIERREZ PECEROS ALBERTO | C77: DEPA-1302 | F77: 0 | G77: 0 | H77: 0 | I77: 0 | J77: 0 | K77: 0 | L77: 520.13 | M77: 502.27 | N77: 534.59 | O77: 505.81 | P77: 510.26 | Q77: 516.88 | R77: =SUM(D77:Q77) -> 3089.94
A78: PP-076 | B78: HAYA HIDALGO FERNANDO TEOBALDO | C78: DEPA-901 | F78: 0 | G78: 0 | H78: 0 | I78: 0 | J78: 0 | K78: 0 | L78: 456.23 | M78: 459.24 | N78: 469.83 | O78: 459.91 | P78: 463.71 | Q78: 485.45 | R78: =SUM(D78:Q78) -> 2794.37
A79: PP-077 | B79: HENOSTROZA DIAZ JULIAN | C79: DEPA-910 | M79: 394.36 | N79: 415.35 | O79: 430.34 | P79: 400.73 | Q79: 418.91 | R79: =SUM(D79:Q79) -> 2059.69
A80: PP-078 | B80: HERNAN MORALES DIEGO | C80: DEPA-810 | M80: 398.15 | N80: 424.02 | O80: 429.74 | P80: 394.58 | Q80: 404.62 | R80: =SUM(D80:Q80) -> 2051.11
A81: PP-079 | B81: HERRERA MENDOZA JEAN PIERRE | C81: DEPA-1206 | M81: 265.35 | N81: 274.77 | O81: 281.16 | P81: 274.82 | Q81: 277.75 | R81: =SUM(D81:Q81) -> 1373.85
A82: PP-080 | B82: HUANAY MARTINEZ FRANZ CESAR | C82: DEPA-310 | M82: 365.8 | N82: 382.39 | O82: 381.42 | P82: 373.21 | Q82: 380.25 | R82: =SUM(D82:Q82) -> 1883.07
A83: PP-081 | B83: HUANGAL KESSLER JOSEFINA | C83: DEPA-1511 | M83: 175.82 | N83: 179.56 | O83: 178.5 | P83: 175.35 | Q83: 176.66 | R83: =SUM(D83:Q83) -> 885.89
A84: PP-082 | B84: HUERTA HUERTA CARLA ALESSANDRA | C84: DEPA-1208 | M84: 168.8 | N84: 175.08 | O84: 177.32 | P84: 176.67 | Q84: 173.91 | R84: =SUM(D84:Q84) -> 871.78
A85: PP-083 | B85: INDUSTRIAS GENERALES SAC | C85: DEPA-1705 | F85: 0 | G85: 0 | H85: 0 | I85: 0 | J85: 0 | K85: 0 | L85: 80.52 | M85: 377.68 | N85: 410.72 | O85: 415.06 | P85: 392.97 | Q85: 402.01 | R85: =SUM(D85:Q85) -> 2078.96
A86: PP-084 | B86: INFANTES JHEYSON | C86: DEPA-1303 | F86: 0 | G86: 0 | H86: 0 | I86: 0 | J86: 0 | K86: 0 | L86: 381.36 | M86: 368.28 | N86: 374.19 | O86: 365.88 | P86: 371.62 | Q86: 368.86 | R86: =SUM(D86:Q86) -> 2230.19
A87: PP-085 | B87: PARI NUÑEZ LEONOR | C87: DEPA-512 | F87: 0 | G87: 0 | H87: 0 | I87: 0 | J87: 487.31 | K87: 466.41 | L87: 463.74 | M87: 407.07 | N87: 421.91 | O87: 422.41 | P87: 393.7 | Q87: 418.99 | R87: =SUM(D87:Q87) -> 3481.54
A88: PP-086 | B88: IZQUIERDO ALATA LIAM JUAN PEDRO | C88: DEPA-710 | M88: 389.14 | N88: 409.51 | O88: 404.03 | P88: 388.09 | Q88: 393.68 | R88: =SUM(D88:Q88) -> 1984.45
A89: PP-087 | B89: JARA CISNEROS RICHARD | C89: DEPA-1604 | F89: 0 | G89: 385.43 | H89: 404.78 | I89: 373.62 | J89: 381.36 | K89: 381.36 | L89: 373.62 | M89: 368.25 | N89: 386.65 | O89: 385.04 | P89: 385.97 | Q89: 368.86 | R89: =SUM(D89:Q89) -> 4194.94
A90: PP-088 | B90: JIMENEZ CARMEN | C90: DEPA-508 | F90: 0 | G90: 0 | H90: 0 | I90: 0 | J90: 0 | K90: 23.32 | L90: 194.25 | M90: 187.59 | N90: 194.25 | O90: 194.25 | P90: 199.99 | Q90: 194.25 | R90: =SUM(D90:Q90) -> 1187.9
A91: PP-089 | B91: JO RENZO | C91: DEPA-1212 | F91: 0 | G91: 0 | H91: 0 | I91: 0 | J91: 0 | K91: 0 | L91: 365.88 | M91: 360.8 | N91: 394.96 | O91: 423.35 | P91: 397.45 | Q91: 410.58 | R91: =SUM(D91:Q91) -> 2353.02
A92: PP-090 | B92: JURADO PAZ Y MIÑO VICTOR | C92: DEPA-703 | M92: 275.58 | N92: 285.36 | O92: 285.36 | P92: 288.23 | Q92: 285.36 | R92: =SUM(D92:Q92) -> 1419.89
A93: PP-091 | B93: JUSTO NIETO MILENA KATHERINE | C93: DEPA-1309 | M93: 254.03 | N93: 259.76 | O93: 276.99 | P93: 254.32 | Q93: 257.41 | R93: =SUM(D93:Q93) -> 1302.51
A94: PP-092 | B94: LA MADRID JOSE | C94: DEPA-1007 | M94: 375.74 | N94: 390.81 | O94: 397.81 | P94: 383.1 | Q94: 380.78 | R94: =SUM(D94:Q94) -> 1928.24
A95: PP-093 | B95: MENDOZA TERESA LAURA | C95: DEPA-1406 | F95: 0 | G95: 0 | H95: 0 | I95: 0 | J95: 0 | K95: 0 | L95: 255.32 | M95: 250.3 | N95: 259.76 | O95: 251.45 | P95: 262.93 | Q95: 251.45 | R95: =SUM(D95:Q95) -> 1531.21
A96: PP-094 | B96: LAURA MENDOZA YSELA ROCIO | C96: DEPA-1009 | M96: 261.5 | N96: 272.22 | O96: 270.61 | P96: 260.06 | Q96: 257.41 | R96: =SUM(D96:Q96) -> 1321.8
A97: PP-095 | B97: LEON PRISCILLA | C97: DEPA-1104 | M97: 294.25 | N97: 339.37 | O97: 342.83 | P97: 316.93 | Q97: 321.12 | R97: =SUM(D97:Q97) -> 1614.5
A98: PP-096 | B98: LIANG YANQIU | C98: DEPA-1505 | M98: 381.5 | N98: 390.96 | O98: 376.09 | P98: 367.03 | Q98: 368.33 | R98: =SUM(D98:Q98) -> 1883.91
A99: PP-097 | B99: LIZARZABURU PETROZZI MIKEL ARITZ | C99: DEPA-1304 | M99: 641.09 | N99: 653.11 | O99: 659.81 | P99: 660.74 | Q99: 673.43 | R99: =SUM(D99:Q99) -> 3288.18
A100: PP-098 | B100: LLANO QUISPE JOSE LUIS | C100: DEPA-1712 | F100: 0 | G100: 0 | H100: 0 | I100: 0 | J100: 0 | K100: 0 | L100: 304.71 | M100: 297.99 | N100: 306.13 | O100: 304.52 | P100: 302.58 | Q100: 300.26 | R100: =SUM(D100:Q100) -> 1816.19
...

Sheet saldos
A1: EDIFICIO MULTIFAMILIAR "PACIFIK OCEAN TOWER"
A2: Av. Bertolotto Negro 850 - San Miguel
A3: 20614642247
A4: Listado de morosos al 31/12/2025
A6: CODIGO | B6: PROPIETARIO(S) | C6: propiedad | D6: 2023 | E6: 2024 | F6: 2025-01 | G6: 2025-02 | H6: 2025-03 | I6: 2025-04 | J6: 2025-05 | K6: 2025-06 | L6: 2025-07 | M6: 2025-08 | N6: 2025-09 | O6: 2025-10 | P6: 2025-11 | Q6: 2025-12 | R6: acumulado | T6: ULTIMO MES DIC-2025 | U6: MESES ANTERIORES
A7: PP-000 | B7: SIN IDENTIFICAR | C7: E000 | D7: =cuotas_emitidas!D2-SUMIFS(ingresos!$D:$D,ingresos!$F:$F,saldos!$A7,ingresos!$G:$G,saldos!D$6) -> 0 | E7: =cuotas_emitidas!E2-SUMIFS(ingresos!$D:$D,ingresos!$F:$F,saldos!$A7,ingresos!$G:$G,saldos!E$6) -> 0 | F7: =cuotas_emitidas!F2-SUMIFS(ingresos!$D:$D,ingresos!$F:$F,saldos!$A7,ingresos!$G:$G,saldos!F$6) -> 0 | G7: =cuotas_emitidas!G2-SUMIFS(ingresos!$D:$D,ingresos!$F:$F,saldos!$A7,ingresos!$G:$G,saldos!G$6) -> 0 | H7: =cuotas_emitidas!H2-SUMIFS(ingresos!$D:$D,ingresos!$F:$F,saldos!$A7,ingresos!$G:$G,saldos!H$6) -> 0 | I7: =cuotas_emitidas!I2-SUMIFS(ingresos!$D:$D,ingresos!$F:$F,saldos!$A7,ingresos!$G:$G,saldos!I$6) -> 0 | J7: =cuotas_emitidas!J2-SUMIFS(ingresos!$D:$D,ingresos!$F:$F,saldos!$A7,ingresos!$G:$G,saldos!J$6) -> 0 | K7: =cuotas_emitidas!K2-SUMIFS(ingresos!$D:$D,ingresos!$F:$F,saldos!$A7,ingresos!$G:$G,saldos!K$6) -> 0 | ... Q7: =cuotas_emitidas!Q2-SUMIFS(ingresos!$D:$D,ingresos!$F:$F,saldos!$A7,ingresos!$G:$G,saldos!Q$6) -> 180.84 | R7: =SUM(D7:Q7) -> 897.99 | T7: =Q7 -> 180.84 | U7: =R7-T7 -> 717.15
A8: PP-001 | B8: AJK ASOCIADOS SAC | C8: DEPA-1605 | D8: =cuotas_emitidas!D3-SUMIFS(ingresos!$D:$D,ingresos!$F:$F,saldos!$A8,ingresos!$G:$G,saldos!D$6) -> 0 | E8: =cuotas_emitidas!E3-SUMIFS(ingresos!$D:$D,ingresos!$F:$F,saldos!$A8,ingresos!$G:$G,saldos!E$6) -> 0 | F8: =cuotas_emitidas!F3-SUMIFS(ingresos!$D:$D,ingresos!$F:$F,saldos!$A8,ingresos!$G:$G,saldos!F$6) -> 0 | G8: =cuotas_emitidas!G3-SUMIFS(ingresos!$D:$D,ingresos!$F:$F,saldos!$A8,ingresos!$G:$G,saldos!G$6) -> 0 | H8: =cuotas_emitidas!H3-SUMIFS(ingresos!$D:$D,ingresos!$F:$F,saldos!$A8,ingresos!$G:$G,saldos!H$6) -> 0 | I8: =cuotas_emitidas!I3-SUMIFS(ingresos!$D:$D,ingresos!$F:$F,saldos!$A8,ingresos!$G:$G,saldos!I$6) -> 0 | J8: =cuotas_emitidas!J3-SUMIFS(ingresos!$D:$D,ingresos!$F:$F,saldos!$A8,ingresos!$G:$G,saldos!J$6) -> 0 | K8: =cuotas_emitidas!K3-SUMIFS(ingresos!$D:$D,ingresos!$F:$F,saldos!$A8,ingresos!$G:$G,saldos!K$6) -> 0 | ... Q8: =cuotas_emitidas!Q3-SUMIFS(ingresos!$D:$D,ingresos!$F:$F,saldos!$A8,ingresos!$G:$G,saldos!Q$6) -> 377.02 | R8: =SUM(D8:Q8) -> 377.02 | T8: =Q8 -> 377.02 | U8: =R8-T8 -> 0
A9: PP-002 | B9: ALBAN MALACHE CHABELI | C9: DEPA-612 | D9: =cuotas_emitidas!D4-SUMIFS(ingresos!$D:$D,ingresos!$F:$F,saldos!$A9,ingresos!$G:$G,saldos!D$6) -> 0 | E9: =cuotas_emitidas!E4-SUMIFS(ingresos!$D:$D,ingresos!$F:$F,saldos!$A9,ingresos!$G:$G,saldos!E$6) -> 0 | F9: =cuotas_emitidas!F4-SUMIFS(ingresos!$D:$D,ingresos!$F:$F,saldos!$A9,ingresos!$G:$G,saldos!F$6) -> 0 | G9: =cuotas_emitidas!G4-SUMIFS(ingresos!$D:$D,ingresos!$F:$F,saldos!$A9,ingresos!$G:$G,saldos!G$6) -> 0 | H9: =cuotas_emitidas!H4-SUMIFS(ingresos!$D:$D,ingresos!$F:$F,saldos!$A9,ingresos!$G:$G,saldos!H$6) -> 0 | I9: =cuotas_emitidas!I4-SUMIFS(ingresos!$D:$D,ingresos!$F:$F,saldos!$A9,ingresos!$G:$G,saldos!I$6) -> 0 | J9: =cuotas_emitidas!J4-SUMIFS(ingresos!$D:$D,ingresos!$F:$F,saldos!$A9,ingresos!$G:$G,saldos!J$6) -> 0 | K9: =cuotas_emitidas!K4-SUMIFS(ingresos!$D:$D,ingresos!$F:$F,saldos!$A9,ingresos!$G:$G,saldos!K$6) -> 0 | ... Q9: =cuotas_emitidas!Q4-SUMIFS(ingresos!$D:$D,ingresos!$F:$F,saldos!$A9,ingresos!$G:$G,saldos!Q$6) -> 395.44 | R9: =SUM(D9:Q9) -> 395.44 | T9: =Q9 -> 395.44 | U9: =R9-T9 -> 0
A10: PP-003 | B10: RUIZ JAVIER ALEJANDRO | C10: DEPA-811 | D10: =cuotas_emitidas!D5-SUMIFS(ingresos!$D:$D,ingresos!$F:$F,saldos!$A10,ingresos!$G:$G,saldos!D$6) -> 0 | E10: =cuotas_emitidas!E5-SUMIFS(ingresos!$D:$D,ingresos!$F:$F,saldos!$A10,ingresos!$G:$G,saldos!E$6) -> 0 | F10: =cuotas_emitidas!F5-SUMIFS(ingresos!$D:$D,ingresos!$F:$F,saldos!$A10,ingresos!$G:$G,saldos!F$6) -> 0 | G10: =cuotas_emitidas!G5-SUMIFS(ingresos!$D:$D,ingresos!$F:$F,saldos!$A10,ingresos!$G:$G,saldos!G$6) -> 0 | H10: =cuotas_emitidas!H5-SUMIFS(ingresos!$D:$D,ingresos!$F:$F,saldos!$A10,ingresos!$G:$G,saldos!H$6) -> 0 | I10: =cuotas_emitidas!I5-SUMIFS(ingresos!$D:$D,ingresos!$F:$F,saldos!$A10,ingresos!$G:$G,saldos!I$6) -> 0 | J10: =cuotas_emitidas!J5-SUMIFS(ingresos!$D:$D,ingresos!$F:$F,saldos!$A10,ingresos!$G:$G,saldos!J$6) -> 0 | K10: =cuotas_emitidas!K5-SUMIFS(ingresos!$D:$D,ingresos!$F:$F,saldos!$A10,ingresos!$G:$G,saldos!K$6) -> 0 | ... Q10: =cuotas_emitidas!Q5-SUMIFS(ingresos!$D:$D,ingresos!$F:$F,saldos!$A10,ingresos!$G:$G,saldos!Q$6) -> 179.63 | R10: =SUM(D10:Q10) -> 179.63 | T10: =Q10 -> 179.63 | U10: =R10-T10 -> 0
A11: PP-004 | B11: ALEXANDER STRAHLE JURGEN | C11: DEPA-902 | D11: =cuotas_emitidas!D6-SUMIFS(ingresos!$D:$D,ingresos!$F:$F,saldos!$A11,ingresos!$G:$G,saldos!D$6) -> 0 | E11: =cuotas_emitidas!E6-SUMIFS(ingresos!$D:$D,ingresos!$F:$F,saldos!$A11,ingresos!$G:$G,saldos!E$6) -> 0 | F11: =cuotas_emitidas!F6-SUMIFS(ingresos!$D:$D,ingresos!$F:$F,saldos!$A11,ingresos!$G:$G,saldos!F$6) -> 0 | G11: =cuotas_emitidas!G6-SUMIFS(ingresos!$D:$D,ingresos!$F:$F,saldos!$A11,ingresos!$G:$G,saldos!G$6) -> 0 | H11: =cuotas_emitidas!H6-SUMIFS(ingresos!$D:$D,ingresos!$F:$F,saldos!$A11,ingresos!$G:$G,saldos!H$6) -> 0 | I11: =cuotas_emitidas!I6-SUMIFS(ingresos!$D:$D,ingresos!$F:$F,saldos!$A11,ingresos!$G:$G,saldos!I$6) -> 0 | J11: =cuotas_emitidas!J6-SUMIFS(ingresos!$D:$D,ingresos!$F:$F,saldos!$A11,ingresos!$G:$G,saldos!J$6) -> 0 | K11: =cuotas_emitidas!K6-SUMIFS(ingresos!$D:$D,ingresos!$F:$F,saldos!$A11,ingresos!$G:$G,saldos!K$6) -> 0 | ... Q11: =cuotas_emitidas!Q6-SUMIFS(ingresos!$D:$D,ingresos!$F:$F,saldos!$A11,ingresos!$G:$G,saldos!Q$6) -> 0 | R11: =SUM(D11:Q11) -> 0 | T11: =Q11 -> 0 | U11: =R11-T11 -> 0
A12: PP-005 | B12: ALVA CUELLAR DUGLAS CONCEPCION | C12: DEPA-1205 | D12: =cuotas_emitidas!D7-SUMIFS(ingresos!$D:$D,ingresos!$F:$F,saldos!$A12,ingresos!$G:$G,saldos!D$6) -> 0 | E12: =cuotas_emitidas!E7-SUMIFS(ingresos!$D:$D,ingresos!$F:$F,saldos!$A12,ingresos!$G:$G,saldos!E$6) -> 0 | F12: =cuotas_emitidas!F7-SUMIFS(ingresos!$D:$D,ingresos!$F:$F,saldos!$A12,ingresos!$G:$G,saldos!F$6) -> 0 | G12: =cuotas_emitidas!G7-SUMIFS(ingresos!$D:$D,ingresos!$F:$F,saldos!$A12,ingresos!$G:$G,saldos!G$6) -> 0 | H12: =cuotas_emitidas!H7-SUMIFS(ingresos!$D:$D,ingresos!$F:$F,saldos!$A12,ingresos!$G:$G,saldos!H$6) -> 0 | I12: =cuotas_emitidas!I7-SUMIFS(ingresos!$D:$D,ingresos!$F:$F,saldos!$A12,ingresos!$G:$G,saldos!I$6) -> 0 | J12: =cuotas_emitidas!J7-SUMIFS(ingresos!$D:$D,ingresos!$F:$F,saldos!$A12,ingresos!$G:$G,saldos!J$6) -> 0 | K12: =cuotas_emitidas!K7-SUMIFS(ingresos!$D:$D,ingresos!$F:$F,saldos!$A12,ingresos!$G:$G,saldos!K$6) -> 0 | ... Q12: =cuotas_emitidas!Q7-SUMIFS(ingresos!$D:$D,ingresos!$F:$F,saldos!$A12,ingresos!$G:$G,saldos!Q$6) -> 0 | R12: =SUM(D12:Q12) -> 0 | T12: =Q12 -> 0 | U12: =R12-T12 -> 0
A13: PP-006 | B13: ALVARADO BRINGAS MILUSKA CARLA | C13: DEPA-1001 | D13: =cuotas_emitidas!D8-SUMIFS(ingresos!$D:$D,ingresos!$F:$F,saldos!$A13,ingresos!$G:$G,saldos!D$6) -> 0 | E13: =cuotas_emitidas!E8-SUMIFS(ingresos!$D:$D,ingresos!$F:$F,saldos!$A13,ingresos!$G:$G,saldos!E$6) -> 0 | F13: =cuotas_emitidas!F8-SUMIFS(ingresos!$D:$D,ingresos!$F:$F,saldos!$A13,ingresos!$G:$G,saldos!F$6) -> 0 | G13: =cuotas_emitidas!G8-SUMIFS(ingresos!$D:$D,ingresos!$F:$F,saldos!$A13,ingresos!$G:$G,saldos!G$6) -> 0 | H13: =cuotas_emitidas!H8-SUMIFS(ingresos!$D:$D,ingresos!$F:$F,saldos!$A13,ingresos!$G:$G,saldos!H$6) -> 0 | I13: =cuotas_emitidas!I8-SUMIFS(ingresos!$D:$D,ingresos!$F:$F,saldos!$A13,ingresos!$G:$G,saldos!I$6) -> 0 | J13: =cuotas_emitidas!J8-SUMIFS(ingresos!$D:$D,ingresos!$F:$F,saldos!$A13,ingresos!$G:$G,saldos!J$6) -> 0 | K13: =cuotas_emitidas!K8-SUMIFS(ingresos!$D:$D,ingresos!$F:$F,saldos!$A13,ingresos!$G:$G,saldos!K$6) -> 0 | ... Q13: =cuotas_emitidas!Q8-SUMIFS(ingresos!$D:$D,ingresos!$F:$F,saldos!$A13,ingresos!$G:$G,saldos!Q$6) -> 534.14 | R13: =SUM(D13:Q13) -> 534.14 | T13: =Q13 -> 534.14 | U13: =R13-T13 -> 0
A14: PP-007 | B14: ANTON ENICE | C14: DEPA-610 | D14: =cuotas_emitidas!D9-SUMIFS(ingresos!$D:$D,ingresos!$F:$F,saldos!$A14,ingresos!$G:$G,saldos!D$6) -> 0 | E14: =cuotas_emitidas!E9-SUMIFS(ingresos!$D:$D,ingresos!$F:$F,saldos!$A14,ingresos!$G:$G,saldos!E$6) -> 0 | F14: =cuotas_emitidas!F9-SUMIFS(ingresos!$D:$D,ingresos!$F:$F,saldos!$A14,ingresos!$G:$G,saldos!F$6) -> 0 | G14: =cuotas_emitidas!G9-SUMIFS(ingresos!$D:$D,ingresos!$F:$F,saldos!$A14,ingresos!$G:$G,saldos!G$6) -> 0 | H14: =cuotas_emitidas!H9-SUMIFS(ingresos!$D:$D,ingresos!$F:$F,saldos!$A14,ingresos!$G:$G,saldos!H$6) -> 0 | I14: =cuotas_emitidas!I9-SUMIFS(ingresos!$D:$D,ingresos!$F:$F,saldos!$A14,ingresos!$G:$G,saldos!I$6) -> 0 | J14: =cuotas_emitidas!J9-SUMIFS(ingresos!$D:$D,ingresos!$F:$F,saldos!$A14,ingresos!$G:$G,saldos!J$6) -> 0 | K14: =cuotas_emitidas!K9-SUMIFS(ingresos!$D:$D,ingresos!$F:$F,saldos!$A14,ingresos!$G:$G,saldos!K$6) -> 0 | ... Q14: =cuotas_emitidas!Q9-SUMIFS(ingresos!$D:$D,ingresos!$F:$F,saldos!$A14,ingresos!$G:$G,saldos!Q$6) -> 318.57 | R14: =SUM(D14:Q14) -> 1913.57 | T14: =Q14 -> 318.57 | U14: =R14-T14 -> 1595
A15: PP-008 | B15: APARCANA ROSADIO LUIS MIGUEL | C15: DEPA-606 | D15: =cuotas_emitidas!D10-SUMIFS(ingresos!$D:$D,ingresos!$F:$F,saldos!$A15,ingresos!$G:$G,saldos!D$6) -> 0 | E15: =cuotas_emitidas!E10-SUMIFS(ingresos!$D:$D,ingresos!$F:$F,saldos!$A15,ingresos!$G:$G,saldos!E$6) -> 0 | F15: =cuotas_emitidas!F10-SUMIFS(ingresos!$D:$D,ingresos!$F:$F,saldos!$A15,ingresos!$G:$G,saldos!F$6) -> 0 | G15: =cuotas_emitidas!G10-SUMIFS(ingresos!$D:$D,ingresos!$F:$F,saldos!$A15,ingresos!$G:$G,saldos!G$6) -> 0 | H15: =cuotas_emitidas!H10-SUMIFS(ingresos!$D:$D,ingresos!$F:$F,saldos!$A15,ingresos!$G:$G,saldos!H$6) -> 0 | I15: =cuotas_emitidas!I10-SUMIFS(ingresos!$D:$D,ingresos!$F:$F,saldos!$A15,ingresos!$G:$G,saldos!I$6) -> 0 | J15: =cuotas_emitidas!J10-SUMIFS(ingresos!$D:$D,ingresos!$F:$F,saldos!$A15,ingresos!$G:$G,saldos!J$6) -> 0 | K15: =cuotas_emitidas!K10-SUMIFS(ingresos!$D:$D,ingresos!$F:$F,saldos!$A15,ingresos!$G:$G,saldos!K$6) -> 0 | ... Q15: =cuotas_emitidas!Q10-SUMIFS(ingresos!$D:$D,ingresos!$F:$F,saldos!$A15,ingresos!$G:$G,saldos!Q$6) -> 251.45 | R15: =SUM(D15:Q15) -> 251.45 | T15: =Q15 -> 251.45 | U15: =R15-T15 -> 0
A16: PP-009 | B16: ASTO VARGAS HANS PIERRE | C16: DEPA-1311 | D16: =cuotas_emitidas!D11-SUMIFS(ingresos!$D:$D,ingresos!$F:$F,saldos!$A16,ingresos!$G:$G,saldos!D$6) -> 0 | E16: =cuotas_emitidas!E11-SUMIFS(ingresos!$D:$D,ingresos!$F:$F,saldos!$A16,ingresos!$G:$G,saldos!E$6) -> 0 | F16: =cuotas_emitidas!F11-SUMIFS(ingresos!$D:$D,ingresos!$F:$F,saldos!$A16,ingresos!$G:$G,saldos!F$6) -> 0 | G16: =cuotas_emitidas!G11-SUMIFS(ingresos!$D:$D,ingresos!$F:$F,saldos!$A16,ingresos!$G:$G,saldos!G$6) -> 0 | H16: =cuotas_emitidas!H11-SUMIFS(ingresos!$D:$D,ingresos!$F:$F,saldos!$A16,ingresos!$G:$G,saldos!H$6) -> 0 | I16: =cuotas_emitidas!I11-SUMIFS(ingresos!$D:$D,ingresos!$F:$F,saldos!$A16,ingresos!$G:$G,saldos!I$6) -> 0 | J16: =cuotas_emitidas!J11-SUMIFS(ingresos!$D:$D,ingresos!$F:$F,saldos!$A16,ingresos!$G:$G,saldos!J$6) -> 0 | K16: =cuotas_emitidas!K11-SUMIFS(ingresos!$D:$D,ingresos!$F:$F,saldos!$A16,ingresos!$G:$G,saldos!K$6) -> 0 | ... Q16: =cuotas_emitidas!Q11-SUMIFS(ingresos!$D:$D,ingresos!$F:$F,saldos!$A16,ingresos!$G:$G,saldos!Q$6) -> 0 | R16: =SUM(D16:Q16) -> 3.34 | T16: =Q16 -> 0 | U16: =R16-T16 -> 3.34
A17: PP-010 | B17: AVENDAÑO SILVA MIRLEY JESUS | C17: ESTA-087 | D17: =cuotas_emitidas!D12-SUMIFS(ingresos!$D:$D,ingresos!$F:$F,saldos!$A17,ingresos!$G:$G,saldos!D$6) -> 0 | E17: =cuotas_emitidas!E12-SUMIFS(ingresos!$D:$D,ingresos!$F:$F,saldos!$A17,ingresos!$G:$G,saldos!E$6) -> 0 | F17: =cuotas_emitidas!F12-SUMIFS(ingresos!$D:$D,ingresos!$F:$F,saldos!$A17,ingresos!$G:$G,saldos!F$6) -> 0 | G17: =cuotas_emitidas!G12-SUMIFS(ingresos!$D:$D,ingresos!$F:$F,saldos!$A17,ingresos!$G:$G,saldos!G$6) -> 0 | H17: =cuotas_emitidas!H12-SUMIFS(ingresos!$D:$D,ingresos!$F:$F,saldos!$A17,ingresos!$G:$G,saldos!H$6) -> 0 | I17: =cuotas_emitidas!I12-SUMIFS(ingresos!$D:$D,ingresos!$F:$F,saldos!$A17,ingresos!$G:$G,saldos!I$6) -> 0 | J17: =cuotas_emitidas!J12-SUMIFS(ingresos!$D:$D,ingresos!$F:$F,saldos!$A17,ingresos!$G:$G,saldos!J$6) -> 0 | K17: =cuotas_emitidas!K12-SUMIFS(ingresos!$D:$D,ingresos!$F:$F,saldos!$A17,ingresos!$G:$G,saldos!K$6) -> 0 | ... Q17: =cuotas_emitidas!Q12-SUMIFS(ingresos!$D:$D,ingresos!$F:$F,saldos!$A17,ingresos!$G:$G,saldos!Q$6) -> 80.52 | R17: =SUM(D17:Q17) -> 241.56 | T17: =Q17 -> 80.52 | U17: =R17-T17 -> 161.04
A18: PP-011 | B18: AVILA JOEL ANTONIO | C18: DEPA-804 | D18: =cuotas_emitidas!D13-SUMIFS(ingresos!$D:$D,ingresos!$F:$F,saldos!$A18,ingresos!$G:$G,saldos!D$6) -> 0 | E18: =cuotas_emitidas!E13-SUMIFS(ingresos!$D:$D,ingresos!$F:$F,saldos!$A18,ingresos!$G:$G,saldos!E$6) -> 0 | F18: =cuotas_emitidas!F13-SUMIFS(ingresos!$D:$D,ingresos!$F:$F,saldos!$A18,ingresos!$G:$G,saldos!F$6) -> 0 | G18: =cuotas_emitidas!G13-SUMIFS(ingresos!$D:$D,ingresos!$F:$F,saldos!$A18,ingresos!$G:$G,saldos!G$6) -> 0 | H18: =cuotas_emitidas!H13-SUMIFS(ingresos!$D:$D,ingresos!$F:$F,saldos!$A18,ingresos!$G:$G,saldos!H$6) -> 0 | I18: =cuotas_emitidas!I13-SUMIFS(ingresos!$D:$D,ingresos!$F:$F,saldos!$A18,ingresos!$G:$G,saldos!I$6) -> 0 | J18: =cuotas_emitidas!J13-SUMIFS(ingresos!$D:$D,ingresos!$F:$F,saldos!$A18,ingresos!$G:$G,saldos!J$6) -> 0 | K18: =cuotas_emitidas!K13-SUMIFS(ingresos!$D:$D,ingresos!$F:$F,saldos!$A18,ingresos!$G:$G,saldos!K$6) -> 0 | ... Q18: =cuotas_emitidas!Q13-SUMIFS(ingresos!$D:$D,ingresos!$F:$F,saldos!$A18,ingresos!$G:$G,saldos!Q$6) -> 0 | R18: =SUM(D18:Q18) -> 0 | T18: =Q18 -> 0 | U18: =R18-T18 -> 0
... A210: PP-LAV | B210: LAVANDERIA PRONTOMATIK | C210: PP-LAV | D210: =cuotas_emitidas!D205-SUMIFS(ingresos!$D:$D,ingresos!$F:$F,saldos!$A210,ingresos!$G:$G,saldos!D$6) -> 0 | E210: =cuotas_emitidas!E205-SUMIFS(ingresos!$D:$D,ingresos!$F:$F,saldos!$A210,ingresos!$G:$G,saldos!E$6) -> 0 | F210: =cuotas_emitidas!F205-SUMIFS(ingresos!$D:$D,ingresos!$F:$F,saldos!$A210,ingresos!$G:$G,saldos!F$6) -> 0 | G210: =cuotas_emitidas!G205-SUMIFS(ingresos!$D:$D,ingresos!$F:$F,saldos!$A210,ingresos!$G:$G,saldos!G$6) -> 0 | H210: =cuotas_emitidas!H205-SUMIFS(ingresos!$D:$D,ingresos!$F:$F,saldos!$A210,ingresos!$G:$G,saldos!H$6) -> 0 | I210: =cuotas_emitidas!I205-SUMIFS(ingresos!$D:$D,ingresos!$F:$F,saldos!$A210,ingresos!$G:$G,saldos!I$6) -> 0 | J210: =cuotas_emitidas!J205-SUMIFS(ingresos!$D:$D,ingresos!$F:$F,saldos!$A210,ingresos!$G:$G,saldos!J$6) -> 0 | K210: =cuotas_emitidas!K205-SUMIFS(ingresos!$D:$D,ingresos!$F:$F,saldos!$A210,ingresos!$G:$G,saldos!K$6) -> 0 | ... Q210: =cuotas_emitidas!Q205-SUMIFS(ingresos!$D:$D,ingresos!$F:$F,saldos!$A210,ingresos!$G:$G,saldos!Q$6) -> 0 | R210: =SUM(D210:Q210) -> 437.12 | T210: =Q210 -> 0 | U210: =R210-T210 -> 437.12
D211: =SUM(D7:D210) -> 1099.8 | E211: =SUM(E7:E210) -> 3717.73 | F211: =SUM(F7:F210) -> 302.58 | G211: =SUM(G7:G210) -> 305.64 | H211: =SUM(H7:H210) -> 309.7 | I211: =SUM(I7:I210) -> 599.71 | J211: =SUM(J7:J210) -> 1716.01 | K211: =SUM(K7:K210) -> 2000.11 | ... R211: =SUM(R7:R210) -> 94395.33 | T211: =SUBTOTAL(9,T6:T208) -> 39699.6 | U211: =SUBTOTAL(9,U6:U208) -> 53889.75

Sheet recibo_newP
A1: EDIFICIO MULTIFAMILIAR "PACIFIK OCEAN TOWER"
A2: Av. Bertolotto Negro 850 - San Miguel
A3: 20614642247
A5: RECIBO MANTENIMIENTO | H5: cuota del mes | I5: =VLOOKUP($I$8,RESUMEN_mes!$A:$E,5,0) -> 349.6281
A7: Periodo | C7: Fecha emisión | E7: Fecha vencimiento | G7: Consumo agua (m3) | I7: Codigo Propietario
A8: 2026-enero | C8: 46030 | E8: 46044 | G8: =IFERROR(VLOOKUP($C$21,consumo_agua!$A$7:$X$203,22,0),0) -> 1 | I8: =$D$18 -> PP-202
A10: Titular 1 | C10: =VLOOKUP($I$8,calculo!$A:$B,2,0) -> PALOMINO CRISTIAN
A12: Titular 2
A14: Arrendatario
C18: CODIGO | D18: PP-202
C20: Predio | D20: % PARTICIPACIÓN | E20: VALOR CUOTA S/. | F20: AGUA CONSUMO S/. | G20: SUMA
C21: DEPA-1303 | D21: 0.0044974 | E21: 270.3657 | F21: 2.9752 | G21: 273.3409
C22: ESTA-133 | D22: 0.001269 | E22: 76.287204 | F22: 0 | G22: 76.287204
C23: Total general | D23: 0.0057664 | E23: 346.6529 | F23: 2.9752 | G23: 349.6281
A37: Informacion historica: | D37: abonos recibidos
A38: cuotas emitidas | D38: codigo | E38: PP-000 | H38: saldo por cobrar al mes anterior
A39: periodos ant. | B39: =VLOOKUP($I$8,cuotas_emitidas!$A$1:$E$206,4,0)+VLOOKUP($I$8,cuotas_emitidas!$A$1:$E$206,5,0) -> 0 | H39: periodos ant. | I39: =VLOOKUP($I$8,saldos!$A$6:$R$211,4,0)+VLOOKUP($I$8,saldos!$A$6:$R$211,5,0) -> 0
A40: 45658 | B40: =VLOOKUP($I$8,cuotas_emitidas!$A$1:$R$206,6,0) -> 0 | D40: FECHA ABONO | E40: IMPORTE RECIBIDO | H40: 45658 | I40: =VLOOKUP($I$8,saldos!$A$6:$R$211,6,0) -> 0
A41: 45689 | B41: =VLOOKUP($I$8,cuotas_emitidas!$A$1:$R$206,7,0) -> 0 | D41: 45870 | E41: 0 | H41: 45689 | I41: =VLOOKUP($I$8,saldos!$A$6:$R$211,7,0) -> 0
A42: 45717 | B42: =VLOOKUP($I$8,cuotas_emitidas!$A$1:$R$206,8,0) -> 0 | D42: Total general | E42: 0 | H42: 45717 | I42: =VLOOKUP($I$8,saldos!$A$6:$R$211,8,0) -> 0
A43: 45748 | B43: =VLOOKUP($I$8,cuotas_emitidas!$A$1:$R$206,9,0) -> 0 | H43: 45748 | I43: =VLOOKUP($I$8,saldos!$A$6:$R$211,9,0) -> 0
A44: 45778 | B44: =VLOOKUP($I$8,cuotas_emitidas!$A$1:$R$206,10,0) -> 0 | H44: 45778 | I44: =VLOOKUP($I$8,saldos!$A$6:$R$211,10,0) -> 0
A45: 45809 | B45: =VLOOKUP($I$8,cuotas_emitidas!$A$1:$R$206,11,0) -> 0 | H45: 45809 | I45: =VLOOKUP($I$8,saldos!$A$6:$R$211,11,0) -> 0
A46: 45839 | B46: =VLOOKUP($I$8,cuotas_emitidas!$A$1:$R$206,12,0) -> 0 | H46: 45839 | I46: =VLOOKUP($I$8,saldos!$A$6:$R$211,12,0) -> 0
A47: 45870 | B47: =VLOOKUP($I$8,cuotas_emitidas!$A$1:$R$206,13,0) -> 0 | H47: 45870 | I47: =VLOOKUP($I$8,saldos!$A$6:$R$211,13,0) -> 0
A48: 45901 | B48: =VLOOKUP($I$8,cuotas_emitidas!$A$1:$R$206,14,0) -> 0 | H48: 45901 | I48: =VLOOKUP($I$8,saldos!$A$6:$R$211,14,0) -> 0
A49: 45931 | B49: =VLOOKUP($I$8,cuotas_emitidas!$A$1:$R$206,15,0) -> 0 | H49: 45931 | I49: =VLOOKUP($I$8,saldos!$A$6:$R$211,15,0) -> 0
A50: 45962 | B50: =VLOOKUP($I$8,cuotas_emitidas!$A$1:$R$206,16,0) -> 0 | H50: 45962 | I50: =VLOOKUP($I$8,saldos!$A$6:$R$211,16,0) -> 0
A51: 45992 | B51: =VLOOKUP($I$8,cuotas_emitidas!$A$1:$R$206,17,0) -> 368.86 | H51: 45992 | I51: =VLOOKUP($I$8,saldos!$A$6:$R$211,17,0) -> 368.86
B52: =SUM(B39:B51) -> 368.86 | I52: =SUM(I39:I51) -> 368.86
A54: Recibo digital elaborado por: | H54: =IF($I$52<0,"*saldo a favor del propietario","-") -> -
A55: ALGORITMO ADMIN
